Workbook

Sheet ST公司
F1: 下一步 | H1: 退市概率
B2: 600136 | C2: 明诚 | D2: 湖北国企 | E2: 已经破除重组过了，正在优化资产负债表，目前收购了大股东的一个物业公司，估计是保壳用的。 | F2: 不知道装入什么资产 | G2: 干净壳 | H2: 低
B3: 600165 | C3: 宁科 | D3: 民营 | E3: 债务预期，可能要破产了 | F3: 破产 | H3: 中高
B4: 600190 | C4: 锦州港 | D4: 无控制人 | E4: 年报可能无法表示的意见，应收账款大量预期，违规担保 | F4: 强退 | H4: 高
B5: 600234 | C5: 科新发展 | D5: 民营 | E5: 2023年营收低于1亿。2024年预计可以摘帽营收大幅增加，利润转正 | F5: 摘帽 | G5: 干净壳 | H5: 低 | I5: 2023年年报带帽后大跌到5亿，然后触底后上涨
B6: 600243 | C6: 青海华鼎 | D6: 民营 | E6: 2024营收2.3亿不足3亿退市风险 | F6: 做大营收或利润或卖壳 | G6: 干净壳 | H6: 低 | I6: 大跌后可以抄底赌2025年摘帽
B7: 600287 | C7: 江苏舜天 | D7: 江苏国企 | E7: 前面多年财务造假，虚增收入，已经处罚完了 | F7: 摘帽 | G7: 干净壳 | H7: 低 | I7: 带帽后跌到10亿左右反弹
B8: 600289 | C8: 亿阳信通 | D8: 民营 | E8: 2023年年报无法表示意见、资金占用、违规担保，还有违规担保没解决 | F8: 解决担保问题 | H8: 低 | I8: 股价大涨过了，不用管
B9: 600358 | C9: 国旅联合 | D9: 江西国企 | E9: 2020年有几百万利润放错年份了，这个很好解决 | F9: 2026年可摘帽 | H9: 低 | I9: 跌停打开后反弹
B10: 600360 | C10: 华微电子 | D10: 民营 | E10: 2025年10月12前必须解决14亿的非经营资金占用问题，否则终止上市 | F10: 解决资产占用 | H10: 中 | I10: 占用有点多，2023年报披露后大跌到20亿反弹
B11: 600365 | C11: 通葡股份 | D11: 民营 | E11: 担保问题 | F11: 解决担保问题 | H11: 低
B12: 600381 | C12: 青海春天 | D12: 民营 | E12: 审计预测营收不足3亿，很多收入不符合常理，可能否定意见 | F12: 解决审计和营收 | G12: 干净壳
B13: 2289 | C13: 宇顺电子 | D13: 民营 | E13: 202308月大股东进入，现在需要保壳。正打算购买一些数据中心。 | F13: 保壳 | G13: 干净壳 | H13: 低 | I13: 已经大涨
B14: 600387 | C14: 海越能源 | D14: 银川国企 | E14: 2023年非标，2024又可能非标 | H14: 高
B15: 600462 | C15: 九有投资 | D15: 民营 | E15: 2023净资产为负，2024可能转正，但正被立案侦查。 | H15: 中
B16: 600568 | C16: 中珠医疗 | D16: 无控制人 | E16: 非经营资金占用5.6亿 | F16: 归还资金 | G16: 干净壳 | H16: 低
B17: 600599 | C17: 熊猫金控 | D17: 民营 | E17: 金融公司，小贷业务基本快没了。剩烟花业务了。2022-2023连续否定审计。业绩正的。 | F17: 解决历史问题 | G17: 干净壳 | H17: 低
B18: 600603 | C18: 广汇物流 | D18: 民营 | E18: 之前有小小的财务造假 | F18: 应该可以摘帽了 | H18: 低 | I18: 无投资价值了
B19: 600608 | C19: 宽频科技 | D19: 昆明国企 | E19: 原大股东资金占用3.4亿，已经10几年了，但原大股东已经没有偿还能力了。没有收入了，资产也很干净。2024年触发不足3亿退市风险。现大股东都10年了也没注入资产。 | F19: 做大营收或利润，注入资产 | G19: 干净壳 | H19: 低
B20: 2693 | C20: 双成药业 | D20: 民营 | E20: 收入不足。 本来要购买大股东的半导体资产，但最终终止了，因为跟有些交易方达不成一致。 | G20: 估值高 | H20: 中

Sheet 博弈记录
A1: 类型 | B1: 标的 | C1: 结果 | D1: 仓位 | E1: 收益 | F1: 买入日期 | G1: 最迟日期 | H1: 负债率 | I1: 转债规模 | J1: 现金 | K1: 转债现金比
A2: 不强赎 | B2: 金铜转债 | C2: 失败 | E2: -0.015 | F2: 20250731
A3: 年报延期 | B3: 天茂集团 | C3: 失败 | E3: -0.45
A4: 要约波动 | B4: 申科股份 | C4: 成功 | D4: 5000 | E4: 0.012 | F4: 20250721
A5: 要约波动 | B5: 申科股份 | C5: 成功 | D5: 10000 | E5: 0.01 | F5: 20250729
A6: 要约波动 | B6: 申科股份 | C6: 失败 | D6: 16000 | F6: 20250811
A7: 化债 | B7: 柳药集团 | G7: 20260112 | H7: 0.61 | I7: 8 | J7: 26 | K7: =I7/J7 -> 0.30769231
A8: 化债 | B8: 重庆建工 | C8: 失败 | D8: 10000 | F8: 20250811 | G8: 20251220 | H8: 0.9 | I8: 13 | J8: 40 | K8: =I8/J8 -> 0.325
A9: 化债 | B9: 烽火通信 | G9: 20251127 | H9: 0.63 | I9: 31 | J9: 39 | K9: =I9/J9 -> 0.79487179
A10: 化债 | B10: 鲁泰股份 | G10: 20260401 | H10: 0.28 | I10: 14 | J10: 30 | K10: =I10/J10 -> 0.46666667
A11: 化债 | B11: 利群股份 | C11: 失败 | G11: 20260401 | H11: 0.73 | I11: 13 | J11: 9 | K11: =I11/J11 -> 1.4444444
A12: 异议选择权 | B12: 海光信息 | C12: 成功 | D12: 27000 | E12: 0.036 | F12: 20250808
A13: 保壳 | B13: 清研 | G13: 20251231
A14: 保壳 | B14: 太和 | G14: 20251231
A15: 保壳 | B15: 凯鑫 | G15: 20251231
A16: 保壳 | B16: 海钦 | G16: 20251231
A17: 保壳 | B17: 海源 | G17: 20251231
A18: 保壳 | B18: 返利 | G18: 20251231
A19: 保壳 | B19: 威尔 | G19: 20251231
A20: 保壳 | B20: 艾艾 | G20: 20251231
A21: 保壳 | B21: 四通 | G21: 20251231
A22: 保壳 | B22: 亿通 | G22: 20251231
A23: 化债 | B23: 本钢板材 | C23: 失败 | G23: 20260629 | H23: 0.74 | I23: 56 | J23: 32 | K23: =I23/J23 -> 1.75

Sheet 摘帽
D1: 戴帽原因 | E1: 解决方法 | F1: 关键节点 | G1: 公布前市值 | H1: 公布前 | I1: 公布日 | J1: 摘帽当天 | K1: 第二天 | L1: 第三天
B2: 809 | C2: 和展能源 | D2: 2023亏损且收入不足1亿 | E2: 做大收入 | F2: 最低市值11亿，出现在20240424 20230830实控人变更为和展中达 | G2: 30 | H2: 翻倍 | J2: 高开低走 | K2: 0.0997 | L2: 0.0523
B3: 603023 | C3: 威帝 | D3: 2023亏损且收入不足1亿 | E3: 净利润正 | G3: 18 | H3: 翻倍 | I3: 涨停
B4: 688282 | C4: 理工导航 | D4: 2023年亏损且收入不足1亿 | E4: 收入做大 | F4: 20240403公告收购宇讯电子，1.2亿价款，宇讯电子收入7000万，利润1200万。 20240430带帽当天市值最低16亿。 20240605公告签定大额经营合同，1个多亿，年内交付，基本锁定摘帽。 20240830半年报显示业绩没有改善。 2241029三季报显示收入开始大涨。 20250117业绩预告显示收入满足1亿要求。 | G4: 40 | H4: 翻倍
B5: 600234 | C5: 科新发展 | D5: 2023年亏损且收入不足1亿 | E5: 做大收入和做正利润，实控人变更 | F5: 股价一直跌到20240611，晚上公告管理层增持计划。第二天开始股价反弹。最低市值5亿。 20240731公告实控人变更为连宗盛。股价继续上涨。 20240830半年报业绩没有改善。但公告新签合同2个多亿。 20240927公告出售广告子公司。 20241030三季报显示收入大涨。 20250125公告业绩预盈。 | G5: 18 | H5: 翻两倍 | I5: 0
B6: 600715 | C6: 文投控股 | D6: 2023净资产负、持续经营不确定性 | E6: 重整 | G6: 95 | H6: 涨50%
B7: 603879 | C7: 永悦科技 | D7: 2023内部否定审计 | G7: 18 | H7: 翻倍
B8: 603608 | C8: 天创时尚 | D8: 2023无法表示意见审计报告和否定意见内部审计 | E8: 解决相关事项 | G8: 21 | H8: 翻倍
B9: 603557 | C9: 起步股份 | D9: 2021年否定内部审计、2023年持续经营不确定性 | E9: 解决相关事项 | G9: 14 | H9: 0.7
B10: 506 | C10: 中润资源 | D10: 2023经营重大不确定性 | E10: 大股东为公司提供担保和借款 收回股权转让款 达成还款协议，解除账户冻结 聚焦黄金主业，增强经营能力 实控人变更为招远国企 | G10: 63 | H10: 7
B11: 2217 | C11: 合力泰 | D11: 2023净资产负、持续经营不确定性 | E11: 重整 | G11: 160 | H11: 1 | I11: -0.05
B12: 2310 | C12: 东方园林 | D12: 2023净资产负、持续经营不确定性 | E12: 重整 | G12: 121 | H12: 1 | I12: 0.03
B13: 2141 | C13: 贤丰控股 | D13: 2023亏损且收入不足1亿 2023否定内控报告： 1、1-2季度预收账款确认不当，说明收入相关内部控制有缺陷。 2、虚增收入成本，说明内部控制缺陷。 | E13: 靠覆铜板业务营收超过3亿 内部缺陷解决，前期会计差错纠正；批判相关人员 | G13: 22 | H13: 1 | I13: 0.05
B14: 2951 | C14: 金时科技 | D14: 2023年亏损且收入不足1亿 子公司四川金时印务有限公司实施停产已满3个月 | E14: 营收超过3亿 剥离停产的不良子公司 | F14: 2024年7月半年报预告时还没有摘帽的可能性，股价也一直跌到了这时候 20240822晚，公司发布公告出售停产子公司给关联方，总价3亿，股票开始涨停。 20241028三季报显示收入还只是有所提升，但离摘帽相差很远。 20241029、1114分别公告签订两项经营合同、总金额差不多3亿。储能相关业务。股价继续上涨。 20241231公告出售停产子公司完成。 20250125业绩预告，基本确定可以摘帽。 | G14: 32 | H14: 1 | I14: -0.05
B15: 525 | C15: 红太阳 | D15: 2023年否定内控报告 | E15: 非经营资金占用归还 对部分预付款项缺乏合理的商业理由和依据已完成整改 重整 | G15: 86 | H15: 0.2 | I15: -0.05
B16: 2259 | C16: 升达林业 | D16: 大股东违规担保 非经营资金占用 | E16: 解决相关事项 | G16: 23 | H16: 0.5 | I16: 0
B17: 989 | C17: 九芝堂 | D17: 2023年否定内控报告 | E17: 非经营资金3700万占用归还 | G17: 70 | H17: 0.3 | I17: 0.05
B18: 2052 | C18: 同洲电子 | D18: 2023亏损且收入不足1亿 经营不确定性 与大族控股有物业纠纷银行账户被冻结 | E18: 尝试重整没成功 开展算力服务电源业务改善收入和利润 投资者诉讼过期失效 | G18: 57 | H18: 7 | I18: 0.05 | J18: 0.05
B19: 300965 | C19: 恒宇信通 | D19: 2023亏损且收入不足1亿 经营不确定性，2023年一次性计提了前面8年的营业收入导致营收负数 | E19: 收入利润恢复正常 销售收入的审核价如果低于暂定价，就会计提营收，所以感觉很难确定以后不会作假 | G19: 22 | H19: 0.5 | I19: -0.04
B20: 600375 | C20: 汉马科技 | D20: 2023净资产负、持续经营不确定性 | E20: 重整 | G20: 90 | H20: 0.5 | I20: 0
B21: 2251 | C21: 步步高 | D21: 2023经营重大不确定性 | E21: 重整 | G21: 100 | H21: 0.7 | I21: 0.1 | J21: 0.1 | K21: 0.1 | L21: 0.1
B22: 600165 | C22: 宁科生物 | D22: 2023年无法表示意见的审计报告 | E22: 子公司重整中 退市风险解除了，但子公司持续经营能力未解除
B23: 300013 | C23: 新宁物流 | D23: 2023净资产负、持续经营不确定性 | E23: 定向增发融资优化财务状况，引入新大股东湖南国资
E33: =22*1.3 -> 28.6

Sheet 2023戴帽回测
B2: 名称 | C2: 戴帽当天收盘价 | D2: 戴帽当天打开跌停价 | E2: 2024年12月31收盘价 | F2: 申请摘帽当天开盘价 | G2: 摘帽当天开盘价 | H2: 戴帽当天到年底收益 | I2: 戴帽跌停打开到年底收益
B3: 恒宇信通 | C3: 27 | D3: 27 | E3: 35.81 | G3: 42.6 | H3: =E3/C3-1 -> 0.3262963 | I3: =E3/D3-1 -> 0.3262963
B4: 九芝堂 | C4: 8.1 | D4: 7.48 | E4: 7.96 | G4: 9.27 | H4: =E4/C4-1 -> -0.017283951 | I4: =E4/D4-1 -> 0.064171123
B5: 贤丰控股 | C5: 1.06 | D5: 0.96 | E5: 1.76 | F5: 2.15 | H5: =E5/C5-1 -> 0.66037736 | I5: =E5/D5-1 -> 0.83333333
B6: 合力泰 | C6: 1.22 | D6: 1.2 | E6: 2.39 | F6: 2.14 | H6: =E6/C6-1 -> 0.95901639 | I6: =E6/D6-1 -> 0.99166667
B7: 中润资源 | C7: 4.6 | D7: 2.75 | E7: 3.97 | H7: =E7/C7-1 -> -0.13695652 | I7: =E7/D7-1 -> 0.44363636
B8: 永悦科技 | C8: 4.84 | D8: 3.2 | E8: 3.84 | H8: =E8/C8-1 -> -0.20661157 | I8: =E8/D8-1 -> 0.2
B9: 天创时尚 | C9: 3.97 | D9: 2.92 | E9: 3.72 | H9: =E9/C9-1 -> -0.062972292 | I9: =E9/D9-1 -> 0.2739726
B10: 威帝股份 | C10: 2.75 | D10: 2.24 | E10: 2.74 | H10: =E10/C10-1 -> -0.0036363636 | I10: =E10/D10-1 -> 0.22321429
B11: 新宁物流 | C11: 1.95 | D11: 1.95 | E11: 3.47 | H11: =E11/C11-1 -> 0.77948718 | I11: =E11/D11-1 -> 0.77948718
B12: 天邦食品 | C12: 2.57 | D12: 2.32 | E12: 2.79 | H12: =E12/C12-1 -> 0.085603113 | I12: =E12/D12-1 -> 0.20258621
B13: 金时股份 | C13: 7.16 | D13: 7.16 | E13: 6.65 | H13: =E13/C13-1 -> -0.07122905 | I13: =E13/D13-1 -> -0.07122905
B14: 科新发展 | C14: 4.29 | D14: 2.71 | E14: 5.55 | H14: =E14/C14-1 -> 0.29370629 | I14: =E14/D14-1 -> 1.0479705
B15: 理工导航 | C15: 20.11 | D15: 20.11 | E15: 30.9 | H15: =E15/C15-1 -> 0.53654898 | I15: =E15/D15-1 -> 0.53654898
B16: 和展能源 | C16: 2.28 | D16: 2.28 | E16: 3.06 | H16: =E16/C16-1 -> 0.34210526 | I16: =E16/D16-1 -> 0.34210526
B17: 天沃科技 | C17: 3.56 | D17: 2.66 | E17: 3.83 | H17: =E17/C17-1 -> 0.075842697 | I17: =E17/D17-1 -> 0.43984962
B18: 汉马科技 | C18: 4.83 | D18: 5.04 | E18: 5.51 | H18: =E18/C18-1 -> 0.14078675 | I18: =E18/D18-1 -> 0.093253968
B19: 山东魔龙 | C19: 3.22 | D19: 2.87 | E19: 2.78 | H19: =E19/C19-1 -> -0.13664596 | I19: =E19/D19-1 -> -0.031358885

Sheet 退市
K1: 年份 | L1: 退市总数 | M1: ST退市 | N1: 其他退市 | O1: ST* | P1: 实际退市 | Q1: 退市率
B2: 代码 | C2: 公司 | D2: 原因 | E2: 详细 | F2: 思考 | G2: 确定日市值 | H2: 是否国资 | I2: 年底前收益 | K2: 2001 | L2: =M2+N2 -> 5 | M2: 3 | N2: 2
B3: 2750 | C3: 龙津药业 | D3: 财务退 | E3: 连续两年财务亏损营收不足。负债率是低的。 | F3: 为什么不卖壳呢？ | G3: 4 | H3: 否 | I3: 平 | K3: 2002 | L3: =M3+N3 -> 8 | M3: 7 | N3: 1
B4: 603963 | C4: 大理药业 | D4: 财务退 | E4: 连续两年财务亏损营收不足。负债率是低的。 | F4: 为什么不卖壳呢？ | G4: 2 | H4: 否 | I4: 负 | K4: 2003 | L4: =M4+N4 -> 4 | M4: 4
B5: 622 | C5: 恒立实业 | D5: 财务退 | E5: 2023年财务退市风险+保留意见审计报告+强调事项内控报告。 2024年无法及时披露年报 20250216实控人股份过户 | F5: 20240827实控人变更，总价1个亿，后面经过一系列努力还是没能挽救 | G5: 8 | H5: 否 | I5: 正 | K5: 2004 | L5: =M5+N5 -> 11 | M5: 8 | N5: 3
B6: 851 | C6: ST高鸿 | D6: 重大违法 | K6: 2005 | L6: =M6+N6 -> 12 | M6: 11 | N6: 1
B7: 600804 | C7: 鹏博士 | D7: 面值退 | E7: 2023年无法表示意见，资金占用，违规担保，立案调查。最终拒绝受理预重整。股价低于1元退市。2024继续无法表示意见。 | F7: 主要是非经营问题太多了。 | G7: 2 | I7: 平 | K7: 2006 | L7: =M7+N7 -> 11 | M7: 10 | N7: 1
B8: 627 | C8: 天茂集团 | D8: 主动退 | H8: 否 | K8: 2007 | L8: =M8+N8 -> 10 | M8: 6 | N8: 4
B9: 600837 | C9: 海通证券 | D9: 吸收合并 | H9: 是 | K9: 2008 | L9: =M9+N9 -> 2 | N9: 2
B10: 601519 | C10: 大智慧 | D10: 吸收合并 | H10: 否 | K10: 2009 | L10: =M10+N10 -> 6 | N10: 6
B11: 688041 | C11: 海光信息 | D11: 吸收合并 | H11: 是 | K11: 2010 | L11: =M11+N11 -> 4 | N11: 4
B12: 603213 | C12: 镇洋发展 | D12: 吸收合并 | H12: 是 | K12: 2011 | L12: =M12+N12 -> 3 | N12: 3
B13: 601989 | C13: 中国重工 | D13: 吸收合并 | H13: 是 | K13: 2012 | L13: =M13+N13 -> 4 | N13: 4
B14: 300379 | C14: ST东通 | D14: 重大违法 | K14: 2013 | L14: =M14+N14 -> 7 | M14: 2 | N14: 5
B15: 600200 | C15: ST苏吴 | D15: 重大违法 | K15: 2014 | L15: =M15+N15 -> 3 | M15: 1 | N15: 2
B16: 300280 | C16: ST紫天 | D16: 强制退 | E16: 拒绝整改，披露财务报告 | K16: 2015 | L16: =M16+N16 -> 10 | M16: 2 | N16: 8
B17: 920680 | C17: ST广道 | D17: 重大违法 | E17: 2018-2023连续虚假记载，2024定向发行股票说明书虚假记载 | I17: 负 | K17: 2016 | L17: =M17+N17 -> 2 | M17: 1 | N17: 1
B18: 600190 | C18: ST锦港 | D18: 重大违法 | E18: 连续三年虚假记载 | I18: 平 | K18: 2017 | L18: =M18+N18 -> 5 | M18: 2 | N18: 3
B19: 300208 | C19: ST中程 | D19: 财务退 | E19: 2023年净资产负，2024年保留意见审计报告和否定内控报告 | H19: 是 | I19: 平 | K19: 2018 | L19: =M19+N19 -> 6 | M19: 4 | N19: 2
B20: 600462 | C20: ST九有 | D20: 财务退 | E20: 2023年净资产负，2024无法表示意见的报告 | H20: 否 | I20: 平 | K20: 2019 | L20: =M20+N20 -> 12 | M20: 9 | N20: 3
B21: 584 | C21: ST工智 | D21: 财务退 | E21: 2023年无法表示意见，2024年又无法表示意见 | F21: 中间想购买资产来消除相关事项，但没成功 | H21: 否 | I21: 正 | K21: 2020 | L21: =M21+N21 -> 20 | M21: 17 | N21: 3 | O21: 98 | P21: 10 | Q21: =P21/O21 -> 0.10204082
B22: 600387 | C22: ST海越 | D22: 财务退 | E22: 2023年无法表示意见，2024年又无法表示意见 | G22: 4 | H22: 是 | I22: 平 | K22: 2021 | L22: =M22+N22 -> 23 | M22: 17 | N22: 6 | O22: 54 | P22: 22 | Q22: =P22/O22 -> 0.40740741
B23: 2336 | C23: ST人乐 | D23: 财务退 | E23: 2023年净资产负，2024年净资产负且无法表示意见 | F23: 公司中间也努力了，但是出售资产的进展没能在年末走完流程，因此无法确认收益。 | G23: 1.5 | H23: 是 | I23: 正 | K23: 2022 | L23: =M23+N23 -> 47 | M23: 42 | N23: 5 | O23: 45 | P23: 25 | Q23: =P23/O23 -> 0.55555556
B24: 603003 | C24: ST龙宇 | D24: 财务退 | E24: 2023年无法表示意见，2024年又无法表示意见 | F24: 大股东资金占用8亿未归还 20241216被立案调查 | H24: 否 | I24: 平 | K24: 2023 | L24: =M24+N24 -> 46 | M24: 43 | N24: 3 | O24: 53 | P24: 27 | Q24: =P24/O24 -> 0.50943396
B25: 600225 | C25: ST卓朗 | D25: 重大违法 | F25: 立案调查20240314-20141030 | H25: 是 | I25: 负 | K25: 2024 | L25: =M25+N25 -> 54 | M25: 46 | N25: 8 | O25: 57 | P25: 29 | Q25: =P25/O25 -> 0.50877193
B26: 601028 | C26: 玉龙股份 | D26: 主动退 | H26: 是 | K26: 2025 | L26: 32 | M26: 25 | N26: 6 | O26: 97 | P26: 20 | Q26: =P26/O26 -> 0.20618557
B27: 600705 | C27: 中航产融 | D27: 主动退 | H27: 是
B28: 300630 | C28: ST普利 | D28: 重大违法 | F28: 立案调查20240707-20250105 | G28: 4 | H28: 否 | I28: 负
B29: 600898 | C29: 国美通讯 | D29: 市值退 | E29: 市值低于5亿，2023年净资产负、收入低于1亿亏损 | F29: 立案调查20231206-20240415 公司没有努力 | G29: 2 | H29: 否 | I29: 正
B30: 600083 | C30: 博信股份 | D30: 市值退 | E30: 市值低于5亿，2023年净资产负，收入低于1亿亏损 | F30: 公司没有努力 | G30: 2 | H30: 是 | I30: 正
B31: 300108 | C31: ST吉药 | D31: 面值退 | E31: 2023年净资产负，打算重整，但没有拿到路条，最终股价低于1元 | F31: 2022-2023刚带帽摘帽，2024又带帽。实控人持股比例太低，可能没有动力。 | H31: 否 | I31: 负
B32: 603388 | C32: 元成 | D32: 重大违法 | H32: 否 | I32: 负
B33: 300344 | C33: 立方 | D33: 重大违法 | H33: 否
B34: 300391 | C34: ST长药 | D34: 重大违法 | H34: 否

Sheet 控股权变更
A1: 是否已经重组 | B1: 代码 | C1: 名称 | D1: 属性 | E1: 公告时间 | F1: 实际变更时间 | G1: 新实控人 | H1: 资产星级1-5，不知道默认0 | I1: 变更是否完成 | J1: 进展 | K1: 可转债 | L1: 代价（亿） | M1: 估值 | N1: 市值（亿） | O1: 营收（亿） | P1: 变更时资产规模（亿） | Q1: 净资产（亿） | R1: 实际注入间隔，单位年 | S1: 停牌时市值 | T1: 复牌后打开涨停市值
B2: 600684 | C2: 珠江股份 | D2: 广州国企 | E2: 20080101 | F2: =E2 -> 20080101 | G2: 广州国资，不知道会不会注入其他资产 | H2: 0 | I2: 完成 | J2: 剥离了房地产业务，目前剩物业业务和文体运营。 20241231，资产规模下降到17亿，原来330亿，负债从300下降到12亿 20250408，定向发行股票补充流动资金7.4亿。 20251014，发行2.5亿股，募资7.3亿 | L2: 0 | N2: 29 | O2: 16 | P2: 17 | Q2: 5 | R2: 0
A3: 是 | B3: 603268 | C3: 松发股份 | D3: 民营 | E3: 20181012 | G3: 恒力集团陈建华先生、范红卫女士夫妇29.91% | H3: 3 | I3: 完成 | J3: 一直到2024年都维持了原陶瓷业务，直到2024年再不进行资产注入就要触发不足3亿退市风险了，终于置入大股东的船舶资产，由于在变更控股权36个月之后进行的资产重组，不触发重组上市。。 | L3: 8.2 | N3: 20 | O3: 6 | P3: 12.6 | Q3: 7 | R3: 6 | S3: 17 | T3: 55
A4: 终止 | B4: 300489 | C4: 光智科技 | D4: 民营 | E4: 20190423 | G4: 朱世会6.8% 股份转让+表决权委托 | H4: 5 | I4: 完成 | J4: 20200224，定向发行4.5亿投资红外光学业务，子公司安徽中飞负责，注册资本9亿，与滁州市国资委一起 20200306，继续收购原实控人5%股份，花1亿 20200706，二股东王强转让股份给深圳富银城投 20200707，继续收购原实控人15%股份，花6.1亿 20210312，发行终止 20210430，红外业务开始开展，因投入过大，产生大量借款，负债率80%。 20211119，再次定向发行股票，7.2亿 20221206，又终止了 20230525，再次定向发行股票，5.5亿，发行价格一次比一次低 20240930，发布购买资产重大重组方案，收购实控人旗下先导电科，年净利润4亿，股价大涨3倍。这里终于知道为什么当时二股东要买股份了，肯定是深圳的相关企业。 20250627，终止。后卖给衢州发展，因为先导稀材在衢州投资了110亿项目。 | L4: 7.5 | N4: 26 | O4: 1.3 | P4: 5 | Q4: 3.7 | R4: 5 | S4: 31 | T4: 134
B5: 600076 | C5: 康欣新材 | D5: 国企 | E5: 20191111 | F5: =E5 -> 20191111 | G5: 无锡国资委，无锡建发受让15%+表决权委托13% | H5: 0 | I5: 完成 | J5: 20181218，首次转让9%，6.2亿 20191018，二次转让6%，4.3亿 20210202，向大股东定向发行募资8.5亿，发行后无锡建发占38% | L5: =6.2+4.3+8.5 -> 19 | N5: 40 | O5: 6 | P5: 71 | Q5: 40 | R5: 0
A6: 是 | B6: 301297 | C6: 富乐德 | D6: 民营 | E6: 20200101 | G6: 上海申和，无实际控制人 | H6: 4 | I6: 完成 | J6: 202410，购买大股东旗下资产富乐华，3亿净利润，定价65亿，大涨2倍。功率半导体覆铜陶瓷载板 | R6: 4 | S6: 66 | T6: 200
A7: 是 | B7: 603991 | C7: 至正股份 | D7: 民营 | E7: 20200521 | G7: 正信同创的王强受让27% ，旗下有深圳市国弘半导体发展有限公司，深圳市旅游（集团）股份有限公司。资本运作高手 | H7: 4 | I7: 完成 | J7: 王强还持有哈尔滨中飞新技术股份有限公司15%（20200724已经转让给基金公司），沈阳商业城股份有限公司5.6%（已退市） 20201128，向原大股东转让亏损资产，4.1亿 20201224，终止重大资产出售 20221109，收购苏州桔云科技51%股权，半导体湿法工艺设备，1.1亿 20241024，发行股份购买大股东的先进封装材料国际有限公司半导体资产并且置出原至正新材料资产，估值37亿，5个涨停。净资产39亿，净利润7000万 | L7: 6.2 | N7: 20 | O7: 3 | P7: 5.7 | Q7: 3.7 | R7: 4 | S7: 46 | T7: 74
B8: 603168 | C8: 莎普爱思 | D8: 民营 | E8: 20200530 | F8: =E8 -> 20200530 | G8: 养和投资的林弘立、林弘远受让7%，原来持有9%+表决权放弃，旗下有医院资产，天伦医院、明好医院 | H8: 2 | I8: 完成 | J8: 2021年内二次股份转让5% 20240924，大股东同业竞争延期3年，到2027年底，主要是医院还不符合注入的条件 | L8: 4.1 | N8: 30 | O8: 3.5 | P8: 16 | Q8: 13 | R8: 0
B9: 600738 | C9: 丽尚国潮 | D9: 国企 | E9: 20200725 | F9: =E9 -> 20200725 | G9: 丽水经开区的元明控股受让20% | H9: 0 | I9: 完成 | J9: 20210729，公开挂牌转让兰州红楼房地产开发有限公司股权，8亿 20211012，未能征集到受让方，终止出售 20250103，向大股东定向发行募资7.1亿，已终止 | L9: 10 | N9: 50 | O9: 6 | P9: 33 | Q9: 17 | R9: 0
B10: 601599 | C10: 浙文影业 | D10: 国企 | E10: 20200826 | F10: =E10 -> 20200826 | G10: 浙江财政厅的浙江文投受让表决权17%，旗下有很多影视公司，有同业竞争问题 | H10: 0 | I10: 完成 | J10: 20210608，定向发行募资6亿完成，浙江文投持有23%股份和16%的表决权 | L10: 6 | N10: 26 | O10: 17 | P10: 38 | Q10: 6 | R10: 0
B11: 600966 | C11: 博汇纸业 | D11: 民营 | E11: 20200828 | F11: =E11 -> 20200828 | G11: 金光纸业的黄志源股份转让28.81%，合计持有48%，外商独资。承诺6年内解决同业竞争问题。经查询，金光纸业2022年净资产740亿，净利润46亿；2023年净利润36亿 | H11: 1 | I11: 完成 | J11: 还没有注入过资产 | L11: 20 | N11: 65 | O11: 97 | P11: 193 | Q11: 48 | R11: 0
B12: 603306 | C12: 华懋科技 | D12: 民营 | E12: 20201020 | F12: =E12 -> 20201020 | G12: 袁晋清先生、林晖 不知道到底想干嘛 | H12: 0 | I12: 完成 | J12: 20230221，一致行动人宁波新点减持股份到5%以下。 20250522，购买华懋东阳子公司剩余股权。 | L12: 12 | N12: 60 | O12: 9.5 | P12: 27 | Q12: 24 | R12: 0
B13: 603223 | C13: 恒通股份 | D13: 国企 | E13: 20201119 | F13: =E13 -> 20201119 | G13: 龙口市东江街道南山村村民委员会的南山集团受让20%+表决权委托5%。旗下资产规模巨大，2020年净利润40亿。持有南山铝业44%，南山智尚科技股份有限公司67%，山东裕龙石化有限公司51%，石化公司规模很大 | H13: 3 | I13: 完成 | J13: 20220809，向南山集团定向发行募资24亿，占比41% 期间，陆续收购了大股东旗下一些港口资产 20240731，要约收购5%股份 | L13: 34 | N13: 50 | O13: 55 | P13: 19 | Q13: 13 | R13: 0
B14: 300211 | C14: 亿通科技 | D14: 民营 | E14: 20210204 | F14: =E14 -> 20210204 | G14: 黄汪，股份转让29.99%，旗下有安徽华米做健康监测设备，2024年末营收15亿，净利润8800万，净资产25亿。可能注入上市公司。 公司每季度财报都非常详实。 | H14: 3 | I14: 完成 | J14: 2021控股后，发展了传感器和芯片业务 | L14: 9.5 | N14: 24 | O14: 0.8 | P14: 5 | Q14: 4.6 | R14: 0
B15: 603159 | C15: 上海亚虹 | D15: 民营 | E15: 20210206 | F15: =E15 -> 20210206 | G15: 海南宁生旅游，孙林，29.99%，文旅公司 | H15: 1 | I15: 完成 | L15: 5 | N15: 21 | O15: 6.7 | P15: 6.4 | Q15: 4.6 | R15: 0
B16: 603110 | C16: 东方材料 | D16: 民营 | E16: 20210223 | F16: =E16 -> 20210223 | G16: 许广彬29.9% | H16: 0 | I16: 完成 | J16: 20250603，大股东股份被司法拍卖后只剩5%，基本无用了 | L16: 7.6 | N16: 22 | O16: 4 | P16: 8 | Q16: 6.5 | R16: 0
B17: 2857 | C17: 三晖电气 | D17: 民营 | E17: 20210420 | F17: =E17 -> 20210420 | G17: 上海长耘，胡坤，20%，不知道有什么资产 | H17: 0 | I17: 完成 | J17: 2023年开始涉猎储能设备 | L17: 4.5 | N17: 17 | O17: 2.2 | P17: 6.3 | Q17: 5.1 | R17: 0
B18: 603677 | C18: 奇精机械 | D18: 国企 | E18: 20210506 | F18: =E18 -> 20210506 | G18: 浙江宁波工投，宁波国资委，29.99% | H18: 0 | I18: 完成 | J18: 不知道什么资产 | L18: 8.8 | N18: 22 | O18: 15.6 | P18: 20.5 | Q18: 10 | R18: 0
B19: 603909 | C19: 建发合诚 | D19: 国企 | E19: 20211113 | F19: =E19 -> 20211113 | G19: 福建厦门益悦，厦门国资委16%，下面主要是房地产公司，也有一些其他的，建发集团下面很多 | H19: 0 | I19: 完成 | J19: 入驻后，发展了很大的建筑施工业务，收入规模做大了。 | L19: 5.4 | N19: 24 | O19: 8 | P19: 15 | Q19: 10 | R19: 0
B20: 600300 | C20: 维维股份 | D20: 国企 | E20: 20211127 | F20: =E20 -> 20211127 | G20: 江苏徐州市新盛投资控股集团有限公司，徐州国资委，29.99% | H20: 0 | I20: 完成 | J20: 20190801，转让17%给新盛集团，公司变更为无实际控制人 20200805，转让枝江酒业股权给江苏综艺控股集团，4.6亿 20211127，继续转让12%给新盛集团，变更为徐州国资委 20230429，江苏综艺为枝江酒业的欠款做担保 | L20: =9.5+9.1 -> 18.6 | N20: 48 | O20: 50 | P20: 67 | Q20: 30 | R20: 0
B21: 600645 | C21: 中源协和 | D21: 民营 | E21: 20211215 | F21: =E21 -> 20211215 | G21: 陈春梅、龚虹嘉原持有10%，受让表决权7%。生命健康领域投资人。知名资本大佬。同时6亿参与ST长药的重整 | H21: 0 | I21: 完成 | J21: 20231228大股东继续增持了一些股份，目前持有表决权25% | L21: 0 | N21: 100 | O21: 15 | P21: 50 | Q21: 35 | R21: 0
B22: 600222 | C22: 太龙药业 | D22: 国企 | E22: 20220125 | F22: =E22 -> 20220125 | G22: 河南郑州高新区国资委受让14% | H22: 0 | I22: 完成 | L22: 8 | N22: 56 | O22: 16 | P22: 37 | Q22: 17 | R22: 0
B23: 603903 | C23: 中持股份 | D23: 国企 | E23: 20220310 | F23: =E23 -> 20220310 | G23: 长江环保受让5%+定向发行后总共24%，无实际控制人 | H23: 0 | I23: 完成 | L23: 8 | N23: 15 | O23: 37 | P23: 13 | Q23: 0 | R23: 0
B24: 603458 | C24: 勘设股份 | D24: 国企 | E24: 20220329 | F24: =E24 -> 20220329 | G24: 贵州贵阳国资委23%，定向发行股份 | H24: 0 | I24: 已终止 | J24: 2024，发行获得通过，但一直未启动，估计要黄 | L24: 9.5 | N24: 23 | O24: 14 | P24: 58 | Q24: 31 | R24: 0
B25: 603922 | C25: 金鸿顺 | D25: 民营 | E25: 20220409 | F25: =E25 -> 20220409 | G25: 海南众德科技，刘栩29.99%，旗下物业和商业公司 | H25: 0 | I25: 完成 | J25: 2023年剥离了一些子公司 20241106，发行股份收购新思考马达公司，非大股东资产。2024净利润1亿。 | L25: 7.5 | M25: 25 | N25: 25 | O25: 5 | P25: 12.5 | Q25: 10 | R25: 0
B26: 600388 | C26: 龙净环保 | D26: 国企 | E26: 20220531 | F26: =E26 -> 20220531 | G26: 紫金矿业，股份转让15%+表决权委托10%。新能源平台 | H26: 1 | I26: 完成 | J26: 20221021，收购大股东旗下的一些新能源业务，4700万 20230721，定向发行股票15亿搞储能等项目 20231202，终止发行 都是自己新开一些新能源发电，感觉注入资产的量也不大 | L26: 17 | N26: 113 | O26: 113 | P26: 270 | Q26: 170 | R26: 0
B27: 300269 | C27: 联建光电 | D27: 民营 | E27: 20220907 | F27: =E27 -> 20220907 | G27: 广东南峰谭炜樑，环保和房地产公司 | H27: 1 | I27: 完成 | J27: 剥离了一些子公司，目前负债率还是太高 | L27: 2.1 | N27: 22 | O27: 12 | P27: 12 | Q27: 0.4 | R27: 0
B28: 603078 | C28: 江化微 | D28: 国企 | E28: 20221201 | F28: =E28 -> 20221201 | G28: 山东淄博财政局23.95%，股份转让+定向发行 | H28: 0 | I28: 完成 | L28: 14 | N28: 60 | O28: 5.6 | P28: 20 | Q28: 11 | R28: 0
B29: 603990 | C29: 麦迪科技 | D29: 国企 | E29: 20230105 | F29: =E29 -> 20230105 | G29: 皓祥控股，绵阳安州区国资委16% | H29: 0 | I29: 完成 | J29: 20250128，剥离光伏子公司给大股东，5.9亿，感觉有戴帽的风险 | L29: =3.3+2.2 -> 5.5 | M29: ================================================================== | N29: 34 | O29: 3 | P29: 16 | Q29: 13 | R29: 0
B30: 603088 | C30: 宁波精达 | D30: 国企 | E30: 20230110 | F30: =E30 -> 20230110 | G30: 通商集团，浙江宁波国资委29.99% | H30: 0 | I30: 完成 | J30: 20240430，发行股票购买无锡微研股权，3.6亿，非关联人公司。2个涨停不到 20250522，收购完成 | L30: 10 | M30: ST组合策略8只仓位8.7。 | N30: 33 | O30: 6.5 | P30: 13.4 | Q30: 6.4 | R30: 0
B31: 600243 | C31: 青海华鼎 | D31: 民营 | E31: 20230131 | F31: =E31 -> 20230131 | G31: 王封，股份很少，主要是一致行动人，感觉没什么意思 | H31: 0 | I31: 完成 | L31: 2 | M31: ================================================================== | N31: 17 | O31: 3.5 | P31: 10 | Q31: 7 | R31: 0
B32: 600193 | C32: 创兴资源 | D32: 民营 | E32: 20230401 | F32: =E32 -> 20230401 | G32: 华侨实业余增云受让23.9% | H32: 1 | I32: 完成 | J32: 20241109，余增云被杭州上城公安局立案，涉嫌集资诈骗。 20250530，余增云股份被司法拍卖 | L32: 5.4 | M32: 博重组策略3只仓位1.92。 | N32: 23 | O32: 2.6 | P32: 7 | Q32: 2.5 | R32: 0
B33: 603016 | C33: 新宏泰 | D33: 国企 | E33: 20230408 | F33: =E33 -> 20230408 | G33: 江苏无锡国资委，是原大股东减持后升级为大股东的 | H33: 0 | I33: 完成 | J33: 20200102，首次转让15%给无锡国资委 20201225，继续转让12%给无锡国资委 | L33: =3.3+4.4 -> 7.7 | M33: ================================================================== | N33: 24 | O33: 6 | P33: 10 | Q33: 8 | R33: 0
B34: 300536 | C34: 农尚环境 | D34: 民营 | E34: 20230616 | F34: =E34 -> 20230616 | G34: 林峰（公司总经理）20%，实控人过往有多年半导体从业经历，算力服务和显示驱动芯片。 | H34: 2 | I34: 完成 | J34: 已经在开展算力服务相关业务了 | L34: 7.1 | M34: 低估红利仓位10.85。 | N34: 42 | O34: 0.7 | P34: 10 | Q34: 6 | R34: 0
B35: 603136 | C35: 天目湖 | D35: 国企 | E35: 20230701 | F35: =E35 -> 20230701 | G35: 溧阳城发受让26%，溧阳人民政府 | H35: 0 | I35: 完成 | J35: 20211019，城发受让11.19% 20220719，城发受让8.7% 20230701，城发受让6.5% | L35: 11 | M35: =L35/0.26 -> 42.307692 | N35: 42 | O35: 4 | P35: 16 | Q35: 12 | R35: 0
B36: 603685 | C36: 晨丰科技 | D36: 民营 | E36: 20230801 | F36: =E36 -> 20230801 | G36: 丁闵受让20%+表决权放弃+定向发行，发行后占38% | H36: 1 | I36: 完成 | J36: 20230510，签订受让股票协议同时，向丁闵收购麒麟新能等电力公司。同时定向发行募资4.4亿 202309，收购资产完成，3.6亿，牛逼啊，相当于用大股东自己募资的钱买自己的公司，左右口袋互换，股票还多了。 20250410，定向发行获得批复 | K36: 是 | L36: 3.3 | N36: 17 | O36: 12 | P36: 36 | Q36: 12 | R36: 0
B37: 603196 | C37: 日播时尚 | D37: 民营 | E37: 20230901 | F37: =E37 -> 20230901 | G37: 上海阔元梁丰受让29.72% | H37: 1 | I37: 完成 | J37: 20230516，变更实控人的同时，收购新实控人的新能源电池正极材料资产，置出上市公司原服装资产。本次交易构成重组上市，10个涨停。 20231106，终止重大资产置换。重组上市太难了。 20241101，发行股份购买茵地乐71%股权，20亿，锂电池粘结剂，不是大股东的资产，但向大股东募集资金。2024年净利润2亿。6个涨停。 20250520，向原大股东转让日播致胜子公司，1.3亿 | L37: 7.1 | N37: 22 | O37: 10 | P37: 12 | Q37: 7 | R37: 0
B38: 600540 | C38: 新赛股份 | D38: 国企 | E38: 20230905 | F38: =E38 -> 20230905 | G38: 中新建物流，新疆生产建设兵团国资委29.16%，物流资产整合 | H38: 1 | I38: 完成 | L38: 7.3 | N38: 23 | O38: 13 | P38: 26 | Q38: 7 | R38: 0
B39: 603578 | C39: 三星新材 | D39: 民营 | E39: 20230906 | F39: =E39 -> 20230906 | G39: 金玺泰有限公司受让14.15%+定向发行，金银山 | H39: 1 | I39: 完成 | J39: 20230628，公司向金银山实控国华金泰增资4000万，控股。主要是做光伏玻璃的。 20250320，发行股票5.6亿得到批复，等待发行 2023-2024股东资产大幅增加，就是国华金泰的业务导致，刚好赶上下行期。 | L39: 5.25 | N39: 37 | O39: 10 | P39: 27 | Q39: 12 | R39: 0
B40: 603778 | C40: 国晟科技 | D40: 民营 | E40: 20230908 | F40: =E40 -> 20230908 | G40: 国晟能源，吴君、高飞先转让8%，2.1亿，又转让8%，4.1亿。电力行业 | H40: 0 | I40: 完成 | J40: 20240601，继续定向发行5.4亿 | L40: 6.4 | N40: 40 | O40: 21 | P40: 32 | Q40: 14 | R40: 0
B41: 603038 | C41: 华立股份 | D41: 民营 | E41: 20231108 | F41: =E41 -> 20231108 | G41: 安徽洪典资本何全洪受让25%，里面有地方国资委的影子 | H41: 0 | I41: 完成 | J41: 20240323，收购尚源智能（污水处理设备）51%股权，同时投资郑州智能制造及大数据平台项目10亿 20240823，向关联方转让东莞市宏源复合材料有限公司子公司，1.3亿，总资产4亿 20240824，尚源智能审计报告，净资产2亿，净利润2000万。全部权益价值7亿在，增值5亿。这估值高太多了吧。 20241011，受大盘影响，沾上华为鸿蒙概念，12个涨停 20241015，转让子公司成功，2.8亿 20241107，收购尚源智能完成工商变更 | L41: 7.5 | N41: 30 | O41: 7 | P41: 20 | Q41: 13 | R41: 0
A42: 是 | B42: 600720 | C42: 中交设计 | D42: 国企 | E42: 20231201 | G42: 中国交投54% | H42: 1 | I42: 完成 | J42: 主要是原祁连山水泥股份通过与中国交投置换资产的方式借壳上市，这是一起成功的借壳上市案例，差额资产120亿左右.从20220512发起，到核准历时1年半 | L42: 120 | N42: 110 | O42: 76 | P42: 116 | Q42: 80 | R42: 1 | S42: 110 | T42: 150
B43: 600136 | C43: 当代明诚 | D43: 湖北国资 | E43: 20231220 | F43: =E43 -> 20231220 | G43: 重整中变更为联投城运，城市垃圾运营，湖北国资委。2022年净资产6.6亿，营收6.2亿 | H43: 1 | I43: 完成 | J43: 正在优化资产负债表 20240925，收购大股东的清能碧桂园物业公司51%股权 20250522，出售子公司时光传媒 | L43: 4 | N43: 45 | O43: 5.2 | P43: 7 | Q43: 4.4 | R43: 0
B44: 2476 | C44: 宝莫股份 | D44: 民营 | E44: 20240106 | F44: =E44 -> 20240106 | G44: 罗小林、韩明夫妇 股份转让15% 旗下主要是工程建筑，宏凌实业2022年净利润4亿，净资产10亿，2023年净利润2亿 | H44: 1 | I44: 完成 | J44: 202407想定向发行20%股份的 20250423，终止发行 | L44: 4.5 | N44: 27 | O44: 3.8 | P44: 9.6 | Q44: 9.5 | R44: 0
B45: 600172 | C45: 黄河旋风 | D45: 国企 | E45: 20240118 | F45: =E45 -> 20240118 | G45: 许昌财政局受让9.36%，原来有6.81% | H45: 0 | I45: 完成 | L45: 4.75 | N45: 50 | O45: 15 | P45: 90 | Q45: 25 | R45: 0
B46: 603329 | C46: 上海雅仕 | D46: 国企 | E46: 20240205 | F46: =E46 -> 20240205 | G46: 湖北国资委，湖北国贸26% | H46: 0 | I46: 完成 | L46: 7.2 | N46: 28 | O46: 25 | P46: 23 | Q46: 12 | R46: 0
B47: 600753 | C47: 庚星股份 | D47: 民营 | E47: 20240320 | F47: =E47 -> 20240320 | G47: 钟仁海司法拍卖受让24%，有鸿基石化股份公司，2023净资产12亿，净利润140万。 | H47: 1 | I47: 完成 | J47: 2025戴帽，净资产负了。大股东一直在处理各种问题，还挺有能力的，搞定了二股东。大股东还有浙江华泓新材料有限公司 鸿基石化2024净利润5000万，净资产12亿 202506，大股东增持了股份 | L47: 3.9 | N47: 16 | O47: 4 | P47: 4.6 | Q47: 2.3 | R47: 0
B48: 600844 | C48: 丹化科技/金煤科技 | D48: 民营 | E48: 20240401 | F48: =E48 -> 20240401 | G48: 北京中泽控股于泽国15% 铁合金、炭素、大黑山钼业、吉恩镍业（退市三板吉恩5） | H48: 5 | I48: 完成 | J48: 中泽控股在2018年对昊融集团、大黑山钼业、吉恩镍业的破产重整中作为产业投资人进入的。出资21亿。 公开查询，大黑山钼业2023净资产29亿，收入20亿，净利润8亿 20240722，向大股东中泽定向发行募资5.6亿，完成后控股34%，巩固控股权 永杉锂业、金钼股份是大黑山的客户 发行股份获批 | L48: 4.9 | M48: =L48/0.15 -> 32.666667 | N48: 28 | O48: 8.6 | P48: 14.6 | Q48: 8 | R48: 0
B49: 688550 | C49: 瑞联新材 | D49: 民营 | E49: 20240511 | F49: =E49 -> 20240511 | G49: 青岛开投集团 | H49: 0 | I49: 未完成 | J49: 原大股东反悔了，还在打官司
B50: 600892 | C50: 大晟文化 | D50: 国企 | E50: 20240514 | F50: =E50 -> 20240514 | G50: 唐山文旅，唐山市国资委受让17%，应该是旅游资产 | H50: 2 | I50: 完成 | J50: 唐山文旅2023净资产54亿，净利润估计2亿 | L50: 7.1 | N50: 42 | O50: 2.7 | P50: 3 | Q50: 1.6 | R50: 0
B51: 601700 | C51: 风范股份 | D51: 国企 | E51: 20240515 | F51: =E51 -> 20240515 | G51: 唐山金控受让12,67%，河北唐山国资委，后面还要受让17%的股份。原大股东放弃表决权 | H51: 0 | I51: 完成 | L51: 7.4 | N51: 58 | O51: 25 | P51: 77 | Q51: 30 | R51: 0
B52: 603300 | C52: 华铁应急 | D52: 国企 | E52: 20240725 | F52: =E52 -> 20240725 | G52: 河南国资委13.96% | H52: 0 | I52: 完成 | L52: 20 | N52: 142 | O52: 44 | P52: 200 | Q52: 65 | R52: 0
B53: 600234 | C53: 科新发展 | D53: 民营 | E53: 20240731 | F53: =E53 -> 20240731 | G53: 连宗盛，做股权投资的。 | H53: 0 | I53: 完成 | J53: 20230902，原实控人将海派德高盛合伙份额转让给连宗盛，1.7亿。占公司股份10% 20240731，原实控人继续转让科新实业给连宗盛，占17.88%，2亿，本次转让价格几乎腰斩 | L53: 3.7 | N53: 12 | O53: 2 | P53: 8.7 | Q53: 5 | R53: 0
B54: 600615 | C54: 丰华股份 | D54: 民营 | E54: 20240830 | F54: =E54 -> 20240830 | G54: 东方鑫源龚大兴29.99%，通过原控制股东的重整获得。汽车、摩托车零部件 | H54: 2 | I54: 完成 | J54: 20241122，实控人无偿赠送重庆鑫源农机股份有限公司51%股权给上市公司，价值1.5亿，2023净利润1700万。小型收割机、微耕机全国第一，全球第三。 公开查询，东方鑫源2023净资产40亿，净利润3.5亿，收入98亿 | L54: 7.4 | N54: 20 | O54: 1.8 | P54: 12 | Q54: 8 | R54: 0
B55: 601933 | C55: 永辉超市 | D55: 民营 | E55: 20240924 | F55: =E55 -> 20240924 | G55: 名创优品实控人受让29.4%，但只是第一大股东 | H55: 0 | I55: 未完成 | J55: 这个公司太垃圾了，什么时候转让股份完成的公告都没有，突然就看到骏山国际变大股东了。 拉黑
B56: 603887 | C56: 城地香江 | D56: 国企 | E56: 20241015 | F56: =E56 -> 20241015 | G56: 中电智算定向发行23% | H56: 1 | I56: 未完成 | J56: 20241015，向中电智算定向发行募资6亿，发行完成后实控人变更为国务院国资委 | L56: 6 | N56: 45 | O56: 16 | P56: 80 | Q56: 36 | R56: 0
B57: 603188 | C57: 亚邦股份 | D57: 国企 | E57: 20241029 | F57: =E57 -> 20241029 | G57: 国经集团，常州武进国资办抵债20%=司法拍卖8.8%，一共29.64% | H57: 0 | I57: 完成 | J57: 20241011，国经集团司法拍卖获得8.8% | L57: 4 | N57: 14 | O57: 7 | P57: 15 | Q57: 7 | R57: 0
B58: 603955 | C58: 大千生态 | D58: 民营 | E58: 20241123 | F58: =E58 -> 20241123 | G58: 江苏步步高，张源，18%。 两个酒公司，1个房地产置业公司，同时还是光一退的一致行动人 | H58: 0 | I58: 完成 | L58: 3.6 | N58: 13 | O58: 1.1 | P58: 24 | Q58: 18 | R58: 0
B59: 600584 | C59: 长电科技 | D59: 国企 | E59: 20241130 | F59: =E59 -> 20241130 | G59: 中国华润22.53% | H59: 0 | I59: 完成 | J59: 变更时，华润集团承诺5年内解决与华润微的同业竞争，感觉吸收合并的可能性大 | L59: 120 | N59: 540 | O59: 300 | P59: 540 | Q59: 300 | R59: 0
B60: 603399 | C60: 永杉锂业 | D60: 民营 | E60: 20241211 | F60: =E60 -> 20241211 | G60: 永荣致胜的吴华新通过司法拍卖19.9%，福建永荣集团，化工新材料，资产规模大，但详细不详 | H60: 1 | I60: 完成 | J60: 20250516，向大股东定向发行募资5.6亿 | L60: 8 | N60: 40 | O60: 59 | P60: 36 | Q60: 17 | R60: 0
B61: 603920 | C61: 世运电路 | D61: 国企 | E61: 20241217 | F61: =E61 -> 20241217 | G61: 顺德区国资委受让25.9%，顺控集团，自来水和垃圾焚烧业务 | H61: 1 | I61: 完成 | L61: 34.4 | N61: 132 | O61: 50 | P61: 90 | Q61: 67 | R61: 0
B62: 603656 | C62: 泰禾智能 | D62: 民营 | E62: 20241219 | F62: =E62 -> 20241219 | G62: 阳光能源旗下阳光新能源曹仁贤受让10%+表决权委托+表决权放弃，新能源发电 | H62: 2 | I62: 完成 | J62: 20241017签订股权转让协议，转让价格24/股，溢价100%，9个涨停 第二笔股份转让5.8%预计在20251231解除限售前完成 第三笔股份转让4.34%预计在20261231解除限售前完成 公开信息，2023阳光新能源净资产78亿，净利润11亿 20250408，大股东增持1.3% 不知道为什么要选这个公司，主营业务毫无关联 | L62: 4.5 | N62: 24 | O62: 5.6 | P62: 16 | Q62: 13 | R62: 0
B63: 300807 | C63: 天迈科技 | D63: 民营 | E63: 20250107 | F63: 20260106 | G63: 启明基金邝子平26.1%，股权投资的。 | H63: 0 | I63: 完成 | L63: 5.4 | M63: =L63/0.261 -> 20.689655 | N63: 29 | O63: 1.6 | P63: 6.8 | Q63: 4.9 | R63: 0
B64: 601515 | C64: 东峰集团 | D64: 国企 | E64: 20250612 | F64: =E64 -> 20250612 | G64: 衢州国资委受让29.9% | H64: 0 | I64: 完成 | L64: 18 | M64: =L64/0.3 -> 60 | N64: 54 | O64: 14 | P64: 67 | Q64: 54 | R64: 0
B65: 600520 | C65: 三佳科技 | D65: 国企 | E65: 20250125 | F65: =E65 -> 20250125 | G65: 合肥国资委受让17%+表决权委托5% | H65: 0 | I65: 完成 | L65: 6.6 | M65: =L65/0.17 -> 38.823529 | N65: 38 | O65: 3 | P65: 5.4 | Q65: 3.7 | R65: 0
B66: 603825 | C66: 华扬联众 | D66: 国企 | E66: 20250125 | F66: =E66 -> 20250125 | G66: 湖南长沙国资委的湘江集团拍卖获得18.81% | H66: 0 | I66: 完成 | J66: 20250318，与湘江集团文旅公司签订商业合作 20250423，继续拍卖获得1.47%股份，成为第一大股东 | L66: 5.07 | M66: =L66/0.1881 -> 26.953748 | N66: 30 | O66: 20 | P66: 22 | Q66: 1 | R66: 0
B67: 2501 | C67: 利源股份 | D67: 民营 | E67: 20250220 | F67: =E67 -> 20250220 | G67: 江苏步步高，张源22%，两个酒公司，1个房地产置业公司，同时还是光一退的一致行动人 | H67: 0 | I67: 完成 | L67: 3600万+9亿贷款担保 | N67: 65 | O67: 3.3 | P67: 9.2 | Q67: 3.4 | R67: 0
B68: 300192 | C68: 科德教育 | D68: 十堰市国企 | E68: 20250221 | F68: =E68 -> 20250221 | G68: 湖北十堰市国资委 | H68: 0 | I68: 已终止 | L68: 11 | N68: 53 | O68: 7.9 | P68: 12 | Q68: 8.2 | R68: 0
B69: 603227 | C69: 雪峰科技 | D69: 国企 | E69: 20250226 | F69: =E69 -> 20250226 | G69: 广东宏大，上市公司，广东省环保集团有限公司21% | H69: 0 | I69: 完成 | J69: 20240703，签署转让协议，由于广东宏大有民爆业务、矿山爆破业务，与上市公司冲突，承诺5年内解决同业竞争问题。可能又吸收合并？ | L69: 20 | M69: =L69/0.21 -> 95.238095 | N69: 100 | O69: 61 | P69: 78 | Q69: 58 | R69: 0
B70: 300511 | C70: 雪榕生物 | D70: 民营 | E70: 20250304 | F70: 20251104 | G70: 万紫千鸿蒋智，好像是做投资的，人工智能相关的 股份转让+定向发行 | H70: 4 | I70: 完成 | J70: 有可转债 | K70: 是 | L70: 1 | N70: 22 | O70: 21 | P70: 38 | Q70: 7 | R70: 0
B71: 603080 | C71: 新疆火炬 | D71: 民营 | E71: 20250314 | F71: =E71 -> 20250314 | G71: 江西中燃的雍芝君受让 20.52% | H71: 1 | I71: 完成 | J71: 20250516，收购大股东的燃气公司 | L71: 6.3 | M71: =L71/0.205 -> 30.731707 | N71: 23 | O71: 15 | P71: 23 | Q71: 16 | R71: 0
B72: 603139 | C72: 康惠制药 | D72: 民营 | E72: 20250903 | F72: =E72 -> 20250903 | G72: 亿安天下（870849）的李红明、王雪芳受让22%+表决权放弃 | H72: 1 | I72: 完成 | J72: 亿安天下搞数据算力中心的，2024年收入4亿，净利润3800万 | L72: 5.4 | M72: =L72/0.22 -> 24.545455 | N72: 20 | O72: 5.6 | P72: 19 | Q72: 9 | R72: 0
B73: 601500 | C73: 通用股份 | D73: 国企 | E73: 20250617 | F73: =E73 -> 20250617 | G73: 江苏国资委受让25% | H73: 0 | I73: 完成 | L73: 21 | M73: =L73/0.25 -> 84 | N73: 72 | O73: 70 | P73: 156 | Q73: 59 | R73: 0
B74: 603330 | C74: 天洋新材 | D74: 民营 | E74: 20250823 | F74: =E74 -> 20250823 | G74: 江苏百兴产业投资集团有限公司的百瑞兴阳受让21%，PVC，各种薄膜 | H74: 1 | I74: 完成 | J74: 新股东还持有5%的绿康生化股份 | L74: 6.6 | M74: =L74/0.21 -> 31.428571 | N74: 27 | O74: 13 | P74: 25 | Q74: 15 | R74: 0
B75: 688350 | C75: 富淼科技 | D75: 民营 | E75: 20250416 | F75: =E75 -> 20250416 | G75: 永卓控股，股份转让29.98%。 永卓下面有钢铁业务，新能源材料，风电锻件等资产， | H75: 0 | I75: 完成 | J75: 有可转债 转让价格16.38 | K75: 是 | L75: 5.9 | M75: =L75/0.3 -> 19.666667 | N75: 17 | O75: 15.6 | P75: 26.7 | Q75: 14.7 | R75: 0
B76: 603819 | C76: 神力股份 | D76: 民营 | E76: 20250417 | F76: =E76 -> 20250417 | G76: 辽宁为戍王雪受让22% | H76: 0 | I76: 已终止 | J76: 20250414签署股份转让协议 | L76: 7 | M76: =L76/0.22 -> 31.818182 | N76: 31 | O76: 13 | P76: 15 | Q76: 8 | R76: 0
B77: 2868 | C77: 绿康生化 | D77: 民营 | E77: 20250422 | F77: 20251124 | G77: 跨境物流公司福建纵腾网络有限公司，2024年利润11个亿。这个估计肯定要注入了。 | H77: 4 | I77: 完成 | J77: 转让收入6个亿，置出资产估计3个亿，实际原大股东可能赚3个亿左右。那么现有大股东实际买壳成本就是3个亿了。 同时出售原负债资产给原大股东。大股东原29.99%股份全部转让。原光伏胶膜资产置出后，资产负债表将得到极大的改善。 | L77: 6 | N77: 22 | O77: 6.5 | P77: 14.5 | Q77: -0.5 | R77: 0
B78: 603776 | C78: 永安行 | D78: 民营 | E78: 20250422 | F78: =E78 -> 20250422 | G78: 哈啰资产，旗下哈啰出行 | H78: 4 | I78: 完成 | J78: 有可转债 20250509，定向发行预案 20250530，发行方案被上交所受理 | K78: 是 | L78: 4.5 | N78: 36 | O78: 4.5 | P78: 44 | Q78: 32 | R78: 0
B79: 2828 | C79: 贝肯能源 | D79: 民营 | E79: 20250426 | F79: =E79 -> 20250426 | G79: 定向发行21%，陈东（公司董事长） | H79: 0 | I79: 未完成 | J79: 旗下没看到有什么资产 | L79: 3.5 | N79: 18 | O79: 9.5 | P79: 17 | Q79: 7 | R79: 0
B80: 2802 | C80: 洪汇新材 | D80: 无锡国企 | E80: 20250427 | F80: =E80 -> 20250427 | G80: 无锡市锡山区财政局29.99% | H80: 0 | I80: 完成 | L80: 8.9 | M80: =L80/0.3 -> 29.666667 | N80: 22 | O80: 4.5 | P80: 6.8 | Q80: 6.2 | R80: 0
B81: 300609 | C81: 汇纳科技 | D81: 民营 | E81: 20250805 | F81: =E81 -> 20250805 | G81: 3D打印，江泽星，5年内解决同业竞争。 金石三维，搞3D打印增材服务的，主攻工业3D打印机 股份转让15%，然后花7亿多定向发行，控股权提升到34%。同行公司，铂力特，先临三维 | H81: 4 | I81: 完成 | J81: 发行股份还未完成 | L81: 4.5 | M81: =L81/0.15 -> 30 | N81: 36 | O81: 3.6 | P81: 13 | Q81: 11 | R81: 0
B82: 300507 | C82: 苏奥传感 | D82: 民营 | E82: 20250507 | F82: 20251015 | G82: 中创新航，港股上市公司，锂电池、储能。股份转让11%（5.1亿）+定向发行11%（6.7亿） | H82: 2 | I82: 完成 | J82: 20250507，发布定向发行股票预案，建设 AMB 覆铜基板建设项目 | L82: 5.1+6.7 | M82: =5.1/0.11 -> 46.363636 | N82: 60 | O82: 16.7 | P82: 40 | Q82: 24 | R82: 0
B83: 688178 | C83: 万德斯 | D83: 民营 | E83: 20250520 | F83: =E83 -> 20250520 | G83: 瑞源国际，奇瑞控股，无实际控制人28.88%。旗下有奇瑞汽车公司 | H83: 3 | I83: 完成 | L83: 4.1 | M83: =L83/0.2888 -> 14.196676 | N83: 14 | O83: 6.2 | P83: 22 | Q83: 11 | R83: 0
B84: 301007 | C84: 德迈仕 | D84: 民营 | E84: 20250522 | F84: 20250725 | G84: 汇心创智的潘异，创投的受让16.73% | H84: 0 | I84: 完成 | L84: 6.7 | M84: =L84/0.1673 -> 40.047818 | N84: 34 | O84: 6.9 | P84: 10 | Q84: 7 | R84: 0
B85: 603333 | C85: 尚纬股份 | D85: 民营 | E85: 20250524 | F85: =E85 -> 20250524 | G85: 福华通达化学股份公司，张华25.35%，乐山化工龙头，磷、农药。2023年净资产37亿，净利润6亿 | H85: 2 | I85: 完成 | J85: 20250524详式权益变动书里表示，未来增加电子化学品、双氧水、硫酸业务。 | L85: 8 | M85: =L85/0.2535 -> 31.558185 | N85: 40 | O85: 17 | P85: 30 | Q85: 20 | R85: 0
B86: 2114 | C86: 罗平锌电 | D86: 国企 | E86: 20250527 | F86: =E86 -> 20250527 | G86: 云南曲靖发投受让22%，曲靖市国资委 | H86: 0 | I86: 未完成 | J86: 2025604签署股份转让协议 | L86: 4.6 | M86: =L86/0.22 -> 20.909091 | N86: 23 | O86: 12.6 | P86: 22.3 | Q86: 8 | R86: 0
B87: 2199 | C87: 东晶电子 | D87: 民营 | E87: 20250530 | F87: 20250806 | G87: 无锡浩天一意朱海飞受让19.97%+间接控股10% | H87: 0 | I87: 完成 | L87: 3 | M87: =L87/0.2 -> 15 | N87: 15 | O87: 2 | P87: 4.7 | Q87: 2.1 | R87: 0
B88: 605081 | C88: 太和水 | D88: 民营 | E88: 20250527 | F88: =E88 -> 20250527 | G88: 北京欣欣12%，股份转让，再加6%表决权，溢价145% | H88: 0 | I88: 完成 | J88: 20270808前有权购买3%的股份 20250530，出售子公司凯云发展的股权，2000万，优化资产结构。 | L88: 3.9 | M88: =L88/0.12 -> 32.5 | N88: 13 | O88: 1 | P88: 14 | Q88: 9 | R88: 0
B89: 2529 | C89: 海源复材 | D89: 民营 | E89: 20250528 | F89: =E89 -> 20250528 | G89: 深圳市紫光照明技术股份有限公司的刘洪超、丁立中、刘浩14%，搞电力的 | H89: 0 | I89: 完成 | J89: 紫光照明2022年上市失败，2020年收入3.5亿，净利润4000玩，净资产3.5亿 | L89: 3.5 | M89: =L89/0.14 -> 25 | N89: 23 | O89: 1.8 | P89: 8.7 | Q89: 1.7 | R89: 0
B90: 301186 | C90: 超达装逼 | D90: 民营 | E90: 20250528 | F90: =E90 -> 20250528 | G90: 南京友旭29.32%，陈存友、陈浩、陈娇、倪香莲，一家人。 协众国际热管理系统股份公司，汽车热管理系统零部件。 | H90: 1 | I90: 完成 | J90: 星宇股份有投资协助国际 | L90: 9.4 | M90: =L90/0.2932 -> 32.060027 | N90: 34 | O90: 7.2 | P90: 21 | Q90: 15 | R90: 0
B91: 603226 | C91: 菲林格尔 | D91: 民营 | E91: 20250923 | F91: =E91 -> 20250923 | G91: 金亚伟受让25%，还有安吉县财政局作为合伙人 | H91: 0 | I91: 完成 | J91: 20250603，签署股份转让协议 | L91: 7 | M91: =L91/0.25 -> 28 | N91: 29 | O91: 3.3 | P91: 13.86 | Q91: 9.86 | R91: 0
B92: 2633 | C92: 申科股份 | D92: 民营 | E92: 20250530 | F92: 20251105 | G92: 深圳汇理受让41.89% | H92: 0 | I92: 完成 | J92: 20250530，确认由深圳汇理竞得，10亿 | L92: 10 | M92: =L92/0.3189 -> 31.357792 | N92: 23 | O92: 3.2 | P92: 6 | Q92: 4.2 | R92: 0
B93: 603389 | C93: 亚振家居 | D93: 民营 | E93: 20250530 | F93: =E93 -> 20250530 | G93: 济南域潇集团吴涛、范伟浩股份受让29.99%+要约21%，锆钛矿 | H93: 4 | I93: 完成 | J93: 新股东持有400122三板退市企业，还有很多锆钛矿企业，济南域潇集团有限公司，海南域潇锆钛控股股份有限公司，山东域潇有色新材料有限公司，莫桑比克锆钛矿霸主。据鲁北化工20241123对外投资公告显示，济南域潇集团2023年净利润25.9亿，净资产89亿 20250802公告收购大股东的一个子公司51%股权，估计是保壳的 | L93: 4.5 | M93: =L93/0.3 -> 15 | N93: 15 | O93: 2 | P93: 5.7 | Q93: 2.2 | R93: 0
B94: 600491 | C94: 龙元建设 | D94: 国企 | E94: 20230628 | F94: =E94 -> 20230628 | G94: 杭州交投，杭州国资委受让8.4%+定向发行 | H94: 0 | I94: 未完成 | J94: 20250527，定向发行获得批复 | L94: 23 | N94: 60 | O94: 91 | P94: 554 | Q94: 110 | R94: 0
B95: 2634 | C95: 棒杰股份 | D95: 民营 | E95: 20250722 | F95: =E95 -> 20250722 | G95: 上海启烁黄荣耀受让5%+表决权委托14.91% | H95: 0 | I95: 完成 | J95: 20250603，光伏子公司主动停产止损 20250603，签署转让协议。 | L95: 1 | N95: 20 | O95: 11 | P95: 32 | Q95: 2 | R95: 0
B96: 2875 | C96: 安奈儿 | D96: 民营 | E96: 20250603 | F96: 20250815 | G96: 新创源的黄涛受让13%+表决权放弃 | H96: 0 | I96: 完成 | J96: 签署股份转让协议 | L96: 4.22 | N96: 36 | O96: 6.3 | P96: 9 | Q96: 7 | R96: 0
B97: 2826 | C97: 易明医药 | D97: 民营 | E97: 20250527 | F97: 20250820 | G97: 姚劲波受让23%，58同城 | H97: 0 | I97: 完成 | L97: 6.6 | N97: 23 | O97: 6.5 | P97: 9.8 | Q97: 7.7 | R97: 0
B98: 2762 | C98: 金发拉比 | D98: 民营 | E98: 20250604 | F98: =E98 -> 20250604 | G98: 元一成物的陈珂如受让13.3%，还有未来第二次转让14.7% | H98: 0 | I98: 已终止 | J98: 20250712，因受让方实际控制人涉及家族财产清算纠纷，终止转让 | L98: 3.45 | M98: 26 | N98: 22 | O98: 2 | P98: 9 | Q98: 8 | R98: 0
B99: 2955 | C99: 鸿合科技 | D99: 民营 | E99: 20250604 | F99: 20251203 | G99: 合肥瑞丞私募受让25%+表决权放弃，无实际控制人，奇瑞汽车和奇瑞控股设立的 | H99: 0 | I99: 完成 | L99: 15.7 | M99: =L99/0.25 -> 62.8 | N99: 60 | O99: 35 | P99: 46 | Q99: 32 | R99: 0
B100: 403 | C100: 派林生物 | D100: 国企 | E100: 20250605 | F100: =E100 -> 20250605 | G100: 中国生物受让21% | I100: 未完成 | N100: 161 | O100: 26 | P100: 91 | Q100: 79 | R100: 0
...

Sheet 预计摘帽
B1: 利润转正>收入足够，实控人变更加10%概率，负债率太高且没有预重整的排除 | N1: 10 | O1: 10 | P1: 70 | Q1: 30 | R1: 40 | S1: 80 | T1: 5 | U1: 20 | V1: -40 | W1: 30
A2: 年份 | B2: 代码 | C2: 名称 | D2: 警示原因 | E2: 解决措施 | F2: 进展 | G2: 关注点 | H2: 其他 | I2: 财报审计报告 | J2: 内控审计报告 | K2: 是否变更实控人 | L2: 重整 | M2: 摘帽分 | N2: 实控人变更权重 | O2: 变更完成权重 | P2: 出售资产权重 | Q2: 购买资产权重 | R2: 收入增加权重 | S2: 利润转正权重 | T2: 国企权重 | U2: 大合同权重 | V2: 审计扣分 | W2: 腾笼换鸟权重 | X2: 题材分 | Z2: 财报问询
A3: 2025 | B3: 595 | C3: 宝塔实业 | D3: 收入不足3亿，差1亿 | E3: 收入超过3亿或净利润转正 | F3: 已经注入宁夏电投新能源资产 | G3: 宁夏自治区 | I3: 标准无保留意见 | J3: 标准无保留意见 | K3: 否 | M3: =N3+O3+P3+Q3+R3+S3+T3+U3+V3+W3 -> 95 | N3: 0 | O3: 0 | P3: 30 | Q3: 30 | R3: 0 | S3: 0 | T3: 5 | U3: 0 | V3: 0 | W3: 30
A4: 2025 | B4: 2058 | C4: 威尔泰 | D4: 收入不足退市风险 | E4: 向大股东出售仪器仪表相关的亏损资产包2.8亿，净利润转正负债率大幅下降。然后向大股东购买紫江新材，从事软包锂电池用铝塑复合膜的研发。两者不互为前提，独立进行。紫江新材在新三板上市。2024年报显示收入6亿利润5000万，但利润在下滑 大股东拥有紫江企业（饮料包装、软塑包装）、紫江新材 | F4: 2024年1219公告资产重组。 20250401公告出售资产审计已经完成。就等股东大会批准了，价格2.8亿。资产1.6亿，负债6000万，增值170%，主要是紫竹高新的长期股权（穿透后是房地产）投资的增值。出售完成后净利润转正。 购买资产还在审计。 20250510公告，购买控股子公司紫燕机械剩余49%股权，4300万。2024年净利润1578万。提高净利润的措施。资产1.5亿，负债6400万 20250513公告，出售资产议案合并到0527股东大会一起审议 20250527，出售和购买都获得股东大会通过。 20250605，出售资产完成交割和收款，收购资产也完成了，二季度利润转正应该没问题了 半年报净利润还是略亏 20250828半年报净利润-400万，紫燕机械半年收入3000万，净利润350万，紫江新材半年报收入和净利润也增长30%。 | G4: 关注出售亏损资产进展 | H4: 壳价值也够低了 | I4: 标准无保留意见 | J4: 标准无保留意见 | K4: 否 | M4: =N4+O4+P4+Q4+R4+S4+T4+U4+V4+W4 -> 90 | N4: 0 | O4: 0 | P4: 30 | Q4: 30 | R4: 0 | S4: 10 | T4: 0 | U4: 0 | V4: 0 | W4: 20
A5: 2025 | B5: 300899 | C5: 上海凯鑫 | D5: 收入不足退市风险 | E5: 2024年Q4的收入异常的低。导致了最后的亏损。 一季度利润转正、收入大涨 在手订单2.3亿 | F5: 半年报净利润2000万，收入1.2亿 | G5: 关注半年报 | H5: 壳价值也够低了 | I5: 标准无保留意见 | J5: 标准无保留意见 | K5: 否 | M5: =N5+O5+P5+Q5+R5+S5+T5+U5+V5+W5 -> 85 | N5: 0 | O5: 0 | P5: 0 | Q5: 0 | R5: 40 | S5: 40 | T5: 0 | U5: 5 | V5: 0 | W5: 0
A6: 2025 | B6: 600753 | C6: 庚星股份/海钦股份 | D6: 收入不足退市风险 净资产负退市风险 持续经营不确定其他风险 | E6: 20240320原大股东股份被拍卖过户，现大股东钟仁海成为新实控人，3.9亿，单价7。然后与原大股东展开了争夺公司实际控制权的长时间斗争。钟仁海有鸿基石化股份公司，2023净资产12亿，净利润140万。 虽然公司现在净资产负，但负债规模仅1个亿多，只需要大股东随便融资就能解决。 目前看大股东还是有一些能力的，逐渐解决了很多的问题，跟二股东也和解了 20240105证监会对公司违法行为立案调查，现在还没有结论 | F6: 20241031大股东财务资助7000万 一季度净利润大幅减亏，管理销售费用大幅下滑，经营液化石油气业务，从收入上看，全年3亿应该没有问题。 半年报预计净利润500万，算起来净资产应该可以转正 20250822半年报，净资产已经转正 20250908公告，大股东赠送51%子公司股权给上市公司，净资产8000万，5-7月收入3000万，净利润100万，这下净资产稳了 | G6: 关注净资产的解决进展 | I6: 强调无保留 强调项：持续经营不确定性 被立案调查，原控股股东和上市公司 | J6: 强调无保留 强调项：原公司内控缺陷多，现在已整改 | K6: 是 | M6: =N6+O6+P6+Q6+R6+S6+T6+U6+V6+W6 -> 60 | N6: 10 | O6: 10 | P6: 0 | Q6: 15 | R6: 0 | S6: 40 | T6: 0 | U6: 0 | V6: -15
A7: 2025 | B7: 1270 | C7: 铖昌科技 | D7: 收入不足3亿，差9000万 | E7: 收入超过3亿或净利润转正 | F7: 一季度收入大涨，净利润大幅转正。主要是需求增加。 半年报净利润4500万 | G7: 相控雷达芯片，遥感卫星。 | I7: 标准无保留意见 | J7: 标准无保留意见 | K7: 否 | M7: =N7+O7+P7+Q7+R7+S7+T7+U7+V7+W7 -> 73 | N7: 0 | O7: 0 | P7: 0 | Q7: 0 | R7: 13 | S7: 60 | T7: 0 | U7: 0 | V7: 0
A8: 2025 | B8: 603580 | C8: 艾艾精工 | D8: 收入不足退市风险 不过亏得也不多 | E8: 20250429拟花1.25亿购买泰州中石信资产，资产年收入5000万，净利润300万，资产的客户都是果链。预测2025年收入1.2亿，利润1800万，5月有产品量产。 靠收入保3亿有点悬，靠利润转正还是有可能的 | F8: 一季度利润转正，转正原因是财务费用下降，估计是汇率影响。 20250515购买资产议案通过股东大会决议 20250526，中石信完成工商变更。 半年报净利润800万，收入1亿，财务费用就贡献了600万，中石信6月并表贡献了800万，可以预估下半年贡献收入4800万，按收入算3个亿还是有点难 三季报大增1.9亿，净利润1200万 | G8: 警惕固定资产减值，存货跌价，应收账款减值，其他非流动资产减值 | I8: 标准无保留意见 | J8: 标准无保留意见 | K8: 否 | M8: =N8+O8+P8+Q8+R8+S8+T8+U8+V8+W8 -> 50 | N8: 0 | O8: 0 | P8: 0 | Q8: 10 | R8: 0 | S8: 40 | T8: 0 | U8: 0 | V8: 0 | X8: 5
A9: 2025 | B9: 600636 | C9: 国新文化 | D9: 收入不足3亿，差0.2亿，主要是商誉减值4.5亿导致亏损。还剩2.5亿商誉。 | E9: 收入超过3亿或净利润转正 | F9: 20250408，大股东发布增持1%-2%计划。 一季度收入大涨，AI相关，有部分去年的收入在一季度确认。净利润减亏。 半年报收入1.1亿。大增，净利润690万转正 三季报大增2.3亿，净利润1700万 | G9: 现金13亿，国资委 | I9: 标准无保留意见 | J9: 标准无保留意见 | K9: 否 | M9: =N9+O9+P9+Q9+R9+S9+T9+U9+V9+W9 -> 50 | N9: 0 | O9: 0 | P9: 0 | Q9: 0 | R9: 5 | S9: 40 | T9: 5 | U9: 0 | V9: 0
A10: 2025 | B10: 2656 | C10: 摩登大道 | D10: 收入不足3亿，差0.9亿 | E10: 收入超过3亿 | F10: 20250415公告，收购电缆公司，2024收入1亿，净利润600万 20250507公告，收购电力公司完成 半年报2.3亿，大涨，净利润减亏。其中电力公司并表9100万，净利润200万。所有保留事项已经消除。 三季报4.2亿收入 | G10: 原大股东占用2.4亿，被责令归还快到期时被现实控人代替归还，现大股东王立平旗下有锐洋集团，产值25亿。持有10%股份，还有3%的表决权 | I10: 保留意见 | J10: 保留意见 | K10: 是 | M10: =N10+O10+P10+Q10+R10+S10+T10+U10+V10+W10 -> 70 | N10: 5 | O10: 5 | P10: 0 | Q10: 20 | R10: 40 | S10: 0 | T10: 0 | U10: 0 | V10: 0
A11: 2025 | B11: 300268 | C11: 佳沃食品 | D11: 净资产负 | F11: 20250425出售主要净资产负的子公司给大股东，完成净资产大幅提升，净利润大幅提升。只剩青岛国星子公司，收入8亿，净利润6000万。 20250610出售完成 半年报净资产转正，剥离子公司贡献净利润-3.18亿，青岛国星受关税25%影响，进口成本上升，销量下滑，净利润下滑到1400万。 | I11: 持续经营不确定性无保留意见 | J11: 标准无保留意见 | K11: 否 | M11: =N11+O11+P11+Q11+R11+S11+T11+U11+V11+W11 -> 50 | N11: 0 | O11: 0 | P11: 50 | Q11: 0 | R11: 0 | S11: 0 | T11: 0 | U11: 0 | V11: 0
A12: 2025 | B12: 2529 | C12: 海源复材 | D12: 收入不足退市风险，差1.3亿 | E12: 换实控人 主营光伏组件和汽车复合材料和光伏组件代工业务 提高代工业务是不是就可以保收入了 | F12: 20250331实控人变更新余金紫欣的刘洪超、丁立中、刘浩 ，总价3.5亿 20250416设立江西省紫源新技术有限责任公司，搞电力的。 20250417，金紫欣向公司提供1亿财务资助 20250428，一季度收入9600万大涨，说是光伏和复合材料订单增加 20250428担保公告，从中找到一季度收入大涨的主要功臣是新余海源电源科技有限公司子公司收入大涨。Q1就超过了去年一年的收入。 二季度收入继续大涨 20250825，剥离压机资产，净资产可提升1.2亿，2024年收入4000万 半年报收入2亿，净利润下滑 三季报大增2.7亿 | I12: 标准无保留意见 | J12: 标准无保留意见 | K12: 是 | M12: =N12+O12+P12+Q12+R12+S12+T12+U12+V12+W12 -> 40 | N12: 10 | O12: 10 | P12: 0 | Q12: 0 | R12: 20 | S12: 0 | T12: 0 | U12: 0 | V12: 0
A13: 2025 | B13: 518 | C13: 四环生物 | D13: 收入不足退市风险，差1亿 | E13: 20250114原大股东股份被拍卖，新大股东碧水投资进入。已经完成变更。花了3.8亿。好像是搞农业的。 | F13: 一季度收入下降，净利润大幅下滑 半年报预计收入1.7亿，大幅增加，主要是苗木增加 三季报大增2.9亿 | G13: 不知道实控人有什么资产 | I13: 标准无保留意见 | J13: 标准无保留意见 | K13: 是 | M13: =N13+O13+P13+Q13+R13+S13+T13+U13+V13+W13 -> 50 | N13: 10 | O13: 10 | P13: 0 | Q13: 0 | R13: 30 | S13: 0 | T13: 0 | U13: 0 | V13: 0
A14: 2025 | B14: 600228 | C14: 返利网 | D14: 收入不足3亿，差7000万 | E14: 收入超过3亿 | F14: 半年报收入1.8亿，净利润-3000万 三季报已经过3亿 | I14: 标准无保留意见 | J14: 标准无保留意见 | K14: 否 | M14: =N14+O14+P14+Q14+R14+S14+T14+U14+V14+W14 -> 40 | N14: 0 | O14: 0 | P14: 0 | Q14: 0 | R14: 40 | S14: 0 | T14: 0 | U14: 0 | V14: 0 | Z14: 三季报
A15: 2025 | B15: 300211 | C15: 亿通科技 | D15: 收入不足退市风险，9600万 | E15: 2021年3月实控人变更为黄汪，旗下有安徽华米做健康监测设备，2024年末营收15亿，净利润8800万，净资产25亿。可能注入上市公司。 公司每季度财报都非常详实。 | F15: 一季度收入大涨 20250430跟安徽华米签订关联交易合同1.5亿，1年内有效。 三季报大增1.5亿 | G15: 收入保壳基本没问题 大股东注入资产的时间也够了，但是华米现在自己也不太好，不知道符不符合注入条件 | I15: 标准无保留意见 | J15: 标准无保留意见 | K15: 是 | M15: =N15+O15+P15+Q15+R15+S15+T15+U15+V15+W15 -> 65 | N15: 10 | O15: 10 | P15: 0 | Q15: 0 | R15: 40 | S15: 0 | T15: 0 | U15: 5 | V15: 0
A16: 2025 | B16: 288 | C16: 绿康生化 | D16: 2024净资产负 持续经营不确定性 | E16: 20250422变更实控人，跨境物流公司福建纵腾网络有限公司，2024年利润11个亿。这个估计肯定要注入了。同时出售原负债资产给原大股东，两者不互为前提。大股东原29.99%股份全部转让。原光伏胶膜资产置出后，资产负债表将得到极大的改善。还参与了有棵树的破除重整 | F16: 一季度收入利润没有改善 要等资产出售进展和实控人变更进展 20250528，置出资产承接方设立完成 20250628出售草案出炉 | G16: 关注资产出售情况 关注实控人变更情况 | I16: 带解释的无保留意见 解释段是持续经营不确定性 | J16: 标准无保留意见 | K16: 是 | M16: =N16+O16+P16+Q16+R16+S16+T16+U16+V16+W16 -> 30 | N16: 10 | O16: 0 | P16: 20 | Q16: 0 | R16: 0 | S16: 0 | T16: 0 | U16: 0 | V16: 0
A17: 2025 | B17: 603007 | C17: 花王股份 | D17: 收入不足退市风险 | E17: 已经重整过了，2025年必须要解决收入不足的问题，否则投资人就亏死了。正在购买三方资产混动燃油箱，12个亿，购买1半的股权，如果成功，肯定可以满足收入要求了。明年可以摘帽。 大股东还有新质生产力资产，但注入较慢，为了保壳所以先购买三方资产，目前看市场不认可公布购买方案后一直跌。从监管函得知，公司购买的三方资产定价明显过高，偏离汽车零部件行业太多，公司账上现金一共就5个多亿，却全部拿来购买高价资产，目的是什么？所以投资者用脚投票。 大股东旗下还有半导体资产等待注入。 | F17: 实控人变更承诺被第一次股东大会否决，现第二次股东大会继续审议。就算通过能否购买成功也不一样，参照双成药业。 20250604，回复购买资产预案的问询，2024年净利润7000万，按这个看，也不算很贵。竞对公司，世昌股份 20250830，购买资产已经过户完成。预计增加2025年并表收入2.3亿 | G17: 关注实控人承诺变更是否获得股东大会通过 | H17: 市值太高 | I17: 标准无保留意见 | J17: 标准无保留意见 | K17: 是 | M17: =N17+O17+P17+Q17+R17+S17+T17+U17+V17+W17 -> 30 | N17: 10 | O17: 10 | P17: 0 | Q17: 10 | R17: 0 | S17: 0 | T17: 0 | U17: 0 | V17: 0
A18: 2025 | B18: 3004 | C18: 声讯股份 | D18: 收入不足3亿 | E18: 收入超过3亿，差了3000万 | F18: 一季度收入持平，净利润继续下滑 20250614收购浙江中辰城市应急服务管理有限公司51%股权，2024年收入1.4亿，净利润-1500万，0630完成收购，保壳应该没问题了 半年报收入7000万，同比增2000万，净利润减亏，经营在好转 三季报收入1.3亿，净利润继续正，但这主要是减值转回导致的，转回了2700万。还是有点担心Q4的收入 | I18: 标准无保留意见 | J18: 标准无保留意见 | K18: 否 | M18: =N18+O18+P18+Q18+R18+S18+T18+U18+V18+W18 -> 30 | N18: 0 | O18: 0 | P18: 0 | Q18: 20 | R18: 10 | S18: 0 | T18: 0 | U18: 0 | V18: 0
A19: 2025 | B19: 2569 | C19: 步森股份 | D19: 收入不足退市风险 持续经营不确定性 | E19: 202407实控人变更为宝鸡国资，司法拍卖获得，1.6亿，7.5元/股。 | F19: 一季度收入下滑，净利润减亏，减亏原因是信用减值下滑。 半年报收入下滑，净利润增亏，公司管理层正在股东方的支持下努力缓解现金流压力，多措并举恢复和发展主营业务 20250908公告，出售联营公司陕西步森服饰智造有限公司，按长期股权投资项预计，可以卖6000万 | I19: 强调无保留意见 强调项：连续三年亏损，现金流负 持续经营不确定性 | J19: 强调事项段无保留意见 强调项：原大股东非经营资金占用，已归还。 | K19: 是 | M19: =N19+O19+P19+Q19+R19+S19+T19+U19+V19+W19 -> 25 | N19: 10 | O19: 10 | P19: 0 | Q19: 0 | R19: 0 | S19: 0 | T19: 5 | U19: 0 | V19: 0
A20: 2025 | B20: 504 | C20: 南华生物 | D20: 收入不足退市风险 | E20: 说是要发展美妆 大股东旗下有财信证券 | F20: 一季度没有改善 20250811公告收购湖南慧泽生物医药科技有限公司51%股权CRO 20250903华7000万控股娄底金弘新材料新能源电池回收，前7月收入4500万，业绩承诺每年2.5亿 三季报收入0.8亿，但净利润转正，通过管理费用大幅下降完成的 | G20: 关注保壳信号 | I20: 标准无保留意见 | J20: 标准无保留意见 | K20: 否 | M20: =N20+O20+P20+Q20+R20+S20+T20+U20+V20+W20 -> 45 | N20: 0 | O20: 0 | P20: 0 | Q20: 20 | R20: 0 | S20: 20 | T20: 5 | U20: 0 | V20: 0
A21: 2025 | B21: 603721 | C21: 中广天择 | D21: 收入不足退市风险 2024年就差1000万 | E21: 20250430拟购买大股东旗下体育资产，年收入4000万，净利润300万 | F21: 一季度收入大幅下滑 20250430收购大股东旗下长沙体育产业经营有限公司，2024年收入6900万，净利润300万 202506收购完成股权变更登记。 半年报略减，1.3亿，全年应该差的不多，长沙体产并表收入1300万 三季报略减1.8亿，进入两家私募 | G21: 关注保壳信号 | I21: 标准无保留意见 | J21: 标准无保留意见 | K21: 否 | M21: =N21+O21+P21+Q21+R21+S21+T21+U21+V21+W21 -> 25 | N21: 0 | O21: 0 | P21: 0 | Q21: 20 | R21: 0 | S21: 0 | T21: 5 | U21: 0 | V21: 0
A22: 2025 | B22: 688511 | C22: 天微电子 | D22: 收入不足退市风险 | E22: 无 | F22: 一季度利润转正大涨 三季报净利润3000万 | G22: 关注业绩持续性 | H22: 壳价值也够低了 | I22: 标准无保留意见 | J22: 标准无保留意见 | K22: 否 | M22: =N22+O22+P22+Q22+R22+S22+T22+U22+V22+W22 -> 60 | N22: 0 | O22: 0 | P22: 0 | Q22: 0 | R22: 0 | S22: 60 | T22: 0 | V22: 0 | Z22: 半年报
A23: 2025 | B23: 603389 | C23: 亚振家居 | D23: 收入不足退市风险 | E23: 20250424，实控人变更，总价款7个多亿，分两步，先转让29.99%股份，股份过户后十工作日内发起要约，要约21%股份，要约价格5.68 新实控人是向其旗下公司借款收购股份的，旗下公司进行锆钛矿开采业务，净资产超100亿。还有一家三板企业400122，原游久股份，稀土资产，该公司目前不太好。 | F23: 一季度收入略增利润减亏 20250530，变更完成 20250821收购广西锆业科技有限公司51%股权完成，前5月收入1.2亿 半年报收入1亿，净利润-3000万 三季报不变1.5亿 | G23: 关注实控人变更完成情况 | I23: 标准无保留意见 | J23: 标准无保留意见 | K23: 是 | M23: =N23+O23+P23+Q23+R23+S23+T23+U23+V23+W23 -> 20 | N23: 10 | O23: 10 | P23: 0 | Q23: 0 | R23: 0 | S23: 0 | T23: 0 | U23: 0 | V23: 0
A24: 2025 | B24: 2898 | C24: 塞隆药业 | D24: 收入不足退市风险 | E24: 就差5000万 20250518转让给海南雅亿，合伙人企业，无实际控制人，医药行业，2亿，8元/股。 | F24: 一季度收入利润继续下滑 20250524，海南雅亿完成工商变更。 20250710，变更完成 半年报收入1.3亿，净利润继续下滑 三季报收入2亿同比下滑一点 | G24: 关注保壳信号 | I24: 标准无保留意见 | J24: 标准无保留意见 | K24: 是 | M24: =N24+O24+P24+Q24+R24+S24+T24+U24+V24+W24 -> 20 | N24: 10 | O24: 10 | P24: 0 | Q24: 0 | R24: 0 | S24: 0 | T24: 0 | U24: 0 | V24: 0
A25: 2025 | B25: 603838 | C25: 四通股份 | D25: 收入不足退市风险 | E25: 有新业务增加收入，本来差得也不多，按照2024年3个月的矿产品收入3700万计算，今年7400万，总收入肯定超过3亿了。 | F25: 目前看一季度收入增加3000多万，大概率就是矿产品的 半年报业绩收入1.7亿 三季报大增2.6亿 | G25: 关注未来季度财报 | H25: 壳价值也够低了 | I25: 标准无保留意见 | J25: 标准无保留意见 | K25: 否 | M25: =N25+O25+P25+Q25+R25+S25+T25+U25+V25+W25 -> 30 | N25: 0 | O25: 0 | P25: 0 | Q25: 0 | R25: 30 | S25: 0 | T25: 0 | U25: 0 | V25: 0
A26: 2025 | B26: 2762 | C26: 金发拉比 | D26: 收入不足退市风险 | E26: 一季度收入大涨，可能解除风险，合并了几个医疗门诊的收入。 | F26: 一季度收入大涨，合并医疗门诊收入 半年报，收入1.6亿，亏损扩大，其中医美3300万，其他母婴用品增加了4700万 三季报2.6亿收入 | G26: 关注未来季度财报 | H26: 壳价值也够低了 | I26: 标准无保留意见 | J26: 标准无保留意见 | K26: 否 | M26: =N26+O26+P26+Q26+R26+S26+T26+U26+V26+W26 -> 30 | N26: 0 | O26: 0 | P26: 0 | Q26: 0 | R26: 30 | S26: 0 | T26: 0 | U26: 0 | V26: 0
A27: 2025 | B27: 3032 | C27: 传智教育 | D27: 收入不足3亿，差6000万 | E27: 收入超过3亿或净利润转正 | F27: 20240920，收购辅仁控股海外教育公司，2023年收入8000万，净利润1000万。20250104收购完成。 20241220，收购三板公司优优汇联51%股权，1亿。2024收入5000万，净利润-800万。20250213已完成。 一季度收入略涨（主要并表辅仁控股），净利润减亏 半年报收入1.6亿，净利润大幅减亏，-1000万，其中并表辅仁4600万，净利润500万，优优260万净利润-400万 三季报大增2.6亿 | G27: 感觉收入还是有点风险，看看半年报预告再说 公司账上8亿现金。 | I27: 标准无保留意见 | J27: 标准无保留意见 | K27: 否 | M27: =N27+O27+P27+Q27+R27+S27+T27+U27+V27+W27 -> 30 | N27: 0 | O27: 0 | P27: 0 | Q27: 0 | R27: 30 | S27: 0 | T27: 0 | U27: 0 | V27: 0
A28: 2025 | B28: 603813 | C28: 原尚股份 | D28: 收入不足退市风险 | E28: 20250429收购零部件制造公司，收入2700万，利润100万 | F28: 一季度继续恶化，原汽车零部件物流业务继续收缩。汽车零部件业务拓展。 半年报收入略增，1.8亿。净利润增亏 20250823，打算剥离农牧资产，2025上半年收入1000万，利润略亏。 三季报收入3.3亿 | G28: 关注努力信号 | I28: 标准无保留意见 | J28: 标准无保留意见 | K28: 否 | M28: =N28+O28+P28+Q28+R28+S28+T28+U28+V28+W28 -> 40 | N28: 0 | O28: 0 | P28: 0 | Q28: 0 | R28: 40 | S28: 0 | T28: 0 | U28: 0 | V28: 0 | Z28: 三季报
A29: 2025 | B29: 600130 | C29: 波导股份 | D29: 收入不足退市风险 | E29: 收入就差2000万，还是有希望的，账上现金7个亿，随便买个资产 | F29: 一季度没有改善 半年报收入大增，净利润下降为负 三季报大增3.2亿 | G29: 关注保壳信号 | I29: 标准无保留意见 | J29: 标准无保留意见 | K29: 否 | M29: =N29+O29+P29+Q29+R29+S29+T29+U29+V29+W29 -> 40 | N29: 0 | O29: 0 | P29: 0 | Q29: 0 | R29: 40 | S29: 0 | T29: 0 | U29: 0 | V29: 0
A30: 2025 | B30: 2199 | C30: 东晶电子 | D30: 收入不足3亿，差1亿 | E30: 收入超过3亿 | F30: 一季度收入净利润没改善 20250527控制权变更，股权投资行业 20250806完成变更 半年报收入1.1亿，还差不少 三季报1.8亿 | I30: 标准无保留意见 | J30: 标准无保留意见 | K30: 否 | M30: =N30+O30+P30+Q30+R30+S30+T30+U30+V30+W30 -> 20 | N30: 10 | O30: 10 | P30: 0 | Q30: 0 | R30: 0 | S30: 0 | T30: 0 | U30: 0 | V30: 0
A31: 2025 | B31: 600892 | C31: 大晟文化 | D31: 收入不足退市风险 | E31: 暂无 | F31: 一季度收入没有改善 半年报收入增长30%到1亿，净利润增亏到-3000万，主要源于短剧业务的收入3000万，还新增了7个传媒子公司猜测是要通过短剧来扩大收入。但是净资产只剩4000万了，感觉下半年很可能亏到负资产。 三季报大增2亿，但是净资产要负了 20251227，大股东豁免3000万债务 | G31: 关注保壳信号 | I31: 标准无保留意见 | J31: 标准无保留意见 | K31: 是 | M31: =N31+O31+P31+Q31+R31+S31+T31+U31+V31+W31 -> 5 | N31: 5 | O31: 5 | P31: 0 | Q31: 0 | R31: 0 | S31: 0 | T31: 5 | U31: 0 | V31: -10
A32: 2025 | B32: 2816 | C32: 和科达 | D32: 收入不足退市风险 | E32: 20241023实控人变成国企了，已经完成。2022年报退市风险，2023年报撤摘帽。2024年报又退市风险。 | F32: 一季度利润转正、收入大涨，不过一季度明显有调节收入的嫌疑。 二季度利润转亏 三季报收入大增1.7亿，净利润-200万 | G32: 关注二季度 | H32: 壳价值也够低了 | I32: 标准无保留意见 | J32: 标准无保留意见 | K32: 是 | M32: =N32+O32+P32+Q32+R32+S32+T32+U32+V32+W32 -> 15 | N32: 10 | O32: 10 | P32: 0 | Q32: 0 | R32: 0 | S32: -10 | T32: 5 | U32: 0 | V32: 0
A33: 2025 | B33: 691 | C33: 亚太实业 | D33: 净资产负 | E33: 净资产转正 | F33: 20250702，预重整 2025实控人增持1000万，还要增持2000万 20250903，原实控人和现实控人内讧了 | G33: 202307表决权委托给债务方广州万顺，实控人变更，实控人旗下有一些5G通信等资产 | I33: 重大段落的无保留意见 欠广州万顺的借款逾期了 | J33: 标准无保留意见 | K33: 是 | L33: 是 | M33: =N33+O33+P33+Q33+R33+S33+T33+U33+V33+W33 -> 15 | N33: 5 | O33: 10 | P33: 0 | Q33: 0 | R33: 0 | S33: 0 | T33: 0 | U33: 0 | V33: 0
A34: 2025 | B34: 2789 | C34: 建艺集团 | D34: 净资产负 | E34: 净资产转正 | F34: 20250411，向大股东出售子公司广东建艺矿业有限公司股权大概10亿，该公司净资产只有1000万，这是变相的输血，但没有进展 20251225，大股东豁免14亿债务，赠送4亿现金 | G34: 关注建艺矿业出售进展 关注重整的可能性 | I34: 持续经营不确定性无保留意见 | J34: 持续经营不确定性无保留意见 | K34: 否 | L34: 否 | M34: =N34+O34+P34+Q34+R34+S34+T34+U34+V34+W34 -> 15 | N34: 0 | O34: 0 | P34: 10 | Q34: 0 | R34: 0 | S34: 0 | T34: 5 | U34: 0 | V34: 0
A35: 2025 | B35: 2047 | C35: ST宝鹰 | D35: 净资产负 | E35: 差的不多，4000万足够转正 | F35: 珠海国资委是2020年从古少明买过来控股权的，花了16亿 20240721，要约收购13%的股份 2024年曾想通过无偿捐赠现金规避带星，但被审计判断不合规 2024年已经剥离了主要负债资产 20250725公开转让净资产-61万的子公司，标价3000万 20250911，控股股东无偿划转给珠光集团，主要做涉港澳资产运营的 大股东变更 | I35: 标准无保留意见 | J35: 否定意见，但问题不大 | K35: 否 | M35: =N35+O35+P35+Q35+R35+S35+T35+U35+V35+W35 -> 25 | N35: 10 | O35: 0 | P35: 10 | Q35: 0 | R35: 0 | S35: 0 | T35: 5 | U35: 0 | V35: 0 | W35: 0
A36: 2025 | B36: 301288 | C36: 清研环境 | D36: 收入不足1亿，差3000万 | E36: 收入超过1亿或净利润转正 | F36: 20250321，竞拍福建海通镍业公司51%股权，2024年收入8000万，净利润负。固体垃圾处理回收。 一季度收入持平，净利润减亏，主要是管理费用下降和毛利提高。 20250506，福建镍业完成工商变更。那这个时间算，全年能合并收入4500万，差不多够1亿 半年报收入下降到2500万，镍业公司并表650万，目前看还是有点危险的，但是公司存货里有半成品和未验收部分一共5000万，这部分如果在下半年验收就足够1亿了 三季报收入1亿，够了 | G36: 关注二季度合并镍业后的收入。主要原主业也大幅下降 | I36: 标准无保留意见 | J36: 标准无保留意见 | K36: 否 | M36: =N36+O36+P36+Q36+R36+S36+T36+U36+V36+W36 -> 50 | N36: 0 | O36: 0 | P36: 0 | Q36: 10 | R36: 40 | S36: 0 | T36: 0 | U36: 0 | V36: 0
A37: 2025 | B37: 668 | C37: 荣丰控股 | D37: 收入不足3亿 | E37: 收入超过3亿 公司今年以销售长春国金中心即可完成业绩 | F37: 一季度收入大涨，主要是房地产销售 三季报大增1.8亿 | G37: 关注二季度情况 | I37: 标准无保留意见 | J37: 标准无保留意见 | K37: 否 | M37: =N37+O37+P37+Q37+R37+S37+T37+U37+V37+W37 -> 10 | N37: 0 | O37: 0 | P37: 0 | Q37: 0 | R37: 10 | S37: 0 | T37: 0 | U37: 0 | V37: 0
A38: 2025 | B38: 2214 | C38: 大立科技 | D38: 收入不足3亿 | E38: 收入超过3亿 | F38: 20250110签订7100万研发合同。 一季度收入大涨，应该是因为2024年部分收入在一季度确认。 半年报收入大增至1.4亿，但还是危险 三季报大增2.6亿 | G38: 应收和存货都很高，财务有些问题。 | I38: 标准无保留意见 | J38: 标准无保留意见 | K38: 否 | M38: =N38+O38+P38+Q38+R38+S38+T38+U38+V38+W38 -> 10 | N38: 0 | O38: 0 | P38: 0 | Q38: 0 | R38: 10 | S38: 0 | T38: 0 | U38: 0 | V38: 0
A39: 2025 | B39: 820 | C39: 神雾节能 | D39: 收入不足退市风险 | E39: 20250110，持股49%表决权53%的子公司江苏院与其少数股东中清孚尧的子公司签订10亿合同，预期20260331完工。 | F39: 一季度收入大幅下降，净利润减亏 20250802，半年报收入大幅下降，净利润减亏 3亿合同150日内完成，20250819 大股东部分股权要被拍卖，如果全部拍卖完成，控制权可能变更，大股东看来自身难保 三季报略减9000万 | G39: 关注合同履行情况 | I39: 标准无保留意见 | J39: 标准无保留意见 | K39: 否 | M39: =N39+O39+P39+Q39+R39+S39+T39+U39+V39+W39 -> 10 | N39: 0 | O39: 0 | P39: 0 | Q39: 0 | R39: 0 | S39: 0 | T39: 0 | U39: 10 | V39: 0
A40: 2025 | B40: 2168 | C40: 惠程科技 | D40: 收入不足且净资产负 | E40: 净资产转正 收入超过3亿或利润转正 202105变更的控制权。 | F40: 20241010，大股东免除1亿债务 20241218,4700万购买锐恩医药51%股权，2024收入1.6亿，净利润2000万，净资产1600万 一季度收入大涨，利润减亏，主要是合并了锐恩医药，负资产还没进展 半年报医药收入1亿。净利润2300万 20250930，豁免了1.3亿债务，净资产转正。收入2.8亿，净利润大幅减亏 打算重整 20251229，重整投资人赠送3000万现金 | G40: 年终净资产还是可能变负 | I40: 标准无保留意见 | J40: 标准无保留意见 | K40: 否 | L40: 是 | M40: =N40+O40+P40+Q40+R40+S40+T40+U40+V40+W40 -> 6 | N40: 0 | O40: 0 | P40: 0 | Q40: 0 | R40: 1 | S40: 0 | T40: 5 | U40: 0 | V40: 0
A41: 2025 | B41: 972 | C41: 中基健康 | D41: 收入不足3亿且净资产负 | E41: 原来是六师国资 购买新业能化资产 | F41: 20250205，发行股份购买资产新业能化，购买资产后变更为新疆国资委，构成重组上市。净资产38亿，净利润5亿。但是重组上市太难了。 20250430，资产审计中 20250715终止购买资产，改为由新疆新业来重整公司 20251230，豁免1亿债务 | G41: 关注资产重组进展 | I41: 标准无保留意见 | J41: 标准无保留意见 | K41: 否 | L41: 是 | M41: =N41+O41+P41+Q41+R41+S41+T41+U41+V41+W41 -> 5 | N41: 0 | O41: 0 | P41: 0 | Q41: 0 | R41: 0 | S41: 0 | T41: 5 | U41: 0 | V41: 0
A42: 2025 | B42: 300561 | C42: 汇金科技 | D42: 收入不足1亿，差2000万，否定内控 | E42: 收入超过1亿或净利润转正 | F42: 一季度收入不变，净利润转正 半年报净利润略正 三季报净利润150万，收入7400万 | G42: 年终计提风险 | I42: 标准无保留意见 | J42: 否定意见 主要是业绩预告不准 | K42: 否 | M42: =N42+O42+P42+Q42+R42+S42+T42+U42+V42+W42 -> 5 | N42: 0 | O42: 0 | P42: 0 | Q42: 0 | R42: 0 | S42: 5 | T42: 0 | U42: 0 | V42: 0
A43: 2025 | B43: 2306 | C43: 中科云网 | D43: 收入不足3亿，差500万 | E43: 发展光伏组件业务，这个容易增加收入 但公司净资产也岌岌可危啊。 | F43: 一季度收入大涨，应该是光伏业务，按这个估计全年3亿无忧。净利润减亏，主要是管理费用大幅下降。 半年报预计收入1.5亿，净利润减亏不少，但净资产负更多了 三季报大增2亿 20251220，大股东赠送1亿+豁免债务5000万，净资产保住了 | G43: 关注净资产的改善 | I43: 重大段落无保留意见 重大段落：流动负债大于流动资产，持续经营不确定性 | J43: 标准无保留意见 | K43: 否 | M43: =N43+O43+P43+Q43+R43+S43+T43+U43+V43+W43 -> 3 | N43: 0 | O43: 0 | P43: 0 | Q43: 0 | R43: 13 | S43: -10 | T43: 0 | U43: 0 | V43: 0
A44: 2025 | B44: 603261 | C44: 立航科技 | D44: 收入不足3亿，差1000万 | E44: 收入超过3亿 | F44: 一季度收入大涨，净利润减亏 半年报收入大幅下降，净利润大幅下降，存货里发出商品有1.5亿 三季报不变1.4亿 | G44: 大股东被留置 | I44: 标准无保留意见 | J44: 标准无保留意见 | K44: 否 | M44: =N44+O44+P44+Q44+R44+S44+T44+U44+V44+W44 -> 0 | N44: 0 | O44: 0 | P44: 0 | Q44: 0 | R44: 0 | S44: 0 | T44: 0 | U44: 0 | V44: 0
A45: 2025 | B45: 929 | C45: 兰州黄河 | D45: 收入不足退市风险 | E45: 202411月变更实控人为鑫远股份（三板企业同时摘牌），已经完成。做水治理的，应收账款很差。而且实控人是因为纠纷所以成为大股东的。花了3个亿。 | F45: 2025半年报，收入没有改善，利润没有改善 20250904公告2600万购买果汁公司50%股权，2024年光四季度收入5500万，净利润300万，2025年7-8月收入1000万。还是差很多啊 三季报2.1亿了，抖音同增4000万，新公司并表1730，感觉有希望了 | H45: 壳价值也够低了 | I45: 标准无保留意见 | J45: 标准无保留意见 | K45: 是 | M45: =N45+O45+P45+Q45+R45+S45+T45+U45+V45+W45 -> 40 | N45: 10 | O45: 10 | P45: 0 | Q45: 0 | R45: 20 | S45: 0 | T45: 0 | V45: 0
A46: 2025 | B46: 605081 | C46: 太和水 | D46: 收入不足退市风险 | E46: 0331已经有新股东进入4亿，29.8，进入后肯定要保壳吧 目前看保壳难度大，不管是收入或利润都很难做。做利润基本没可能，计提肯定很大，除非把相关资产卖回给原大股东。 202409月尝试销售算力服务3.4亿规避营收不足的风险。但最后被按净额法结算了。且扣除在外。 | F46: 20241130收购北京中科砚云科技有限公司55%股权，2200万元，承诺2025年收入1.5亿 一季度收入没有增加 二季度收入没有增加，亏损扩大，北京中科砚云科技收入1600万 三季报下滑8000万 | G46: 关注新股东确认进入进展，已完成 | H46: 壳价值也够低了 | I46: 标准无保留意见 | J46: 标准无保留意见 | K46: 是 | M46: =N46+O46+P46+Q46+R46+S46+T46+U46+V46+W46 -> -10 | N46: 10 | O46: 10 | P46: 0 | Q46: 0 | R46: -30 | S46: 0 | T46: 0 | V46: 0 | Z46: 三季报
A47: 2025 | B47: 600243 | C47: 青海华鼎 | D47: 收入不足退市风险 | E47: 一季度大幅减亏 公司想转正利润的希望较难达成，年终的计提规模太大了。还是做大收入比较好实现。 | F47: 20241026，购买茫崖源鑫能源有限公司，天然气业务，能增加6000万收入，500万利润。 20250430，一季度大幅减亏是因为管理费用的大幅下降，而且原电梯件业务还在下滑，收入还是不够。 20250801收购鲁新鼎盛完成，年收入预计3500万 半年报收入没有变化，净利润大幅减亏 三季报不变1.9亿，大股东变更 | G47: 关注半年报 关注其他应收款的计提，主要是应收祥馨同佳的股权转让款余额 | H47: 壳价值也够低了 | I47: 标准无保留意见 | J47: 标准无保留意见 | K47: 否 | M47: =N47+O47+P47+Q47+R47+S47+T47+U47+V47+W47 -> 10 | N47: 10 | O47: 0 | P47: 0 | Q47: 0 | R47: 0 | S47: 0 | T47: 0 | U47: 0 | V47: 0 | Z47: 三季报
A48: 2025 | B48: 2808 | C48: 恒久科技 | D48: 收入不足退市风险 财务虚假 | E48: 20251227可以撤销财务虚假风险警示 考虑购买资产提升营业收入 | F48: 一季度收入没有改善 20250709收购上海憬芯科技并表，2024年收入720万，净利润-1000万，光伏系统管理业务，感觉是不是在掏空资产 半年报收入9000万，略增，主要光伏EPC收入1400万。 三季报1.8亿收入，还是有希望的 | G48: 关注购买资产情况 | H48: 壳价值也够低了 | I48: 强调事项段无保留意见 强调项：行政处罚刚下来。原子公司总经理职务侵占案还没结束 | J48: 标准无保留意见 | K48: 否 | M48: =N48+O48+P48+Q48+R48+S48+T48+U48+V48+W48 -> 10 | N48: 0 | O48: 0 | P48: 0 | Q48: 0 | R48: 10 | S48: 0 | T48: 0 | V48: 0
A49: 2025 | B49: 4 | C49: 国华网安 | D49: 收入不足退市风险 | E49: 20250418挂牌转让山东智游子公司，价格2000万，预计可以减少净利润损失700万，还未完成 软件开发，客户预算影响，正在下行期 研发、销售、管理三高吃掉了毛利 | F49: 20250521公告，山东智游网安转让失败，下调价格为1847万继续转让。 20250908转让成功，1500万左右，购买方资金来源于实控人关联方借款 20250930签订90天合同2.2亿 三季报收入下滑5000万，如果合同能确认，还是有希望，但是净资产可能变负 | G49: 关注保壳信号 | I49: 标准无保留意见 | J49: 标准无保留意见 | K49: 否 | M49: =N49+O49+P49+Q49+R49+S49+T49+U49+V49+W49 -> 0 | N49: 0 | O49: 0 | P49: 0 | Q49: 0 | R49: 0 | S49: 0 | T49: 0 | U49: 0 | V49: 0
A50: 2025 | B50: 2253 | C50: 川大智胜 | D50: 收入不足退市风险 | E50: 四川省财政厅将表决权委托给四川产业振兴基金投资集团有限公司，它将为公司赋能，为公司 2025年业绩做出贡献。 | F50: 一季度没有改善 半年报收入利润大幅下滑 大股东把股份质押给了四川产业公司 三季报收入7000万，净利润继续下滑，同时公布收购兴仁科技，1.5亿，上半年收入2000万，净利润279万，军工行业 | G50: 关注实控人是否随时变成四川国资委 | I50: 标准无保留意见 | J50: 标准无保留意见 | K50: 否 | M50: =N50+O50+P50+Q50+R50+S50+T50+U50+V50+W50 -> -10 | N50: 0 | O50: 0 | P50: 0 | Q50: 0 | R50: -10 | S50: 0 | T50: 0 | U50: 0 | V50: 0
A51: 2025 | B51: 2848 | C51: 高斯贝尔 | D51: 收入不足3亿，差1.7亿 2025年还有净资产负的风险 | E51: 收入超过3亿 净资产保正 | F51: 一季度收入净利润持平 半年报没变化 三季报略增1.5亿 | G51: 大股东股份被冻结 关注收入进展 | I51: 强调事项的无保留意见 强调事项：流动负债大于流动资产导致持续经营部确定性 | J51: 标准无保留意见 | K51: 否 | M51: =N51+O51+P51+Q51+R51+S51+T51+U51+V51+W51 -> 0 | N51: 0 | O51: 0 | P51: 0 | Q51: 0 | R51: 0 | S51: 0 | T51: 0 | U51: 0 | V51: 0
A52: 2025 | B52: 2693 | C52: 双成药业 | D52: 收入不足3亿，差1.4亿 | E52: 收入超过3亿或净利润转正 | F52: 本来202408收购大股东的半导体资产的，但是2250311终止了收购，因为某些交易方价格无法达成一致。 一季度收入和净利润略下滑。 半年报收入和利润没有改善 三季报收入1.6亿，净利润只亏600万了，有希望 | I52: 强调事项无保留意见 强调项：收入不足触发退市风险 | J52: 标准无保留意见 | K52: 否 | M52: =N52+O52+P52+Q52+R52+S52+T52+U52+V52+W52 -> 0 | N52: 0 | O52: 0 | P52: 0 | Q52: 0 | R52: 0 | S52: 0 | T52: 0 | U52: 0 | V52: 0
A53: 2025 | B53: 600355 | C53: 精伦电子 | D53: 收入不足3亿，差1.8亿 | E53: 收入超过3亿或净利润转正 | F53: 一季度收入下滑 签订2.3亿企业云服务器采购合同，上半年交付4500万 上半年收入8200万 三季报收入大增2.2亿 | I53: 标准无保留意见 | J53: 标准无保留意见 | K53: 否 | M53: =N53+O53+P53+Q53+R53+S53+T53+U53+V53+W53 -> 10 | N53: 0 | O53: 0 | P53: 0 | Q53: 0 | R53: 10 | S53: 0 | T53: 0 | U53: 0 | V53: 0 | Z53: 三季报
A54: 2025 | B54: 2496 | C54: 辉丰股份 | D54: 收入不足3亿，差6000万 | E54: 收入超过3亿，净利润转正太难了 | F54: 一季度收入净利润略增 半年报收入1.5亿，大幅增加。利润也减亏。主要是油品等收入增加，估计靠这个保壳问题不大。 三季报收入2.1亿，还有点悬 | G54: 每年都有大量的资产减值计提 | I54: 重大段落和强调事项的无保留意见 1、流动负债大于流动资产，持续经营不确定性 2、辉丰股份公司根据法院解散瑞凯公司的判决和法院关于5,000吨草铵膦项目为双方共同所有的再审裁定，重新估算了对瑞凯公司的债务金额和股权价值 | J54: 无保留意见 | K54: 否 | M54: =N54+O54+P54+Q54+R54+S54+T54+U54+V54+W54 -> 15 | N54: 0 | O54: 0 | P54: 0 | Q54: 0 | R54: 20 | S54: 0 | T54: 0 | U54: 0 | V54: -5
A55: 2025 | B55: 600421 | C55: 华嵘控股 | D55: 收入不足3亿，差1.8亿 | E55: 收入超过3亿或净利润转正 | F55: 一季度收入下滑、净利润下滑。 20250507，继续收购子公司浙江庄辰剩余34%股权，2024收入1.1亿，净利润500万。 半年报收入5500万，净利润-340万，浙江庄辰净利润15万 20250812，林木顺的海南伯程受让25%，4.5亿 三季报收入1亿，净利润-200万，有希望净利润转正，主要收入就是子公司的 20251030向新大股东借款750万 | G55: 估计做正利润的希望大些 | I55: 强调无保留意见。 强调项：触发退市风险 | J55: 标准无保留意见 | K55: 是 | M55: =N55+O55+P55+Q55+R55+S55+T55+U55+V55+W55 -> 5 | N55: 10 | O55: 0 | P55: 0 | Q55: 0 | R55: -2 | S55: -3 | T55: 0 | U55: 0 | V55: 0 | Z55: 三季报
A56: 2025 | B56: 2872 | C56: 天圣制药 | D56: 2019年大股东侵占挪用资金1.2亿未及时归还，大股东被判刑了 | E56: 归还资金 立案调查结果出来 上市后业绩一直在下滑，可能有财务造假 | F56: 2024年已经归还 20250119大股东被证监会立案调查，还没有结果。 20250913收到处罚，不用退市了 | G56: 关注立案调查结果 | I56: 保留意见 因大股东立案结果未出，未能就涉案及追溯调整事项获取充分、适当的审计证据，无法确定前述资金占用的完整性。 | J56: 标准无保留意见 | K56: 否 | M56: =N56+O56+P56+Q56+R56+S56+T56+U56+V56+W56 -> 0 | N56: 0 | O56: 0 | P56: 0 | Q56: 0 | R56: 0 | S56: 0 | T56: 0 | U56: 0 | V56: 0
A57: 2025 | B57: 603789 | C57: 星光农机 | D57: 收入不足退市风险 | E57: 20250318收购大股东旗下苏州电中，燃油喷射系统开发，2024收入8000万，净利润-100万。0426完成交易，一季度未并表。0426完成变更。 | F57: 一季度收入大涨，说是销量增加。 公司说审计师正在审计保留事项，后续会有公告 半年报收入1.5亿。大涨，其中苏州电中并表3000万。 20250906，购买中诚汽车子公司完成，1-5月收入1600万 三季报收入3亿 | G57: 被立案调查 关注保留事项的解决进展 | I57: 保留意见 采棉农事服务按总额法确认的依据不足，如果存在问题对2023年的收入调整较大。 董事会的解释是当时开展业务时保留的资料不够充分。还不知道怎么消除。 | J57: 标准无保留意见 | K57: 否 | M57: =N57+O57+P57+Q57+R57+S57+T57+U57+V57+W57 -> 0 | N57: 0 | O57: 0 | P57: 0 | Q57: 0 | R57: 40 | S57: 0 | T57: 0 | U57: 0 | V57: -40 | Z57: 三季报
A58: 2025 | B58: 300159 | C58: 新研股份 | D58: 净资产负 | E58: 净资产转正 | F58: 20250428，与新疆资管重组9800万的债务。以股权抵债。 重整中 | I58: 强调无保留意见 净资产负持续经营不确定性 | J58: 标准无保留意见 | K58: 否 | L58: 是 | M58: =N58+O58+P58+Q58+R58+S58+T58+U58+V58+W58 -> -20 | N58: 0 | O58: 0 | P58: 0 | Q58: 0 | R58: 0 | S58: 0 | T58: 0 | U58: 0 | V58: -20
A59: 2025 | B59: 638 | C59: 万方发展 | D59: 收入不足退市风险 | E59: 历史上保壳过一次。通过做正利润的方式。 大股东的29%股份被判出售以偿还债务，可能会导致实控人变更，现在的实控人只是拥有投票权 长期股权投资公司连连亏损，审计师无法核实剩余价值，出具带强调事项。 2023年曾经由于银行不续贷导致债务逾期 | F59: 一季度收入大增 白山市原来的承诺基本都没有兑现，所以是否愿意保壳存疑 原大股东股份抵债给九台农商行了 三季报收入1.7亿，大增，净利润-900万 | G59: 不确定收入是不是全部是主营 关注对长期股权万方百奥投资的处理情况，这个必须要处理（建仓时点） 关注大股东质押违约的处理，实控人是否成功受让违约股票的债权 关注现在实控人满3年，可以注入资产 | H59: 壳价值也够低了 | I59: 强调事项段保留意见 保留项：万方百奥的不确定性 强调项：原大股东质押的股份可能被拍卖导致实控人变更 | J59: 标准无保留意见 | K59: 否 | M59: =N59+O59+P59+Q59+R59+S59+T59+U59+V59+W59 -> -20 | N59: 0 | O59: 0 | P59: 0 | Q59: 0 | R59: 20 | S59: 0 | T59: 0 | U59: 0 | V59: -40
A60: 2025 | B60: 603398 | C60: 沐邦高科 | D60: 收入不足3亿 否定意见内控报告 | E60: 内控报告否定意见修正 收入超过3亿 | F60: 一季度收入净利润大幅下滑 三季报略下滑收入2.2亿 实控人被立案，资金占用1000万 | G60: 关注二季度情况 关注内控否定事项 | I60: 强调事项的无保留意见 强调事项：流动负债大于流动资产导致持续经营部确定性 | J60: 否定意见 将募集资金以支付供应商货款或工程款的形式付款后，再通过关联企业借款的形式回流到沐邦高科，沐邦高科用来归还银行借款和供应商欠款，涉及金额 2亿，导致募集资金违规使用 | K60: 否 | M60: =N60+O60+P60+Q60+R60+S60+T60+U60+V60+W60 -> -30 | N60: 0 | O60: 0 | P60: 0 | Q60: 0 | R60: -10 | S60: 0 | T60: 0 | U60: 0 | V60: -20
A61: 2025 | B61: 600238 | C61: 海南椰岛 | D61: 收入不足3亿 否定意见内控报告 | E61: 收入超过3亿 解决与糊涂酒业之间的账目问题 | F61: 一季度收入下滑、净利润减亏 半年报收入下滑，净利润增亏 三季报收入不变1.7亿，净资产也很危险了 | G61: 关注与糊涂酒业之间的合作进展 关注收入进展 | I61: 强调事项的保留意见 跟糊涂酒业之间的糊涂账 持续经营不确定性 | J61: 否定意见 经销商管理不明确 总经理一身多职不合理 | K61: 否 | M61: =N61+O61+P61+Q61+R61+S61+T61+U61+V61+W61 -> -30 | N61: 0 | O61: 0 | P61: 0 | Q61: 0 | R61: -10 | S61: 0 | T61: 0 | U61: 0 | V61: -20 | Z61: 三季报
A62: 2025 | B62: 600696 | C62: 岩石股份 | D62: 收入不足3亿，差2000万 | E62: 收入超过3亿 解决保留事项 | F62: 一季度收入净利润大幅下滑 二季度收入净利润继续大幅下滑 三季报收入大幅下滑3400万，基本完了 | G62: 关注保留事项的解决 收入的解决 | I62: 保留意见 1、债务违约的诉讼未完结，涉及金额巨大，无法审计。 2、3亿多存货被查封，无法审计。 3、关联交易的合理性无法确认，与经销商的大量交易合法性待查。 | J62: 强调事项无保留意见 | K62: 否 | M62: =N62+O62+P62+Q62+R62+S62+T62+U62+V62+W62 -> -50 | N62: 0 | O62: 0 | P62: 0 | Q62: 0 | R62: -30 | S62: 0 | T62: 0 | U62: 0 | V62: -20
A63: 2025 | B63: 2231 | C63: 奥维通信 | D63: 收入不足3亿，差2000万 无法表示意见 否定意见 | E63: 收入超过3亿或净利润转正 | F63: 一季度收入和净利润大幅下降 半年报没有变化 三季报收入3000万，基本摆烂了 | G63: 大股东资金占用1.9亿的归还进展。 主要子公司金属制品业务复产情况。 部分销售业务的合理性存疑的解决。 | I63: 无法表示意见 | J63: 否定意见 | K63: 否 | M63: =N63+O63+P63+Q63+R63+S63+T63+U63+V63+W63 -> -50 | N63: 0 | O63: 0 | P63: 0 | Q63: 0 | R63: -20 | S63: 0 | T63: 0 | U63: 0 | V63: -30
A64: 2025 | B64: 600608 | C64: ST沪科 | D64: 收入不足3亿，差2.2亿 | E64: 收入超过3亿 | F64: 半年报收入大幅下滑 三季报收入500万，净利润-23万，感觉可以靠净利润保住 | K64: 否 | M64: =N64+O64+P64+Q64+R64+S64+T64+U64+V64+W64 -> -40 | N64: 0 | O64: 0 | P64: 0 | Q64: 0 | R64: -20 | S64: -20 | T64: 0 | U64: 0 | V64: 0 | Z64: 三季报
A65: 2025 | B65: 600193 | C65: 创兴资源 | D65: 收入不足3亿，差2.2亿 2025年还有净资产负的风险 | E65: 收入超过3亿 净资产保正 | F65: 一季度收入净利润暴跌 二季度收入大幅下跌，净利润也是 三季报收入1800万 | G65: 公司感觉快倒闭了 关注收入改善进展，负债改善进展 20250717，王相荣拍卖15%股权成为大股东，利欧集团股份的老板 20250812转让建设工程子公司3400万，净资产也是3400万。 | I65: 强调事项的无保留意见 强调事项：流动负债大于流动资产导致持续经营部确定性 强调事项2：大股东股份被冻结，控股权可能变更 | J65: 标准无保留意见 | K65: 是 | M65: =N65+O65+P65+Q65+R65+S65+T65+U65+V65+W65 -> -50 | N65: 10 | O65: 10 | P65: 0 | Q65: 0 | R65: -30 | S65: -40 | T65: 0 | U65: 0 | V65: 0 | Z65: 三季报
A66: 2025 | B66: 600599 | C66: 熊猫金控 | D66: 无法表示意见审计报告 | E66: 小贷业务清理 违规担保解除 提供烟花采购应收款计提理由 | F66: 一季度收入下滑净利润下滑 三季报收入1.5亿，净利润1000万 | G66: 关注审计报告相关事项 感觉大股东在掏空公司资产 | I66: 无法表示意见 | J66: 否定意见 | K66: 否 | M66: =N66+O66+P66+Q66+R66+S66+T66+U66+V66+W66 -> -40 | N66: 0 | O66: 0 | P66: 0 | Q66: 0 | R66: 0 | S66: 0 | T66: 0 | U66: 0 | V66: -40
A67: 2025 | B67: 300225 | C67: 金力泰 | D67: 无法表示意见审计报告 | E67: 归还占用资金，加强内控 | F67: 20250506被立案调查 20250916结案 公司董事会还在极力狡辩，但审计委员会已经承认。 | I67: 无法表示意见 1、以战略备库预付款名义将资金转出至相关贸易商后，贸易商又在邻近时间点将相近金额转出至非供货主体的异常情形。转出资金与实际采购金额严重不成比例。2024 年你公司战略备库预付款发生额及取消合作转回款项均超过 9 亿元，但实际采购金额仅 2,900 余万元 3.你公司与相关贸易商的资金往来呈现季度初转出和季度末转回的显著特征，累计转出金额与转回金额大体相当。你公司资金存在以战略备库名义转出后被关联方占用的重大风险 2、股权转让无法确认是否资金占用 | J67: 否定意见 | K67: 否 | M67: =N67+O67+P67+Q67+R67+S67+T67+U67+V67+W67 -> -40 | N67: 0 | O67: 0 | P67: 0 | Q67: 0 | R67: 0 | S67: 0 | T67: 0 | U67: 0 | V67: -40
A68: 2025 | B68: 300716 | C68: 泉为科技 | D68: 持续经营不确定性 | F68: 20250414打算出售子公司安徽泉为，净资产1.6亿，售价2.7亿，购买方上海赢古资产，专门做不良资产处理的。 20250826半年报，收入净利润大幅下滑，安慰泉为收入800万，净利润-1800万。 20250826签订11亿大合同，工期12月，联合中标
A69: 2025 | B69: 300313 | C69: 天山生物 | D69: 净资产负且营收不足1亿且净利润负 | E69: 净资产转正且营收达到1亿 | F69: 20250829，陈明艺、陈欢的厦门舍德拍卖17.21%，花费2.87亿。旗下有谷味德食品有限公司，还持有傲农生物3%股份。 20250920，大股东豁免了5000万债务，净资产负的问题解决了 20251025，向大股东转让亏损子公司巴尔鲁克 20251025，三季报显示业绩还没有进展，收入还差4000万，但存货大增了4000万。 | G69: 实控人喜欢持有养殖公司 公司从原大股东收回的7300万股份要注销，但还没完成 | I69: 强调事项的无保留意见 强调事项：流动负债大于流动资产导致持续经营部确定性 | J69: 标准无保留意见 | K69: 否 | M69: =N69+O69+P69+Q69+R69+S69+T69+U69+V69+W69 -> 20 | N69: 10 | O69: 10 | P69: 0 | Q69: 0 | R69: 0 | S69: 0 | T69: 0 | U69: 0 | V69: 0
A70: 2025 | B70: 600381 | C70: 青海春天 | D70: 收入不足3亿 | E70: 营收达标 | F70: Q3财报2.12亿，净利润大幅减亏 | I70: 标准无保留意见 | J70: 标准无保留意见 | K70: 否 | M70: =N70+O70+P70+Q70+R70+S70+T70+U70+V70+W70 -> 10 | N70: 0 | O70: 0 | P70: 0 | Q70: 0 | R70: 10 | S70: 0 | T70: 0 | U70: 0 | V70: 0 | W70: 0 | X70: 0 | Z70: 三季报
A71: 2025 | B71: 2713 | C71: 东易日盛 | D71: 净资产负 | E71: 净资产转正 | L71: 是
A72: 2025 | B72: 2200 | C72: 交投生态 | D72: 净资产负 | E72: 净资产转正 | L72: 是
A73: 2025 | B73: 300093 | C73: 金刚光伏 | D73: 净资产负 | E73: 净资产转正 | L73: 是
A74: 2025 | B74: 908 | C74: 景峰医药 | D74: 净资产负 | E74: 净资产转正 | L74: 是
A75: 2025 | B75: 697 | C75: 炼石航空 | D75: 净资产负 | E75: 净资产转正 | L75: 是
A76: 2025 | B76: 300125 | C76: 聆达股份 | D76: 净资产负 | E76: 净资产转正 | L76: 是
A77: 2025 | B77: 615 | C77: 奥园美谷 | D77: 净资产负 | E77: 净资产转正 | L77: 是
A78: 2025 | B78: 300506 | C78: 名家汇 | D78: 净资产负 | E78: 净资产转正 | L78: 是
A79: 2025 | B79: 600165 | C79: 宁夏中科生物 | D79: 净资产负 | E79: 净资产转正 | L79: 是
A80: 2025 | B80: 2742 | C80: 三圣股份 | D80: 净资产负 | E80: 净资产转正 | L80: 是
A81: 2025 | B81: 300472 | C81: 新元科技 | D81: 净资产负 否定意见 | E81: 净资产转正 | F81: 净资产也负了 三季报收入6800万 20251226，大股东豁免5000万债务 | L81: 是
A82: 2025 | B82: 300391 | C82: 长药控股 | D82: 净资产负 | E82: 净资产转正 | L82: 是
A83: 2026 | B83: 603825 | C83: 华扬联众 | D83: 净资产负 | G83: 主营品牌营销 | M83: =N83+O83+P83+Q83+R83+S83+T83+U83+V83+W83 -> 5 | T83: 5
A84: 2026 | B84: 603557 | C84: 起步股份 | D84: 收入不足3亿、净资产负 | F84: 20251129，大股东捐赠佛山鹏昌企业80%股权，核心资产是广西天丞铝业51%，2025年净资产4000万，收入5亿，净利润1295万，如果完成的话2026年收入肯定达标了 | G84: 鞋服 | M84: =N84+O84+P84+Q84+R84+S84+T84+U84+V84+W84 -> 20 | Q84: 20
A85: 2026 | B85: 600265 | C85: 景谷林业 | D85: 收入不足3亿、净资产负 | F85: 20250816向大股东剥离汇银木业51%股权，大概1.3亿，占2024年度收入87% 202511，大股东赠送博达数科51%，月收入600万 | M85: =N85+O85+P85+Q85+R85+S85+T85+U85+V85+W85 -> 0
A86: 2026 | B86: 603021 | C86: 华鹏 | D86: 净资产负 | M86: =N86+O86+P86+Q86+R86+S86+T86+U86+V86+W86 -> 5 | T86: 5
A87: 2026 | B87: 600107 | C87: 美尔雅 | D87: 收入不足3亿 | G87: 服装纺织 | M87: =N87+O87+P87+Q87+R87+S87+T87+U87+V87+W87 -> 0
A88: 2026 | B88: 300237 | C88: 美晨科技 | D88: 净资产负 | F88: 20250422，园林资产剥离预案 202512，转让很多债权给大股东 | G88: 汽车零部件 | M88: =N88+O88+P88+Q88+R88+S88+T88+U88+V88+W88 -> 5 | T88: 5
A89: 2026 | B89: 2528 | C89: 英飞拓 | D89: 净资产负 | F89: 20251210，挂牌转让子公司英飞拓杭州科技，净资产-1300万，价格1元，购买人还需要代还1.3亿的债务 | G89: 物联软件 | M89: =N89+O89+P89+Q89+R89+S89+T89+U89+V89+W89 -> 0
A90: 2026 | B90: 2581 | C90: 未名医药 | D90: 收入不足3亿 | G90: 生长因子
A91: 2026 | B91: 300716 | C91: 泉为科技 | D91: 净资产负 | F91: 20250414，向上海赢古资产管理有限公司出售合计持有的安徽泉为100%股权，净资产1.7亿，负债2.1亿，出售价格2.7亿 | G91: 光伏
A92: 2026 | B92: 603959 | C92: 百利科技 | D92: 净资产负 | G92: 大股东破产清算，可能导致实控人变更
A93: 2026 | B93: 2856 | C93: 美芝股份 | D93: 净资产负 | E93: 负得不多 | F93: 20251014，挂牌转让子公司51%股权，净资产-4400万，收入1.3亿。价格102万 20251230，转让完成 20260430，Q1大幅减亏 | G93: 建筑工程施工 | I93: 持续经营无保留 | J93: 持续经营无保留 | M93: =N93+O93+P93+Q93+R93+S93+T93+U93+V93+W93 -> 7 | P93: 2 | T93: 5
A94: 2026 | B94: 890 | C94: 法尔胜 | D94: 收入不足3亿、净资产负 | F94: 20251023，出售一个10%股权，7000万，回笼资金 | G94: 金属制品
A95: 2026 | B95: 300385 | C95: 雪浪环境 | D95: 净资产负 | G95: 垃圾发电，固废处理 | L95: 是
A96: 2026 | B96: 692 | C96: 惠天热电 | D96: 净资产负 | F96: 2024年就差点负了，靠大股东输血了好几亿 | G96: 供暖供气
A97: 2026 | B97: 2513 | C97: 蓝丰生化 | D97: 净资产负 | F97: 20250904，大股东豁免债务2300万 | G97: 光伏
A98: 2026 | B98: 300340 | C98: 科恒股份 | D98: 净资产负 | F98: 20251127，一个子公司的债务转股权，化解了2亿债务，那净资产应该正了 | G98: 正极材料
A99: 2026 | B99: 56 | C99: 皇庭国际 | D99: 净资产负 | F99: 2022年的债务重组终止了 | G99: 物业管理 | I99: 无法表示意见 主要还是经营不确定 | J99: 标准无保留 | M99: =N99+O99+P99+Q99+R99+S99+T99+U99+V99+W99 -> 0
A100: 2026 | B100: 600322 | C100: 津投城开 | D100: 净资产负 | F100: 2025年打算跟大股东置换热力资产的，后改为出售房地产资产 | G100: 房地产开发 | T100: 5
...

Sheet 重整
C1: 法院 | D1: 被债权人申报 | E1: 临时管理人 | F1: 债权申报 | G1: 招募产业投资人 | H1: 确定投资人 | I1: 签署重整协议 | J1: 中间进展 | K1: 是否立案调查 | L1: 批准时带星 | M1: 法院批准受理重整 | N1: 重整债权申报 | O1: 重整计划批准 | P1: 转增股本实施 | Q1: 结果 | R1: 刚兑上限 | S1: 批准受理后走势 | U1: 批准时市值 | V1: 除权后下跌
A2: 2822 | B2: ST中装 | C2: 深圳中院 | D2: 20240622 | F2: 20240808 | H2: 20250228 | I2: 20250307，康恒环境，净资产116亿，净利润13亿，生活垃圾发电。转增10亿股，1.55元 产投3.04亿股，占16% | L2: 否 | M2: 20250820 | N2: 20250822 | R2: 5 | S2: 下跌 | U2: 35
A3: 300391 | B3: 长药控股 | C3: 十堰中院 | D3: 20250121 | E3: 上海市锦天城律师事务所 | F3: 20250123 | G3: 20250123 | H3: 24家报名，20250506四川嘉道博文生态科技有限公司、十堰市昊炜生物科技发展有限公司 | I3: 20250508 转增5.2亿，2.42/股。 嘉道博文：5.9亿 昊伟生物：2500万 抵债价格：不低于10元 | J3: 必须在2025年底之前重整完成，否则就要退市 审计都OK的 股价一直跌，是不是因为重大的诉讼一直没停。 可能被立案调查 | K3: 是 | Q3: 失败
A4: 2742 | B4: 三圣股份 | C4: 重庆五中院 | D4: 20240928 | G4: 20240930 | H4: 冀衡集团药业的 | I4: 1.53元，转赠2.5亿股 1.6亿给投资人 | L4: 是 | M4: 20250809 | N4: 20250813 | R4: 5 | S4: 下跌 | U4: 26
A5: 2713 | B5: 东易日盛 | C5: 北京一中院 | D5: 20241018 | E5: 20241107北京大成律师事务所 | F5: 20241109 | G5: 20241130 | H5: 15家产投、25家财投。20250319，北京华著科技有限公司，智算中心 | I5: 20250319 财投8亿，2.6亿股，后修改为4元一股，因此估计大涨 产投：2.3元，1.5亿股，3.4亿 | M5: 20251119
A6: 300117 | B6: 嘉寓股份 | C6: 北京一中院 | D6: 20240603 | E6: 20240718北京市海问律师事务所 | F6: 20240717 | G6: 20240717 | H6: 20240913北京道荣合利科技集团有限公司和北京久银投资控股股份有限公司组成的联合体 | I6: 20240927 | J6: 20241021，原财务投资人全部退出，引入新财务投资人，且减少财务投资份额 20241114，产业投资人解除重整协议，理由是预计公司无法在可见时间内完成前置审批 | Q6: 失败
A7: 300125 | B7: 聆达股份 | C7: 六安中院 | D7: 20240731 | E7: 20240731金寨县人民政府组建的清算小组 | F7: 20240802 | G7: 20240923 | H7: 20241128 浙江众凌科技有限公司和合肥威迪变色玻璃有限公司联合体，半导体的 | I7: 转赠4亿股 财投价3.87 | J7: 中途有财投退出，重新引入 | L7: 是 | M7: 20251118
A8: 2200 | B8: ST交投 | C8: 昆明中院 | D8: 20250424 | E8: 20250605上海市通力律师事务所（主办机构）与国浩律师（昆明）事务所（辅助机构），临时管理人负责人为刘嘉诚律师。 | F8: 20250606-20240705 | G8: 20250614 要求产投资金总额超500亿，净额200亿，这典型的量身定制 | H8: 大股东自己重整自己，真恶心10转14.5共2.6亿股 | I8: 产投：3.87元，3500万股 财投：4.67元，1.68亿股 | J8: 必须在2025年底之前重整完成，否则就要退市 审计都OK的 | L8: 是 | M8: 20251024 | N8: 20251024 | S8: 下跌
A9: 430 | B9: 张家界 | C9: 张家界中院 | D9: 20241018 | E9: 张家界旅游集团有限公司清算组 | F9: 20241029 | G9: 20241029 | H9: 电广传媒和芒果超媒等财投，没有产投，所以原来的还是大股东 | I9: 财投，3.96元，3.225亿股 财投2，7.3元，0.41亿股 | L9: 否 | M9: 20251103
A10: 300209 | B10: 有棵树 | C10: 长沙中院 | D10: 20240220 | E10: 有棵树科技股份有限公司清算组 | F10: 20240315 | G10: 20240830 | H10: 46家，产投3家 | I10: 20241116，深圳市天行云供应链、福建纵腾网络有限公司 1.85亿转增股票，3.6亿，单价1.95。2.3亿股留给财投。7000万抵债，10元。刚兑上限100万。 | J10: 20241212，与财投签署协议 | M10: 20240930 | N10: 20241008 | O10: 20241207 | P10: 2241219 | Q10: 成功 | R10: 100 | S10: 上涨 | U10: 18
A11: 2217 | B11: 合力泰 | C11: 福州中院 | D11: 20240305 | E11: 合力泰科技股份有限公司清算组 | F11: 20240312 | G11: 20240511 | H11: 没有，不需要 | I11: 20241130 | M11: 20241125 | N11: 20241130 | O11: 20241224 | P11: 20241225 | Q11: 成功 | R11: 0 | S11: 下跌 | U11: 84
A12: 600375 | B12: 汉马科技 | C12: 马鞍山中院 | D12: 20240127 | M12: 20241109 | O12: 20241212 | Q12: 成功 | R12: 10 | S12: 下跌
A13: 603363 | B13: 傲农生物 | C13: 漳州中院 | D13: 20240323 | M13: 20241106 | O13: 20241211 | Q13: 成功 | R13: 35 | S13: 横盘 | U13: 34
A14: 2124 | B14: 天邦食品 | C14: 宁波中院 | D14: 20240319 | H14: 20250509厦门建发物产有限公司联合体 | I14: 产投：1.85元，2亿股 财投：2.1元，1亿股
A15: 2325 | B15: 洪涛股份 | C15: 深圳中院 | D15: 20240130 | E15: 20240430 | F15: 20240529 | G15: 20240531 | J15: 20240731不予受理 | Q15: 失败
A16: 656 | B16: 金科股份 | C16: 重庆五中院 | D16: 20230523 | M16: 20240423 | O16: 20250512
A17: 908 | B17: 景峰医药 | C17: 龙口法院 | D17: 20231102 | E17: 20231118 | G17: 20240802，招募条件里就感觉是因人而设，提前已经有沟通了 | H17: 20240828石药集团 | I17: 20250429 石药集团，8.7亿股，1元/股，石药5.26亿股 | L17: 否 | M17: 20251022 | S17: 上涨
A18: 300506 | B18: 名家汇 | C18: 深圳中院 | D18: 20240731 | G18: 20240910 | H18: 20241129，新余领九投资管理中心 | I18: 20250228，7.3亿股，1.47元 | L18: 否 | M18: 20250930
A19: 300338 | B19: 开元教育 | C19: 长沙中院 | D19: 20240629 | E19: 上海市方达律师事务所 | G19: 20241024 | H19: 20241105深圳嘉道功程股权投资基金 | I19: 20241105，6亿股，1.15元
A20: 600165 | B20: 宁夏中科生物 | C20: 石嘴山中院 | D20: 20240423 | E20: 20240601 | F20: 20240608 | G20: 20240614 | H20: 20241228湖南醇投实业发展有限公司 | I20: 产投：1.12元，3.5亿股 财投：1.6，5.2亿股 | L20: 否 | M20: 20250917 | S20: 上涨 | U20: 26
A21: 600811 | B21: 东方集团 | C21: 哈尔滨中院 | D21: 20240626 | E21: 20240808 | F21: 20240809 | G21: 20240723 | H21: 14家 | J21: 被立案调查，可能触发重大违法退市 | Q21: 失败
A22: 603007 | B22: 花王 | C22: 镇江中院 | D22: 20220429 | G22: 20220525 | H22: 20230130金华辰顺浩景企业管理合伙企业 | I22: 20241115 | K22: 1.5 | M22: 20240910 | O22: 20241116 | P22: 20241220 | Q22: 成功 | R22: 3 | S22: 上涨 | T22: 等了太久才批准所以大涨 | U22: 24
A23: 525 | B23: 红太阳 | C23: 南京中院 | D23: 20220920 | E23: 20221207 | F23: 20221208 | G23: 20221215 | H23: 20240222曲靖高新技术产业开发区 | M23: 20240918 | N23: 20240919 | O23: 20241102 | P23: 20241112 | Q23: 成功 | R23: 0 | S23: 上涨 | T23: 为什么后面又大跌呢 | U23: 48 | V23: 是，还有否定内控帽子没摘
A24: 300093 | B24: 金刚光伏 | C24: 酒泉中院 | D24: 20240708 | F24: 20250919 | H24: 欧昊集团，4.96,3亿 | I24: 20250610 | J24: 必须在2025年底之前重整完成，否则就要退市 审计都OK的 | L24: 是 | M24: 20250919 | R24: 10
A25: 300091 | B25: 金通灵 | C25: 南通中院 | D25: 20250331 | F25: 20250419 | G25: 20250407 | H25: 汇通达网络股份有限公司，香港上市 | I25: 20250906 1.3996元，7亿股，10亿元 | J25: 无资金占用，有一个投资者虚假陈述纠纷 | L25: 否 | M25: 20260101
A26: 615 | B26: 奥园美谷 | C26: 襄阳中院 | D26: 20241119 | F26: 20241206 | G26: 20241214 | H26: 20250423九州通 | I26: 20250424 九州通1.62元，4.35亿股，7亿 天津信美1.62元，1.21股，2亿 财投1，2.08元，0.42亿股，0.88亿 财投2，2.08元，0.96亿股，2亿元 财投3，2.08元，0.32亿股，0.67亿元 财投4，2.08元，0.54亿股，1.2亿元 财投5，2.08元，0.6亿股，1.2亿元 财投6，2.08元，0.18亿股，0.37亿元 | J26: 必须在2025年底之前重整完成，否则就要退市 审计都OK的 20250726，跟京汉控股的官司输了，很可能被动形成控股股东担保从而导致资金占用，资金占用不能及时消除会影响重整受理 | K26: 否 | L26: 是 | M26: 20251114 | S26: 下跌
A27: 300159 | B27: 新研股份 | C27: 乌鲁木齐中院 | D27: 20250603 | E27: 北京市金杜律师事务所和新疆巨臣律师事务所 | G27: 20250612 | H27: 20250701新疆商贸物流（集团）有限公司 | I27: 20250827，转赠17.94亿股 产投1.3元，5亿股，6.5亿元 | J27: 必须在2025年底之前重整完成，否则就要退市 审计都OK的 | L27: 是 | M27: 20251114 | S27: 下跌
A28: 793 | B28: 华闻集团 | C28: 海口中院 | D28: 20241022 | E28: 华闻集团清算组担 | F28: 20241101 | G28: 20241226 | H28: 20250506海南联合及海南国资运营 | I28: 20250506，5亿股，1.22元 | J28: 还可以拖到明年
A29: 752 | B29: 西藏发展 | C29: 拉萨中院 | D29: 20230721 | E29: 上海锦天城律师事务所 | F29: 20230801 | G29: 20230909 | H29: 20230927西藏盛邦发展有限公司，这个就是现在大股东啊。公司历史问题太混乱了。 | J29: 20231117被立案调查，已经处罚，存在资金占用 20231219，大股东豁免了1.9亿债务所以净资产转正 20250115，大股东又捐赠了1.8亿。到目前，还有原大股东资金占用问题未解决。 | L29: 否 | M29: 20260427
A30: 300147 | B30: 香雪制药 | C30: 广州中院 | D30: 20250206 | E30: 京市金杜(广州)律师事务所 | F30: 20250416 | G30: 20260422 | J30: 无保留意见 | L30: 否
A31: 2620 | B31: 瑞和股份 | C31: 深圳中院 | D31: 20250218 | E31: 佛山市贝思特会计师事务所有限公司 | F31: 20250726 | H31: 深圳市槟城电子股份有限公司，半导体元器件 | I31: 20260515 转赠5.6亿股 产投，2.4亿股，3.9元，9亿 财投，2.3亿股，3.9元 债权人，0.8亿股 | J31: 可能要放到明年去了，因为目前还没有戴星，明年肯定戴星了
A32: 300198 | B32: 纳川股份 | C32: 泉州中院 | D32: 20250318 | E32: 纳川管材科技股份有限公司清算组 | F32: 20250325 | I32: 1.25元，2.7亿元，还有另外两个一致行动人2.2亿元
A33: 851 | B33: 高鸿网络 | C33: 贵阳中院 | D33: 20240712 | F33: 20240824 | G33: 20240820 | J33: 20240730被立案调查 20250808触及重大违法退市 | Q33: 失败
A34: 972 | B34: 中基健康 | C34: 六师中院 | D34: 20250730 | F34: 20250730 | G34: 20250805 | H34: 20250912 | I34: 20250912，8.5亿股，1.81元，新业集团5亿配2.7亿股。财投2.52元，2.85亿股，剩下的债转股 | J34: 重整前本来要发行股份购买新业集团下的新疆新业能源化工有限责任公司的，后来终止了，因这个是借壳上市，估计太难了，放弃了。化工2024收入25亿，净利润5亿。目前先重整保壳，然后再择机注入资产
A35: 300472 | B35: 新元科技 | C35: 抚州中院 | D35: 20250630 | E35: 上海市锦天城律师事务所 | F35: 20250704 | G35: 20250728 | J35: 必须重整成功，否则退市
A36: 691 | B36: 亚太实业 | C36: 兰州中院 | D36: 20250712 | E36: 清算组 | F36: 20250712 | G36: 20250806 | H36: 20250909北京星箭长空测控技术股份有限公司 | I36: 20250913，4亿，1.6亿股，产投2.4元，财投2.65元 | J36: 原实控人跟现实控人打架，后和解。转让股份，用钱堵嘴。 | L36: 是 | M36: 20251126 | Q36: 成功
A37: 2168 | B37: 惠程信息 | C37: 重庆五中院 | D37: 20250804 | F37: 20250809 | G37: 20250809 | H37: 20250902植恩生物技术股份有限公司，净资产16亿，净利润4000万，收入11亿 | I37: 20250911 转赠3.7亿股 产投2.3亿股，1.735元，4亿元 财投0.57亿股，1.835元，1亿元 | J37: 获债权人豁免1.3亿债务 20250929，确认债权7.6亿
A38: 300256 | B38: 星星科技 | C38: 萍乡中院 | D38: 20210818 | E38: 萍乡市人民政府有关部门人员组成的清算组，上海市锦天城律师事务所 | F38: ,20250826 | G38: 20210910 | H38: 20220712浙江立马科技有限公司 承诺24月内注入部分电动车资产，36月内全部注入 12月内在萍乡建设电动车制造集群，三年内净利润不低于1.2亿 | I38: 转赠13.1亿股 产投6亿股，0.75元，4.5亿元 财投1.5亿股，1.5元，2.25亿元 | J38: 20210821被实施退市风险，因为财务纠正后2020年净资产为负 20211204大股东捐赠资产 20211221大股东豁免债务25亿 20211130重大子公司破产清算减少大量债务 经过上面几个手段，净资产终于转正了 20210929被立案调查 20221118处罚落地，2019和2020严重造假 | K38: 是 | M38: 20220526 | N38: 20220713 | O38: 20220804 | P38: 20220825 | Q38: 成功 | R38: 20 | S38: 横盘 | T38: 该案例只有保壳阶段有利润 | U38: 28
A39: 600654 | B39: 中安科 | C39: 武汉中原 | D39: 20211225 | E39: 公司清算组 | F39: 20220707 | G39: 20250804 | H39: 武汉融晶 | I39: 转赠15.26亿股 产投： | M39: 20221105 | N39: 20221105 | O39: 20221207 | P39: 20221207 | Q39: 成功 | R39: 6 | S39: 上涨
A40: 697 | B40: 炼石航空 | C40: 成都中院 | D40: 20250103 | E40: 北京金杜（成都）律师事务所 | G40: 20250621 | H40: 20250911联合体 | I40: 10转6，转增5.2亿股 产投：5.65元，0.97亿股，5.48亿 产投：6.73元,0,97亿股，6亿 | L40: 否 | M40: 20250923 | N40: 20250923 | R40: 50 | S40: 横盘
A41: 826 | B41: 启迪环境 | C41: 宜昌中院 | D41: 20250929 | E41: 公司清算组 | F41: 20250929 | G41: 20250929
A42: 300044 | B42: 赛为 | C42: 深圳中院 | D42: 20250723 | E42: 深圳市正源清算事务有限公司 | F42: 20250724
A43: 688033 | B43: 天宜新材 | C43: 北京一中院 | D43: 20251115 | E43: 北京市海问律师事务所
A44: 603377 | B44: 东方时尚 | C44: 北京一中院 | D44: 20250710 | E44: 清算组 | H44: 复利产业发展 | I44: 1.34元，5亿股，6.7亿元 | J44: 立案调查落地，否定内控，主要是之前的资金占用，已解决 有可转债 | K44: 是 | R44: 15
A45: 603398 | B45: 沐邦股份 | C45: 南昌中院 | D45: 20251115 | E45: 清算组 | J45: 立案调查，否定内控 经营资金占用9000万
A46: 300385 | B46: 雪浪环境 | C46: 无锡中院 | D46: 20251119 | J46: 20251231，大股东代还银行的1.5亿借款
A47: 600340 | B47: 华夏幸福 | C47: 廊坊中院 | D47: 20251117 | E47: 清算组
A48: 301030 | B48: 仕净科技 | C48: 苏州中院 | D48: 20260511 | E48: 徽宁芯破产清算事务所 | G48: 20260626 | J48: 意向投资人最近一个会计年度合并口径的资产总额应不低于人民币 40 亿元，且净资产不低于人民币 10 亿元。
A49: 600337 | B49: 美克家居 | C49: 乌鲁木齐中院 | D49: 20260429 | E49: 北京金杜（海口）律师事务所和新疆巨臣律师事务所 | F49: 20260501
A50: 2360 | B50: 同德化工 | C50: 忻州中院 | D50: 20260420 | E50: 清算组 | F50: 20260506 | G50: 20260516 | J50: 意向投资人最近一个会计年度经审计的合并口径净资产不低于人民币 30 亿元，净利润不低于人民币 5 亿元。
A51: 300212 | B51: 易华录 | C51: 北京一中院 | D51: 20260515 | E51: 北京市金杜律师事务所 | F51: 20260601 | K51: 是
A52: 300027 | B52: 华谊兄弟 | C52: 金华中院 | D52: 20260415 | E52: 北京市中伦（上海）律师事务所、浙江智仁律师事务所 | G52: 20260605
A53: 600537 | B53: 亿晶光电 | C53: 常州中院 | D53: 20260204 | E53: 清算组 | F53: 20260210 | G53: 20260427 | H53: 宁波瑞廉（实控郑华玲）+ 中润光能（光伏产业协同方） | I53: 20260427，转增 15.98 亿股，1.86 元，23.34 亿 产投 4.55 亿股 财投 7.93 亿股 债权人 3.50 亿股
A54: 2634 | B54: 棒杰股份 | C54: 金华中院 | D54: 20251205 | E54: 浙江京衡律师事务所、北京金杜（杭州）律师事务所 | H54: 美年大健康 | I54: 20260415，转赠6.5亿股，3.23元,21亿 产投1.8亿股 财投3.9亿股 债权人0.8亿股 | R54: 40
A55: 603843 | B55: 正平 | C55: 西宁中院 | D55: 20251224 | E55: 北京市金杜律师事务所、西宁青石清算事务经纪有限公司
A56: 2726 | B56: 龙大肉食 | D56: 20260703 | J56: 庭外重组
A57: 2528 | B57: 英飞拓 | D57: 20260603 | J57: 庭外重组转重整 | K57: 是
A58: 600337 | B58: 美克家居 | C58: 乌鲁木齐中院 | D58: 20260409 | E58: 北京金杜（海口）律师事务所和新疆巨臣律师事务所 | F58: 20260501
A59: 300716 | B59: 泉为 | C59: 东莞中院 | D59: 20260603 | E59: 广东尚宽律师事务所 | F59: 20260603 | K59: 是
A63: 603007 | B63: 花王股份 | C63: 镇江中院 | D63: 20220428 | E63: 清算组 | H63: 20230130，金华辰顺浩景企业管理合伙企业 | I63: 10转11.55 | J63: 受理前解决的资金占用问题 | M63: 20240910
A65: 525 | B65: 红太阳 | C65: 南京中院 | D65: 20221207 | M65: 20240918
A66: 300209 | B66: 有棵树 | C66: 长沙中院 | D66: 20240220 | M66: 20240930
A67: 600715 | B67: 文投控股 | C67: 北京一中院 | D67: 20240220 | F67: 20240228 | H67: 20240513，首文科集团 | I67: 20241107，8亿元，8亿股 | M67: 20241021 | N67: 20241022 | O67: 20241126 | P67: 20241210 | Q67: 成功 | R67: 15 | S67: 横盘 | U67: 36
A68: 603363 | B68: 傲农生物 | C68: 漳州中院 | M68: 20241105
A69: 603559 | B69: 中国通脉 | C69: 长春中院 | M69: 20241023
A70: 2309 | B70: 中利集团 | C70: 苏州中院 | M70: 20241101
A71: 600375 | B71: 汉马科技 | C71: 马鞍山中院 | M71: 20241108
A72: 2217 | B72: 合力泰 | C72: 福州中院 | M72: 20241122
A73: 2310 | B73: 东方园林 | C73: 北京一中院 | D73: 20240508 | E73: 清算组 | F73: 20240514 | H73: 20241205国联基金联合体,0.66元9亿股，6.28亿 | I73: 20241205 | J73: 20241109豁免15亿债务 | M73: 20241122 | N73: 20241123 | O73: 20241224 | P73: 20241228 | Q73: 成功 | R73: 10 | S73: 下跌 | U73: 60
A74: 2647 | B74: 仁东控股 | C74: 广州中院 | M74: 20241230
A75: 40 | B75: ST旭蓝 | C75: 深圳中院 | D75: 20240902 | J75: 资金占用未完成 | Q75: 失败
A76: 600811 | B76: ST东方 | C76: 哈尔滨中院 | D76: 20240715 | J76: 重大违法 | K76: 是 | Q76: 失败
A77: 300108 | B77: 吉药控股 | C77: 通化中院 | D77: 20230701 | G77: 20231209 | H77: 14家，四环开源佰学联合体 | J77: 20250305，终结。 触发了退市风险 | Q77: 失败
A78: 600804 | B78: 鹏博士 | C78: 青岛中院 | D78: 20241101 | Q78: 失败
A79: 2482 | B79: 广田集团 | C79: 深圳中院 | M79: 20230724
A80: 2157 | B80: 正邦科技 | C80: 南昌中院 | M80: 20230721
A81: 600136 | B81: 当代明诚 | C81: 武汉中院 | M81: 20230605
A82: 2721 | B82: 金一文化 | C82: 北京一中院 | M82: 20230720
A83: 711 | B83: 京蓝科技 | C83: 哈尔滨中院 | M83: 20230605
A84: 600759 | B84: 洲际油气 | C84: 海口中院 | M84: 20230921
A85: 600117 | B85: 西宁特钢 | C85: 西宁中院 | M85: 20230620
A86: 2251 | B86: 步步高 | C86: 湘潭中院 | M86: 20231108
A87: 796 | B87: 凯撒旅游 | C87: 三亚中院 | M87: 20231101
A88: 600306 | B88: 沈阳商城 | C88: 沈阳中院 | M88: 20231111 | V88: 是，收入不达标还是退市了
A89: 603030 | B89: 全筑股份 | C89: 上海三中院 | M89: 20231114
A90: 620 | B90: 盈新发展 | C90: 北京一中院 | M90: 20231115
A91: 300010 | B91: 豆神教育 | C91: 北京一中院 | M91: 20231115
A92: 600589 | B92: 大位科技 | C92: 揭阳中院 | M92: 20231125
A93: 2086 | B93: 东方海洋 | C93: 莱山区法院 | M93: 20231125
A94: 2021 | B94: 中捷资源 | C94: 台州中院 | M94: 20231124 | V94: 是，还有财务类帽子没摘
A95: 46 | B95: ST 泛海 | C95: 北京一中院 | D95: 20230427 | J95: 不具备重整可能 | Q95: 失败
A96: 2776 | B96: ST 柏龙 | C96: 揭阳中院 | D96: 20230801 | Q96: 失败
A97: 2740 | B97: ST 爱迪 | C97: 龙岩中院 | D97: 20230101 | Q97: 失败
A98: 2087 | B98: ST 新纺 | C98: 南阳中院 | D98: 20230717 | Q98: 失败
A99: 2433 | B99: ST 太安 | C99: 汕头中院 | D99: 20230926 | Q99: 失败
A100: 2341 | B100: ST 新纶 | C100: 深圳中院 | D100: 20230101 | Q100: 失败
A101: 300495 | B101: ST 美尚 | C101: 深圳中院 | D101: 20230101 | Q101: 失败
A102: 2280 | B102: ST 联络 | C102: 杭州中院 | D102: 20230101 | Q102: 失败
A103: 600565 | B103: 迪马 | C103: 重庆五中院 | D103: 20230101 | Q103: 失败
A104: 300256 | B104: 星星科技 | C104: 萍乡中院 | M104: 20220526
...

Sheet Sheet5
A2: 45789.368 | C2: 45761.787 | E2: 45762.292
A3: 45789.422 | C3: 45761.79 | D3: =C3-C2 -> 0.0031712963 | E3: 45762.3 | F3: =E3-E2 -> 0.0077893518 | G3: 45763.408
A4: 45789.437 | C4: 45761.794 | D4: =C4-C3 -> 0.0038541667 | E4: 45762.304 | F4: =E4-E3 -> 0.0038888889 | G4: 45763.408 | H4: =G4-G3 -> 8.101853e-05 | M4: 45765.824
A5: 45789.446 | B5: =A5-A4 -> 0.0095949074 | C5: 45761.799 | D5: =C5-C4 -> 0.0046064815 | E5: 45762.312 | F5: =E5-E4 -> 0.0086689815 | G5: 45763.411 | H5: =G5-G4 -> 0.0025578704 | M5: 45765.852
A6: 45789.455 | B6: =A6-A5 -> 0.0085185185 | C6: 45761.804 | D6: =C6-C5 -> 0.0047800926 | E6: 45762.316 | F6: =E6-E5 -> 0.0036689815 | G6: 45763.414 | H6: =G6-G5 -> 0.0035300926
C7: 45761.807 | D7: =C7-C6 -> 0.0031712963 | E7: 45762.335 | F7: =E7-E6 -> 0.018576389 | G7: 45763.424 | H7: =G7-G6 -> 0.01005787
C8: 45761.811 | D8: =C8-C7 -> 0.004375 | E8: 45762.357 | F8: =E8-E7 -> 0.022291667 | G8: 45763.432 | H8: =G8-G7 -> 0.007662037
C9: 45761.818 | D9: =C9-C8 -> 0.0065046296 | E9: 45762.381 | F9: =E9-E8 -> 0.024467593 | G9: 45763.438 | H9: =G9-G8 -> 0.0057407407
A10: 45803.789 | C10: 45761.826 | D10: =C10-C9 -> 0.008275463 | E10: 45762.451 | F10: =E10-E9 -> 0.069398148 | G10: 45763.444 | H10: =G10-G9 -> 0.0063194444
A11: 45803.795 | C11: 45761.836 | D11: =C11-C10 -> 0.010381944 | E11: 45762.526 | F11: =E11-E10 -> 0.074976852 | G11: 45763.45 | H11: =G11-G10 -> 0.0064814815
C12: 45761.845 | D12: =C12-C11 -> 0.0084490741 | E12: 45762.534 | F12: =E12-E11 -> 0.0082523148 | G12: 45763.586
C13: 45761.857 | D13: =C13-C12 -> 0.011921296 | E13: 45762.538 | F13: =E13-E12 -> 0.0036689815 | G13: 45763.596 | H13: =G13-G12 -> 0.010462963 | J13: 45764.49
C14: 45761.866 | D14: =C14-C13 -> 0.0092361111 | E14: 45762.543 | F14: =E14-E13 -> 0.005787037 | G14: 45763.603 | H14: =G14-G13 -> 0.0064814815 | J14: 45764.499 | K14: =J14-J13 -> 0.0091087963
C15: 45761.873 | D15: =C15-C14 -> 0.007349537 | E15: 45762.548 | F15: =E15-E14 -> 0.0047916667 | G15: 45763.616 | H15: =G15-G14 -> 0.013020833 | J15: 45764.504 | K15: =J15-J14 -> 0.0052893519
C16: 45761.889 | D16: =C16-C15 -> 0.016006944 | E16: 45762.553 | F16: =E16-E15 -> 0.0048726852 | G16: 45763.634 | H16: =G16-G15 -> 0.018148148 | J16: 45764.51 | K16: =J16-J15 -> 0.0055902778
C17: 45761.91 | D17: =C17-C16 -> 0.020601852 | E17: 45762.559 | F17: =E17-E16 -> 0.0059027778 | G17: 45763.64 | H17: =G17-G16 -> 0.0062962963 | J17: 45764.523 | K17: =J17-J16 -> 0.013564815
C18: 45761.93 | D18: =C18-C17 -> 0.019780093 | E18: 45762.567 | F18: =E18-E17 -> 0.0077662037 | G18: 45763.647 | H18: =G18-G17 -> 0.0062384259 | J18: 45764.529 | K18: =J18-J17 -> 0.0052430556
C19: 45761.94 | D19: =C19-C18 -> 0.01025463 | E19: 45762.572 | F19: =E19-E18 -> 0.0053240741 | G19: 45763.663 | H19: =G19-G18 -> 0.016354167 | J19: 45764.536 | K19: =J19-J18 -> 0.0069097222
C20: 45761.98 | D20: =C20-C19 -> 0.039884259 | E20: 45762.585 | F20: =E20-E19 -> 0.013217593 | G20: 45763.67 | H20: =G20-G19 -> 0.0065277778 | J20: 45764.554 | K20: =J20-J19 -> 0.018530093
E21: 45762.599 | F21: =E21-E20 -> 0.013819444 | G21: 45763.678 | H21: =G21-G20 -> 0.0085416667 | J21: 45764.575 | K21: =J21-J20 -> 0.020925926
E22: 45762.607 | F22: =E22-E21 -> 0.0078125 | G22: 45763.691 | H22: =G22-G21 -> 0.01318287 | J22: 45764.583 | K22: =J22-J21 -> 0.0081828704
E23: 45762.613 | F23: =E23-E22 -> 0.0059143519 | G23: 45763.697 | H23: =G23-G22 -> 0.0057986111 | J23: 45764.609 | K23: =J23-J22 -> 0.025821759
E24: 45762.624 | F24: =E24-E23 -> 0.011631944 | G24: 45763.709 | H24: =G24-G23 -> 0.011909722 | J24: 45764.622 | K24: =J24-J23 -> 0.012569444
E25: 45762.642 | F25: =E25-E24 -> 0.017523148 | G25: 45763.715 | H25: =G25-G24 -> 0.0062615741 | J25: 45764.633 | K25: =J25-J24 -> 0.011006944
E26: 45762.649 | F26: =E26-E25 -> 0.0073032407 | G26: 45763.722 | H26: =G26-G25 -> 0.0065046296 | J26: 45764.655 | K26: =J26-J25 -> 0.022523148
E27: 45762.666 | F27: =E27-E26 -> 0.016377315 | G27: 45763.732 | H27: =G27-G26 -> 0.010729167 | J27: 45764.666 | K27: =J27-J26 -> 0.010590278
E28: 45762.69 | F28: =E28-E27 -> 0.024270833 | G28: 45763.74 | H28: =G28-G27 -> 0.0071759259 | J28: 45764.705 | K28: =J28-J27 -> 0.039305556
E29: 45762.698 | F29: =E29-E28 -> 0.0080787037 | G29: 45763.747 | H29: =G29-G28 -> 0.0077314815 | J29: 45764.72 | K29: =J29-J28 -> 0.015439815
E30: 45762.712 | F30: =E30-E29 -> 0.013634259 | G30: 45763.771 | H30: =G30-G29 -> 0.0234375 | J30: 45764.739 | K30: =J30-J29 -> 0.018368056
E31: 45762.732 | F31: =E31-E30 -> 0.020277778 | G31: 45763.774 | H31: =G31-G30 -> 0.0028587963 | J31: 45764.741 | K31: =J31-J30 -> 0.0020601852
E32: 45762.735 | F32: =E32-E31 -> 0.0025810185 | G32: 45763.778 | H32: =G32-G31 -> 0.0046759259 | J32: 45764.743 | K32: =J32-J31 -> 0.0018287037
E33: 45762.751 | F33: =E33-E32 -> 0.016238426 | G33: 45763.819 | J33: 45764.746 | K33: =J33-J32 -> 0.0032291667
E34: 45762.759 | F34: =E34-E33 -> 0.0080208333 | G34: 45763.83 | H34: =G34-G33 -> 0.010856481
E35: 45762.771 | F35: =E35-E34 -> 0.012210648 | G35: 45763.843 | H35: =G35-G34 -> 0.013090278
E36: 45762.822 | G36: 45763.864 | H36: =G36-G35 -> 0.02162037
E37: 45762.839 | F37: =E37-E36 -> 0.017141204 | G37: 45763.879 | H37: =G37-G36 -> 0.015127315
E38: 45762.845 | F38: =E38-E37 -> 0.0066203704 | G38: 45763.894 | H38: =G38-G37 -> 0.01412037
E39: 45762.851 | F39: =E39-E38 -> 0.0056828704 | G39: 45763.915 | H39: =G39-G38 -> 0.020925926
E40: 45762.871 | F40: =E40-E39 -> 0.020509259 | G40: 45763.958 | H40: =G40-G39 -> 0.043483796
E41: 45762.875 | F41: =E41-E40 -> 0.0037152778
E42: 45762.88 | F42: =E42-E41 -> 0.0047106482
E43: 45762.888 | F43: =E43-E42 -> 0.0076736111
E44: 45762.896 | F44: =E44-E43 -> 0.0087615741
E45: 45762.916 | F45: =E45-E44 -> 0.019618056
E46: 45762.926 | F46: =E46-E45 -> 0.009837963
E47: 45762.931 | F47: =E47-E46 -> 0.005474537
E48: 45762.94 | F48: =E48-E47 -> 0.0091203704
E49: 45762.946 | F49: =E49-E48 -> 0.0060763889
E50: 45762.954 | F50: =E50-E49 -> 0.0075347222
E51: 45762.964 | F51: =E51-E50 -> 0.0097337963
E52: 45762.978 | F52: =E52-E51 -> 0.014513889

Sheet 月账单
B1: 1380000 | C1: 金额 | D1: 仓位 | F1: 沪深300 | G1: 月份 | H1: ST组合 | I1: 转债组合 | J1: ST组合折算收益 | K1: 转债组合折算收益 | L1: 打新总收益 | M1: 超市策略总收益 | N1: 当月总计 | O1: ST收益 | P1: 转债收益 | Q1: 打新收益 | R1: 超市策略 | S1: 合计 | T1: 持仓不动收益 | U1: 差额 | V1: 雪大师初资产 | W1: 雪大师末资产 | X1: 雪大师实际 | Y1: 雪大师不动 | Z1: 差额 | AC1: 羊哥初资产 | AD1: 羊哥末资产 | AE1: 羊哥实际 | AF1: 羊哥不动 | AG1: 差额
B2: 柳药转债 | C2: =B1-SUM(C3:C35) -> 57400 | D2: =C2/$B$1 -> 0.041594203 | G2: 2025 | O2: 88219 | P2: 44874 | Q2: =9600+66808 -> 76408 | R2: 15830 | S2: =SUM(O2:R2) -> 225331
B3: 小狮子12支 | C3: 120000 | D3: =C3/$B$1 -> 0.086956522 | F3: 0.032 | G3: 202509 | H3: =22094/300000 -> 0.073646667 | I3: =12386/340000 -> 0.036429412 | J3: =H3/1500000*300000 -> 0.014729333 | K3: =I3/1500000*340000 -> 0.0082573333 | L3: =678/1500000 -> 0.000452 | M3: 0 | N3: =SUM(J3:M3) -> 0.023438667
B4: 转债轮动20支 | C4: 380000 | D4: =C4/$B$1 -> 0.27536232 | F4: 0 | G4: 202510 | H4: 0.0405 | I4: -0.0142 | J4: =H4/1500000*380000 -> 0.01026 | K4: =I4/1500000*380000 -> -0.0035973333 | L4: =10900/1500000 -> 0.0072666667 | M4: =10500/1500000 -> 0.007 | N4: =SUM(J4:M4) -> 0.020929333 | O4: 14552 | P4: -5900 | Q4: 10900 | R4: 10500 | S4: =SUM(O4:R4) -> 30052
B5: 万孚转债 | C5: 30000 | D5: =C5/$B$1 -> 0.02173913 | F5: -0.0246 | G5: 202511 | H5: 0.0353 | I5: 0.0023 | J5: =H5/1500000*1000000 -> 0.023533333 | K5: =I5/1500000*400000 -> 0.00061333333 | L5: 0 | M5: 0.006 | N5: =SUM(J5:M5) -> 0.030146667 | S5: 45000
B6: 恒逸转债 | C6: 42000 | D6: =C6/$B$1 -> 0.030434783 | F6: 0.0228 | G6: 202512 | H6: -0.0592 | I6: 0.0255 | J6: =O6/1500000 -> -0.014250667 | K6: =P6/1500000 -> 0.0021706667 | L6: 0 | M6: =R6/1500000 -> -0.008 | N6: =SUM(J6:M6) -> -0.02008 | O6: -21376 | P6: 3256 | Q6: 0 | R6: =9000-21000 -> -12000 | S6: =SUM(O6:R6) -> -30120
B7: 美锦转债 | C7: 42000 | D7: =C7/$B$1 -> 0.030434783 | F7: =SUM(F8:F19) -> -0.0506 | G7: 2026 | N7: =S7/B1 -> 0.018207246 | O7: =SUM(O8:O18) -> -9582 | P7: =SUM(P8:P18) -> 42098 | Q7: =SUM(Q8:Q18) -> 0 | R7: =SUM(R8:R18) -> -7390 | S7: =SUM(S8:S18) -> 25126 | AB7: 2026
B8: 鲁泰转债 | C8: 115000 | D8: =C8/$B$1 -> 0.083333333 | F8: 0.0165 | G8: 202601 | H8: 0 | I8: 0.0831 | J8: =O8/1500000 -> 0 | K8: =P8/1380000 -> 0.04461087 | L8: 0 | M8: =R8/1380000 -> 0.01679058 | N8: =SUM(J8:M8) -> 0.061401449 | O8: 0 | P8: 61563 | Q8: 0 | R8: 23171 | S8: =SUM(O8:R8) -> 84734 | V8: 3441320 | W8: 3802205 | X8: =W8-V8 -> 360885 | Y8: 322691 | Z8: =X8-Y8 -> 38194 | AB8: 202601 | AG8: =AE8-AF8 -> 0
B9: 中国国航 | C9: 46000 | D9: =C9/$B$1 -> 0.033333333 | F9: 0.0009 | G9: 202602 | H9: 0 | I9: 0.0261 | J9: =O9/1500000 -> 0 | K9: =P9/1380000 -> 0.025655072 | L9: 0 | M9: =R9/1380000 -> 0.024687681 | N9: =SUM(J9:M9) -> 0.050342754 | O9: 0 | P9: 35404 | Q9: 0 | R9: 34069 | S9: =SUM(O9:R9) -> 69473 | V9: 3802205 | W9: 3947873 | X9: =W9-V9 -> 145668 | Y9: 78330 | Z9: =X9-Y9 -> 67338 | AB9: 202602 | AG9: =AE9-AF9 -> 0
B10: 南航转债 | C10: 95000 | D10: =C10/$B$1 -> 0.06884058 | E10: 0 | F10: -0.0553 | G10: 202603 | H10: 0 | I10: -0.0666 | J10: =O10/1500000 -> 0 | K10: =P10/1380000 -> -0.043478261 | L10: 0 | M10: =R10/1380000 -> -0.081561594 | N10: =SUM(J10:M10) -> -0.12503986 | O10: 0 | P10: -60000 | Q10: 0 | R10: =-172555-P10 -> -112555 | S10: =SUM(O10:R10) -> -172555 | V10: 3947873 | W10: 3647202 | X10: =W10-V10 -> -300671 | Y10: -354205 | Z10: =X10-Y10 -> 53534 | AB10: 202603 | AE10: -978328 | AF10: -1037315 | AG10: =AE10-AF10 -> 58987
B11: 太阳纸业 | C11: 90000 | D11: =C11/$B$1 -> 0.065217391 | F11: 0.0803 | G11: 202604 | H11: 0 | I11: 0.0023 | J11: =O11/1500000 -> 0 | K11: =P11/1380000 -> 0.0016666667 | L11: 0 | M11: =R11/1380000 -> 0.034782609 | N11: =SUM(J11:M11) -> 0.036449275 | O11: 0 | P11: 2300 | Q11: 0 | R11: 48000 | S11: =SUM(O11:R11) -> 50300 | V11: 3647202 | W11: 3833830 | X11: =W11-V11 -> 186628 | Y11: 216658 | Z11: =X11-Y11 -> -30030 | AB11: 202604 | AE11: 453961 | AF11: 333429 | AG11: =AE11-AF11 -> 120532
B12: 中国海油 | C12: 95000 | D12: =C12/$B$1 -> 0.06884058 | F12: 0.0176 | G12: 202605 | H12: -0.0539 | I12: -0.0334 | J12: =O12/1380000 -> -0.0078586957 | K12: =P12/1380000 -> -0.0093471014 | L12: 0 | M12: =R12/1380000 -> -0.048264493 | N12: =SUM(J12:M12) -> -0.06547029 | O12: -10845 | P12: -12899 | Q12: 0 | R12: -66605 | S12: =SUM(O12:R12) -> -90349 | T12: -82072 | U12: =S12-T12 -> -8277 | V12: =W11 -> 3833830 | W12: 3575152 | X12: =W12-V12 -> -258678 | Y12: =-301136+12852 -> -288284 | Z12: =X12-Y12 -> 29606 | AB12: 202605 | AE12: -1372639 | AF12: -1041718 | AG12: =AE12-AF12 -> -330921
B13: 金煤科技 | C13: 26000 | D13: =C13/$B$1 -> 0.01884058 | F13: 0.0178 | G13: 202606 | H13: -0.1357 | I13: 0.0472 | J13: =O13/1300000 -> -0.028886923 | K13: =P13/1300000 -> 0.0039369231 | L13: 0 | M13: =R13/1300000 -> -0.079981538 | N13: =SUM(J13:M13) -> -0.10493154 | O13: -37553 | P13: 5118 | Q13: 0 | R13: -103976 | S13: =SUM(O13:R13) -> -136411 | T13: -103425 | U13: =S13-T13 -> -32986 | V13: =W12 -> 3575152 | W13: 3315677 | X13: =W13-V13 -> -259475 | Y13: -253164 | Z13: =X13-Y13 -> -6311 | AB13: 202606 | AE13: -1599658 | AF13: -1369778 | AG13: =AE13-AF13 -> -229880
B14: 恒逸石化 | C14: 23000 | D14: =C14/$B$1 -> 0.016666667 | E14: 0 | F14: -0.0786 | G14: 202607 | H14: 0 | I14: 0.1833 | J14: =O14/1130000 -> 0 | K14: =P14/1130000 -> 0.0074469027 | L14: 0 | M14: =R14/1130000 -> 0.058959292 | N14: =SUM(J14:M14) -> 0.066406195 | O14: 0 | P14: 8415 | Q14: 0 | R14: 66624 | S14: =SUM(O14:R14) -> 75039 | T14: 50109 | U14: =S14-T14 -> 24930 | V14: =W13 -> 3315677 | W14: 3444591 | X14: =W14-V14 -> 128914 | Y14: =119044+10000 -> 129044 | Z14: =X14-Y14 -> -130 | AB14: 202607 | AE14: 901848 | AF14: =797126+120000 -> 917126 | AG14: =AE14-AF14 -> -15278
B15: 宏达股份 | C15: 0 | D15: =C15/$B$1 -> 0 | F15: 0.008 | G15: 202608 | H15: 0.1543 | I15: 0.0097 | J15: =O15/1280000 -> 0.030920313 | K15: =P15/1280000 -> 0.002090625 | L15: =Q15/1180000 -> 0 | M15: =R15/1180000 -> 0.072173729 | N15: =SUM(J15:M15) -> 0.10518467 | O15: 39578 | P15: 2676 | Q15: 0 | R15: 85165 | S15: =SUM(O15:R15) -> 127419 | T15: 121910 | U15: =S15-T15 -> 5509 | V15: =W14 -> 3444591 | W15: 3689149 | X15: =W15-V15 -> 244558 | Y15: 235691 | Z15: =X15-Y15 -> 8867 | AB15: 202608 | AE15: 1202381 | AF15: 1047511 | AG15: =AE15-AF15 -> 154870
B16: 低波策略 | F16: -0.0578 | G16: 202609 | H16: -0.86 | I16: -1.25 | J16: =O16/1180000 -> -0.00064576271 | K16: =P16/1180000 -> -0.0004059322 | L16: =Q16/1280000 -> 0 | M16: =R16/1280000 -> 0.014622656 | N16: =SUM(J16:M16) -> 0.013570961 | O16: -762 | P16: -479 | Q16: 0 | R16: 18717 | S16: =SUM(O16:R16) -> 17476 | T16: -18849 | U16: =-4000-T16 -> 14849 | V16: =W15 -> 3689149 | W16: 3747000 | X16: =W16-V16 -> 57851 | Y16: 77637 | Z16: =X16-Y16 -> -19786 | AB16: 202609 | AF16: 112762 | AG16: =AE16-AF16 -> -112762
B17: 青岛港 | C17: 33000 | D17: =C17/$B$1 -> 0.023913043 | G17: 202610 | V17: =W16 -> 3747000
B18: 江阴银行 | C18: 38000 | D18: =C18/$B$1 -> 0.027536232
B19: 豆粕ETF | C19: 21500 | D19: =C19/$B$1 -> 0.01557971
B20: 浙能电力 | C20: 10000 | D20: =C20/$B$1 -> 0.0072463768
B21: 神马电力 | C21: 10000 | D21: =C21/$B$1 -> 0.0072463768
B22: 剩饭策略
B23: 时空科技 | C23: 0 | D23: =C23/$B$1 -> 0
B24: 云天化 | C24: 40000 | D24: =C24/$B$1 -> 0.028985507 | E24: 0
B25: 天齐锂业 | C25: 30000 | D25: =C25/$B$1 -> 0.02173913
B26: 华虹公司 | C26: 0 | D26: =C26/$B$1 -> 0
B27: 苏轴股份 | C27: 23000 | D27: =C27/$B$1 -> 0.016666667
B28: 认沽期权
B29: MO2603沽6900 | C29: 6500 | D29: =C29/$B$1 -> 0.0047101449
B30: MO2603沽6200 | D30: =C30/$B$1 -> 0
B31: 认购期权
B32: MO2603购8400 | C32: 6600 | D32: =C32/$B$1 -> 0.0047826087 | E32: 0

Sheet 转债
A1: 溢价率 | B1: 强赎空间 | C1: 满足强赎天数 | D1: 市价 | E1: 证券代码 | F1: 证券名称 | G1: 到期价格 | H1: 到期收益率 | I1: 正股涨幅 | J1: 涨幅 | K1: 转股价格 | L1: 强赎价格 | M1: 正股价格 | N1: 下修价格 | O1: 到期日期 | P1: 余额 | Q1: 下修倒计时 | R1: 强赎状态 | S1: 连续日 | T1: 重数
A2: =VLOOKUP($F2,全部可转债!$A:$S,9,0) -> 61.91 | B2: =L2*100/M2-100 -> 186.56934 | C2: 0 | D2: =VLOOKUP(F2,全部可转债!$A:$S,16,0) -> 73.45 | E2: =VLOOKUP($F2,全部可转债!$A:$S,2,0) -> 110092 | F2: 三房转债 | G2: =VLOOKUP($F2,全部可转债!$A:$S,7,0) -> 110 | H2: =G2/D2-1 -> 0.49761743 | I2: =VLOOKUP($F2,全部可转债!$A:$S,19,0) -> -5.52 | J2: =VLOOKUP($F2,全部可转债!$A:$S,17,0) -> -2.87 | K2: =VLOOKUP($F2,全部可转债!$A:$S,5,0) -> 3.02 | L2: =VLOOKUP($F2,全部可转债!$A:$S,6,0) -> 3.926 | M2: =VLOOKUP($F2,全部可转债!$A:$S,18,0) -> 1.37 | N2: =VLOOKUP($F2,全部可转债!$A:$S,8,0) -> 2.567 | O2: =VLOOKUP($F2,全部可转债!$A:$S,15,0) -> 20290106 | P2: =VLOOKUP($F2,全部可转债!$A:$S,14,0) -> 21.185 | Q2: 703 | R2: =VLOOKUP($F2,全部可转债!$A:$S,11,0) -> 未满足
A3: =VLOOKUP($F3,全部可转债!$A:$S,9,0) -> 13.3 | B3: =L3*100/M3-100 -> 45.270846 | C3: 0 | D3: =VLOOKUP(F3,全部可转债!$A:$S,16,0) -> 101.39 | E3: =VLOOKUP($F3,全部可转债!$A:$S,2,0) -> 110081 | F3: 闻泰转债 | G3: =VLOOKUP($F3,全部可转债!$A:$S,7,0) -> 108 | H3: =G3/D3-1 -> 0.065193806 | I3: =VLOOKUP($F3,全部可转债!$A:$S,19,0) -> -0.48 | J3: =VLOOKUP($F3,全部可转债!$A:$S,17,0) -> 0.32 | K3: =VLOOKUP($F3,全部可转债!$A:$S,5,0) -> 18.36 | L3: =VLOOKUP($F3,全部可转债!$A:$S,6,0) -> 23.868 | M3: =VLOOKUP($F3,全部可转债!$A:$S,18,0) -> 16.43 | N3: =VLOOKUP($F3,全部可转债!$A:$S,8,0) -> 15.606 | O3: =VLOOKUP($F3,全部可转债!$A:$S,15,0) -> 20270728 | P3: =VLOOKUP($F3,全部可转债!$A:$S,14,0) -> 71.5 | Q3: -1 | R3: =VLOOKUP($F3,全部可转债!$A:$S,11,0) -> 未满足
A4: =VLOOKUP($F4,全部可转债!$A:$S,9,0) -> 7.75 | B4: =L4*100/M4-100 -> 2.6315789 | C4: 0 | D4: =VLOOKUP(F4,全部可转债!$A:$S,16,0) -> 136.48 | E4: =VLOOKUP($F4,全部可转债!$A:$S,2,0) -> 113681 | F4: 镇洋转债 | G4: =VLOOKUP($F4,全部可转债!$A:$S,7,0) -> 115 | H4: =G4/D4-1 -> -0.1573857 | I4: =VLOOKUP($F4,全部可转债!$A:$S,19,0) -> 0.87 | J4: =VLOOKUP($F4,全部可转债!$A:$S,17,0) -> 0.39 | K4: =VLOOKUP($F4,全部可转债!$A:$S,5,0) -> 10.95 | L4: =VLOOKUP($F4,全部可转债!$A:$S,6,0) -> 14.235 | M4: =VLOOKUP($F4,全部可转债!$A:$S,18,0) -> 13.87 | N4: =VLOOKUP($F4,全部可转债!$A:$S,8,0) -> 9.307 | O4: =VLOOKUP($F4,全部可转债!$A:$S,15,0) -> 20291229 | P4: =VLOOKUP($F4,全部可转债!$A:$S,14,0) -> 5.476 | Q4: 0 | R4: =VLOOKUP($F4,全部可转债!$A:$S,11,0) -> 未满足
A7: =VLOOKUP($F7,全部可转债!$A:$S,9,0) -> 46.41 | B7: =L7*100/M7-100 -> 58.605664 | C7: 0 | D7: =VLOOKUP(F7,全部可转债!$A:$S,16,0) -> 120 | E7: =VLOOKUP($F7,全部可转债!$A:$S,2,0) -> 110087 | F7: 天业转债 | G7: =VLOOKUP($F7,全部可转债!$A:$S,7,0) -> 108 | H7: =G7/D7-1 -> -0.1 | I7: =VLOOKUP($F7,全部可转债!$A:$S,19,0) -> 1.55 | J7: =VLOOKUP($F7,全部可转债!$A:$S,17,0) -> 1.59 | K7: =VLOOKUP($F7,全部可转债!$A:$S,5,0) -> 5.6 | L7: =VLOOKUP($F7,全部可转债!$A:$S,6,0) -> 7.28 | M7: =VLOOKUP($F7,全部可转债!$A:$S,18,0) -> 4.59 | N7: =VLOOKUP($F7,全部可转债!$A:$S,8,0) -> 4.76 | O7: =VLOOKUP($F7,全部可转债!$A:$S,15,0) -> 20280623 | P7: =VLOOKUP($F7,全部可转债!$A:$S,14,0) -> 29.975 | R7: =VLOOKUP($F7,全部可转债!$A:$S,11,0) -> 未满足
A8: =VLOOKUP($F8,全部可转债!$A:$S,9,0) -> 70.47 | B8: =L8*100/M8-100 -> 89.262966 | C8: 0 | D8: =VLOOKUP(F8,全部可转债!$A:$S,16,0) -> 117.09 | E8: =VLOOKUP($F8,全部可转债!$A:$S,2,0) -> 118031 | F8: 天23转债 | G8: =VLOOKUP($F8,全部可转债!$A:$S,7,0) -> 115 | H8: =G8/D8-1 -> -0.017849517 | I8: =VLOOKUP($F8,全部可转债!$A:$S,19,0) -> 1.76 | J8: =VLOOKUP($F8,全部可转债!$A:$S,17,0) -> 0.54 | K8: =VLOOKUP($F8,全部可转债!$A:$S,5,0) -> 16 | L8: =VLOOKUP($F8,全部可转债!$A:$S,6,0) -> 20.8 | M8: =VLOOKUP($F8,全部可转债!$A:$S,18,0) -> 10.99 | N8: =VLOOKUP($F8,全部可转债!$A:$S,8,0) -> 13.6 | O8: =VLOOKUP($F8,全部可转债!$A:$S,15,0) -> 20290213 | P8: =VLOOKUP($F8,全部可转债!$A:$S,14,0) -> 58.512 | R8: =VLOOKUP($F8,全部可转债!$A:$S,11,0) -> 未满足
A9: =VLOOKUP($F9,全部可转债!$A:$S,9,0) -> 31.1 | B9: =L9*100/M9-100 -> 35.979112 | C9: 0 | D9: =VLOOKUP(F9,全部可转债!$A:$S,16,0) -> 115.69 | E9: =VLOOKUP($F9,全部可转债!$A:$S,2,0) -> 118034 | F9: 晶能转债 | G9: =VLOOKUP($F9,全部可转债!$A:$S,7,0) -> 108 | H9: =G9/D9-1 -> -0.066470741 | I9: =VLOOKUP($F9,全部可转债!$A:$S,19,0) -> 2.41 | J9: =VLOOKUP($F9,全部可转债!$A:$S,17,0) -> 0.55 | K9: =VLOOKUP($F9,全部可转债!$A:$S,5,0) -> 4.34 | L9: =VLOOKUP($F9,全部可转债!$A:$S,6,0) -> 5.208 | M9: =VLOOKUP($F9,全部可转债!$A:$S,18,0) -> 3.83 | N9: =VLOOKUP($F9,全部可转债!$A:$S,8,0) -> 3.689 | O9: =VLOOKUP($F9,全部可转债!$A:$S,15,0) -> 20290420 | P9: =VLOOKUP($F9,全部可转债!$A:$S,14,0) -> 83.22 | R9: =VLOOKUP($F9,全部可转债!$A:$S,11,0) -> 未满足
A10: =VLOOKUP($F10,全部可转债!$A:$S,9,0) -> 61.2 | B10: =L10*100/M10-100 -> 72.709832 | C10: 0 | D10: =VLOOKUP(F10,全部可转债!$A:$S,16,0) -> 121.33 | E10: =VLOOKUP($F10,全部可转债!$A:$S,2,0) -> 127108 | F10: 太能转债 | G10: =VLOOKUP($F10,全部可转债!$A:$S,7,0) -> 112 | H10: =G10/D10-1 -> -0.076897717 | I10: =VLOOKUP($F10,全部可转债!$A:$S,19,0) -> 0.48 | J10: =VLOOKUP($F10,全部可转债!$A:$S,17,0) -> 0.28 | K10: =VLOOKUP($F10,全部可转债!$A:$S,5,0) -> 5.54 | L10: =VLOOKUP($F10,全部可转债!$A:$S,6,0) -> 7.202 | M10: =VLOOKUP($F10,全部可转债!$A:$S,18,0) -> 4.17 | N10: =VLOOKUP($F10,全部可转债!$A:$S,8,0) -> 4.709 | O10: =VLOOKUP($F10,全部可转债!$A:$S,15,0) -> 20310328 | P10: =VLOOKUP($F10,全部可转债!$A:$S,14,0) -> 29.498 | Q10: 820 | R10: =VLOOKUP($F10,全部可转债!$A:$S,11,0) -> 未满足
A11: =VLOOKUP($F11,全部可转债!$A:$S,9,0) -> 24.23 | B11: =L11*100/M11-100 -> 25.821429 | C11: 0 | D11: =VLOOKUP(F11,全部可转债!$A:$S,16,0) -> 128.35 | E11: =VLOOKUP($F11,全部可转债!$A:$S,2,0) -> 123149 | F11: 通裕转债 | G11: =VLOOKUP($F11,全部可转债!$A:$S,7,0) -> 112 | H11: =G11/D11-1 -> -0.12738605 | I11: =VLOOKUP($F11,全部可转债!$A:$S,19,0) -> -0.71 | J11: =VLOOKUP($F11,全部可转债!$A:$S,17,0) -> 0.11 | K11: =VLOOKUP($F11,全部可转债!$A:$S,5,0) -> 2.71 | L11: =VLOOKUP($F11,全部可转债!$A:$S,6,0) -> 3.523 | M11: =VLOOKUP($F11,全部可转债!$A:$S,18,0) -> 2.8 | N11: =VLOOKUP($F11,全部可转债!$A:$S,8,0) -> 2.304 | O11: =VLOOKUP($F11,全部可转债!$A:$S,15,0) -> 20280620 | P11: =VLOOKUP($F11,全部可转债!$A:$S,14,0) -> 11.069 | R11: =VLOOKUP($F11,全部可转债!$A:$S,11,0) -> 未满足 | S11: 13
A12: =VLOOKUP($F12,全部可转债!$A:$S,9,0) -> #N/A | B12: =L12*100/M12-100 -> #N/A | C12: 15 | D12: =VLOOKUP(F12,全部可转债!$A:$S,16,0) -> #N/A | E12: =VLOOKUP($F12,全部可转债!$A:$S,2,0) -> #N/A | F12: 金埔转债 | G12: =VLOOKUP($F12,全部可转债!$A:$S,7,0) -> #N/A | H12: =G12/D12-1 -> #N/A | I12: =VLOOKUP($F12,全部可转债!$A:$S,19,0) -> #N/A | J12: =VLOOKUP($F12,全部可转债!$A:$S,17,0) -> #N/A | K12: =VLOOKUP($F12,全部可转债!$A:$S,5,0) -> #N/A | L12: =VLOOKUP($F12,全部可转债!$A:$S,6,0) -> #N/A | M12: =VLOOKUP($F12,全部可转债!$A:$S,18,0) -> #N/A | N12: =VLOOKUP($F12,全部可转债!$A:$S,8,0) -> #N/A | O12: =VLOOKUP($F12,全部可转债!$A:$S,15,0) -> #N/A | P12: =VLOOKUP($F12,全部可转债!$A:$S,14,0) -> #N/A | R12: =VLOOKUP($F12,全部可转债!$A:$S,11,0) -> #N/A
A13: =VLOOKUP($F13,全部可转债!$A:$S,9,0) -> 31.42 | B13: =L13*100/M13-100 -> 33.82716 | C13: 10 | D13: =VLOOKUP(F13,全部可转债!$A:$S,16,0) -> 127.67 | E13: =VLOOKUP($F13,全部可转债!$A:$S,2,0) -> 113640 | F13: 苏利转债 | G13: =VLOOKUP($F13,全部可转债!$A:$S,7,0) -> 115 | H13: =G13/D13-1 -> -0.099240229 | I13: =VLOOKUP($F13,全部可转债!$A:$S,19,0) -> -0.28 | J13: =VLOOKUP($F13,全部可转债!$A:$S,17,0) -> 0.29 | K13: =VLOOKUP($F13,全部可转债!$A:$S,5,0) -> 10.84 | L13: =VLOOKUP($F13,全部可转债!$A:$S,6,0) -> 14.092 | M13: =VLOOKUP($F13,全部可转债!$A:$S,18,0) -> 10.53 | N13: =VLOOKUP($F13,全部可转债!$A:$S,8,0) -> 9.756 | O13: =VLOOKUP($F13,全部可转债!$A:$S,15,0) -> 20280216 | P13: =VLOOKUP($F13,全部可转债!$A:$S,14,0) -> 7.39 | R13: =VLOOKUP($F13,全部可转债!$A:$S,11,0) -> 未满足
A14: =VLOOKUP($F14,全部可转债!$A:$S,9,0) -> 20.81 | B14: =L14*100/M14-100 -> 12.537313 | C14: 0 | D14: =VLOOKUP(F14,全部可转债!$A:$S,16,0) -> 139.56 | E14: =VLOOKUP($F14,全部可转债!$A:$S,2,0) -> 123178 | F14: 花园转债 | G14: =VLOOKUP($F14,全部可转债!$A:$S,7,0) -> 115 | H14: =G14/D14-1 -> -0.17598166 | I14: =VLOOKUP($F14,全部可转债!$A:$S,19,0) -> 0.52 | J14: =VLOOKUP($F14,全部可转债!$A:$S,17,0) -> 0.49 | K14: =VLOOKUP($F14,全部可转债!$A:$S,5,0) -> 13.34 | L14: =VLOOKUP($F14,全部可转债!$A:$S,6,0) -> 17.342 | M14: =VLOOKUP($F14,全部可转债!$A:$S,18,0) -> 15.41 | N14: =VLOOKUP($F14,全部可转债!$A:$S,8,0) -> 11.339 | O14: =VLOOKUP($F14,全部可转债!$A:$S,15,0) -> 20290306 | P14: =VLOOKUP($F14,全部可转债!$A:$S,14,0) -> 11.58 | R14: =VLOOKUP($F14,全部可转债!$A:$S,11,0) -> 未满足
A15: =VLOOKUP($F15,全部可转债!$A:$S,9,0) -> 49.48 | B15: =L15*100/M15-100 -> 56.545802 | C15: 0 | D15: =VLOOKUP(F15,全部可转债!$A:$S,16,0) -> 124.13 | E15: =VLOOKUP($F15,全部可转债!$A:$S,2,0) -> 113665 | F15: 汇通转债 | G15: =VLOOKUP($F15,全部可转债!$A:$S,7,0) -> 115 | H15: =G15/D15-1 -> -0.073551921 | I15: =VLOOKUP($F15,全部可转债!$A:$S,19,0) -> -0.76 | J15: =VLOOKUP($F15,全部可转债!$A:$S,17,0) -> -0.27 | K15: =VLOOKUP($F15,全部可转债!$A:$S,5,0) -> 6.31 | L15: =VLOOKUP($F15,全部可转债!$A:$S,6,0) -> 8.203 | M15: =VLOOKUP($F15,全部可转债!$A:$S,18,0) -> 5.24 | N15: =VLOOKUP($F15,全部可转债!$A:$S,8,0) -> 5.364 | O15: =VLOOKUP($F15,全部可转债!$A:$S,15,0) -> 20281215 | P15: =VLOOKUP($F15,全部可转债!$A:$S,14,0) -> 3.596 | R15: =VLOOKUP($F15,全部可转债!$A:$S,11,0) -> 未满足
A16: =VLOOKUP($F16,全部可转债!$A:$S,9,0) -> 38.1 | B16: =L16*100/M16-100 -> 53.716216 | C16: 0 | D16: =VLOOKUP(F16,全部可转债!$A:$S,16,0) -> 116.79 | E16: =VLOOKUP($F16,全部可转债!$A:$S,2,0) -> 118020 | F16: 芳源转债 | G16: =VLOOKUP($F16,全部可转债!$A:$S,7,0) -> 120 | H16: =G16/D16-1 -> 0.02748523 | I16: =VLOOKUP($F16,全部可转债!$A:$S,19,0) -> 0.51 | J16: =VLOOKUP($F16,全部可转债!$A:$S,17,0) -> 0.09 | K16: =VLOOKUP($F16,全部可转债!$A:$S,5,0) -> 7 | L16: =VLOOKUP($F16,全部可转债!$A:$S,6,0) -> 9.1 | M16: =VLOOKUP($F16,全部可转债!$A:$S,18,0) -> 5.92 | N16: =VLOOKUP($F16,全部可转债!$A:$S,8,0) -> 5.95 | O16: =VLOOKUP($F16,全部可转债!$A:$S,15,0) -> 20280923 | P16: =VLOOKUP($F16,全部可转债!$A:$S,14,0) -> 6.417 | Q16: 716 | R16: =VLOOKUP($F16,全部可转债!$A:$S,11,0) -> 未满足
A17: =VLOOKUP($F17,全部可转债!$A:$S,9,0) -> 119.17 | B17: =L17*100/M17-100 -> 130.70423 | C17: 0 | D17: =VLOOKUP(F17,全部可转债!$A:$S,16,0) -> 123.5 | E17: =VLOOKUP($F17,全部可转债!$A:$S,2,0) -> 127062 | F17: 垒知转债 | G17: =VLOOKUP($F17,全部可转债!$A:$S,7,0) -> 115 | H17: =G17/D17-1 -> -0.068825911 | I17: =VLOOKUP($F17,全部可转债!$A:$S,19,0) -> -0.23 | J17: =VLOOKUP($F17,全部可转债!$A:$S,17,0) -> 0.41 | K17: =VLOOKUP($F17,全部可转债!$A:$S,5,0) -> 7.56 | L17: =VLOOKUP($F17,全部可转债!$A:$S,6,0) -> 9.828 | M17: =VLOOKUP($F17,全部可转债!$A:$S,18,0) -> 4.26 | N17: =VLOOKUP($F17,全部可转债!$A:$S,8,0) -> 6.426 | O17: =VLOOKUP($F17,全部可转债!$A:$S,15,0) -> 20280421 | P17: =VLOOKUP($F17,全部可转债!$A:$S,14,0) -> 3.957 | Q17: 12 | R17: =VLOOKUP($F17,全部可转债!$A:$S,11,0) -> 未满足
A18: =VLOOKUP($F18,全部可转债!$A:$S,9,0) -> 35.59 | B18: =L18*100/M18-100 -> 36.980545 | C18: 0 | D18: =VLOOKUP(F18,全部可转债!$A:$S,16,0) -> 128.68 | E18: =VLOOKUP($F18,全部可转债!$A:$S,2,0) -> 123171 | F18: 共同转债 | G18: =VLOOKUP($F18,全部可转债!$A:$S,7,0) -> 115 | H18: =G18/D18-1 -> -0.10631023 | I18: =VLOOKUP($F18,全部可转债!$A:$S,19,0) -> 2.72 | J18: =VLOOKUP($F18,全部可转债!$A:$S,17,0) -> 1.02 | K18: =VLOOKUP($F18,全部可转债!$A:$S,5,0) -> 27.08 | L18: =VLOOKUP($F18,全部可转债!$A:$S,6,0) -> 35.204 | M18: =VLOOKUP($F18,全部可转债!$A:$S,18,0) -> 25.7 | N18: =VLOOKUP($F18,全部可转债!$A:$S,8,0) -> 23.018 | O18: =VLOOKUP($F18,全部可转债!$A:$S,15,0) -> 20281128 | P18: =VLOOKUP($F18,全部可转债!$A:$S,14,0) -> 3.799 | R18: =VLOOKUP($F18,全部可转债!$A:$S,11,0) -> 未满足
A19: =VLOOKUP($F19,全部可转债!$A:$S,9,0) -> 79.28 | B19: =L19*100/M19-100 -> 87.001507 | C19: 0 | D19: =VLOOKUP(F19,全部可转债!$A:$S,16,0) -> 124.63 | E19: =VLOOKUP($F19,全部可转债!$A:$S,2,0) -> 118037 | F19: 上声转债 | G19: =VLOOKUP($F19,全部可转债!$A:$S,7,0) -> 111 | H19: =G19/D19-1 -> -0.10936372 | I19: =VLOOKUP($F19,全部可转债!$A:$S,19,0) -> -0.15 | J19: =VLOOKUP($F19,全部可转债!$A:$S,17,0) -> 0.32 | K19: =VLOOKUP($F19,全部可转债!$A:$S,5,0) -> 28.64 | L19: =VLOOKUP($F19,全部可转债!$A:$S,6,0) -> 37.232 | M19: =VLOOKUP($F19,全部可转债!$A:$S,18,0) -> 19.91 | N19: =VLOOKUP($F19,全部可转债!$A:$S,8,0) -> 24.344 | O19: =VLOOKUP($F19,全部可转债!$A:$S,15,0) -> 20290706 | P19: =VLOOKUP($F19,全部可转债!$A:$S,14,0) -> 4.679 | R19: =VLOOKUP($F19,全部可转债!$A:$S,11,0) -> 未满足
A20: =VLOOKUP($F20,全部可转债!$A:$S,9,0) -> #N/A | B20: =L20*100/M20-100 -> #N/A | C20: 0 | D20: =VLOOKUP(F20,全部可转债!$A:$S,16,0) -> #N/A | E20: =VLOOKUP($F20,全部可转债!$A:$S,2,0) -> #N/A | F20: 万讯转债 | G20: =VLOOKUP($F20,全部可转债!$A:$S,7,0) -> #N/A | H20: =G20/D20-1 -> #N/A | I20: =VLOOKUP($F20,全部可转债!$A:$S,19,0) -> #N/A | J20: =VLOOKUP($F20,全部可转债!$A:$S,17,0) -> #N/A | K20: =VLOOKUP($F20,全部可转债!$A:$S,5,0) -> #N/A | L20: =VLOOKUP($F20,全部可转债!$A:$S,6,0) -> #N/A | M20: =VLOOKUP($F20,全部可转债!$A:$S,18,0) -> #N/A | N20: =VLOOKUP($F20,全部可转债!$A:$S,8,0) -> #N/A | O20: =VLOOKUP($F20,全部可转债!$A:$S,15,0) -> #N/A | P20: =VLOOKUP($F20,全部可转债!$A:$S,14,0) -> #N/A | R20: =VLOOKUP($F20,全部可转债!$A:$S,11,0) -> #N/A
A21: =VLOOKUP($F21,全部可转债!$A:$S,9,0) -> 28.15 | B21: =L21*100/M21-100 -> 24.898734 | C21: 0 | D21: =VLOOKUP(F21,全部可转债!$A:$S,16,0) -> 133.38 | E21: =VLOOKUP($F21,全部可转债!$A:$S,2,0) -> 123189 | F21: 晓鸣转债 | G21: =VLOOKUP($F21,全部可转债!$A:$S,7,0) -> 113 | H21: =G21/D21-1 -> -0.15279652 | I21: =VLOOKUP($F21,全部可转债!$A:$S,19,0) -> -0.88 | J21: =VLOOKUP($F21,全部可转债!$A:$S,17,0) -> -0.37 | K21: =VLOOKUP($F21,全部可转债!$A:$S,5,0) -> 15.18 | L21: =VLOOKUP($F21,全部可转债!$A:$S,6,0) -> 19.734 | M21: =VLOOKUP($F21,全部可转债!$A:$S,18,0) -> 15.8 | N21: =VLOOKUP($F21,全部可转债!$A:$S,8,0) -> 12.903 | O21: =VLOOKUP($F21,全部可转债!$A:$S,15,0) -> 20290406 | P21: =VLOOKUP($F21,全部可转债!$A:$S,14,0) -> 3.286 | R21: =VLOOKUP($F21,全部可转债!$A:$S,11,0) -> 未满足
A22: =VLOOKUP($F22,全部可转债!$A:$S,9,0) -> 30.76 | B22: =L22*100/M22-100 -> 38.464373 | C22: 0 | D22: =VLOOKUP(F22,全部可转债!$A:$S,16,0) -> 122.77 | E22: =VLOOKUP($F22,全部可转债!$A:$S,2,0) -> 113054 | F22: 绿动转债 | G22: =VLOOKUP($F22,全部可转债!$A:$S,7,0) -> 109 | H22: =G22/D22-1 -> -0.11216095 | I22: =VLOOKUP($F22,全部可转债!$A:$S,19,0) -> -1.45 | J22: =VLOOKUP($F22,全部可转债!$A:$S,17,0) -> -0.43 | K22: =VLOOKUP($F22,全部可转债!$A:$S,5,0) -> 8.67 | L22: =VLOOKUP($F22,全部可转债!$A:$S,6,0) -> 11.271 | M22: =VLOOKUP($F22,全部可转债!$A:$S,18,0) -> 8.14 | N22: =VLOOKUP($F22,全部可转债!$A:$S,8,0) -> 7.37 | O22: =VLOOKUP($F22,全部可转债!$A:$S,15,0) -> 20280225 | P22: =VLOOKUP($F22,全部可转债!$A:$S,14,0) -> 23.598 | R22: =VLOOKUP($F22,全部可转债!$A:$S,11,0) -> 未满足
A23: =VLOOKUP($F23,全部可转债!$A:$S,9,0) -> 35.23 | B23: =L23*100/M23-100 -> 40.955291 | C23: 0 | D23: =VLOOKUP(F23,全部可转债!$A:$S,16,0) -> 124.72 | E23: =VLOOKUP($F23,全部可转债!$A:$S,2,0) -> 123142 | F23: 申昊转债 | G23: =VLOOKUP($F23,全部可转债!$A:$S,7,0) -> 110 | H23: =G23/D23-1 -> -0.11802437 | I23: =VLOOKUP($F23,全部可转债!$A:$S,19,0) -> 4.5 | J23: =VLOOKUP($F23,全部可转债!$A:$S,17,0) -> 1.31 | K23: =VLOOKUP($F23,全部可转债!$A:$S,5,0) -> 33.71 | L23: =VLOOKUP($F23,全部可转债!$A:$S,6,0) -> 43.823 | M23: =VLOOKUP($F23,全部可转债!$A:$S,18,0) -> 31.09 | N23: =VLOOKUP($F23,全部可转债!$A:$S,8,0) -> 28.653 | O23: =VLOOKUP($F23,全部可转债!$A:$S,15,0) -> 20280318 | P23: =VLOOKUP($F23,全部可转债!$A:$S,14,0) -> 5.494 | R23: =VLOOKUP($F23,全部可转债!$A:$S,11,0) -> 未满足
A24: =VLOOKUP($F24,全部可转债!$A:$S,9,0) -> 70.57 | B24: =L24*100/M24-100 -> 84.247392 | C24: 0 | D24: =VLOOKUP(F24,全部可转债!$A:$S,16,0) -> 120.35 | E24: =VLOOKUP($F24,全部可转债!$A:$S,2,0) -> 113652 | F24: 伟22转债 | G24: =VLOOKUP($F24,全部可转债!$A:$S,7,0) -> 110 | H24: =G24/D24-1 -> -0.085999169 | I24: =VLOOKUP($F24,全部可转债!$A:$S,19,0) -> 1.51 | J24: =VLOOKUP($F24,全部可转债!$A:$S,17,0) -> 0.94 | K24: =VLOOKUP($F24,全部可转债!$A:$S,5,0) -> 19.02 | L24: =VLOOKUP($F24,全部可转债!$A:$S,6,0) -> 24.726 | M24: =VLOOKUP($F24,全部可转债!$A:$S,18,0) -> 13.42 | N24: =VLOOKUP($F24,全部可转债!$A:$S,8,0) -> 17.118 | O24: =VLOOKUP($F24,全部可转债!$A:$S,15,0) -> 20280722 | P24: =VLOOKUP($F24,全部可转债!$A:$S,14,0) -> 14.766 | R24: =VLOOKUP($F24,全部可转债!$A:$S,11,0) -> 未满足
A25: =VLOOKUP($F25,全部可转债!$A:$S,9,0) -> 11.18 | B25: =L25*100/M25-100 -> 8.6727123 | C25: 0 | D25: =VLOOKUP(F25,全部可转债!$A:$S,16,0) -> 133 | E25: =VLOOKUP($F25,全部可转债!$A:$S,2,0) -> 111015 | F25: 东亚转债 | G25: =VLOOKUP($F25,全部可转债!$A:$S,7,0) -> 115 | H25: =G25/D25-1 -> -0.13533835 | I25: =VLOOKUP($F25,全部可转债!$A:$S,19,0) -> -2.26 | J25: =VLOOKUP($F25,全部可转债!$A:$S,17,0) -> -0.1 | K25: =VLOOKUP($F25,全部可转债!$A:$S,5,0) -> 20.28 | L25: =VLOOKUP($F25,全部可转债!$A:$S,6,0) -> 26.364 | M25: =VLOOKUP($F25,全部可转债!$A:$S,18,0) -> 24.26 | N25: =VLOOKUP($F25,全部可转债!$A:$S,8,0) -> 18.252 | O25: =VLOOKUP($F25,全部可转债!$A:$S,15,0) -> 20290706 | P25: =VLOOKUP($F25,全部可转债!$A:$S,14,0) -> 6.662 | R25: =VLOOKUP($F25,全部可转债!$A:$S,11,0) -> 未满足
A26: =VLOOKUP($F26,全部可转债!$A:$S,9,0) -> 6.77 | B26: =L26*100/M26-100 -> 28.518519 | C26: 0 | D26: =VLOOKUP(F26,全部可转债!$A:$S,16,0) -> 108 | E26: =VLOOKUP($F26,全部可转债!$A:$S,2,0) -> 127061 | F26: 美锦转债 | G26: =VLOOKUP($F26,全部可转债!$A:$S,7,0) -> 118 | H26: =G26/D26-1 -> 0.092592593 | I26: =VLOOKUP($F26,全部可转债!$A:$S,19,0) -> 1.15 | J26: =VLOOKUP($F26,全部可转债!$A:$S,17,0) -> 0.62 | K26: =VLOOKUP($F26,全部可转债!$A:$S,5,0) -> 3.47 | L26: =VLOOKUP($F26,全部可转债!$A:$S,6,0) -> 4.511 | M26: =VLOOKUP($F26,全部可转债!$A:$S,18,0) -> 3.51 | N26: =VLOOKUP($F26,全部可转债!$A:$S,8,0) -> 2.95 | O26: =VLOOKUP($F26,全部可转债!$A:$S,15,0) -> 20280420 | P26: =VLOOKUP($F26,全部可转债!$A:$S,14,0) -> 27.74 | Q26: 7 | R26: =VLOOKUP($F26,全部可转债!$A:$S,11,0) -> 未满足
A27: =VLOOKUP($F27,全部可转债!$A:$S,9,0) -> 42.62 | B27: =L27*100/M27-100 -> 47.215347 | C27: 0 | D27: =VLOOKUP(F27,全部可转债!$A:$S,16,0) -> 125.94 | E27: =VLOOKUP($F27,全部可转债!$A:$S,2,0) -> 123122 | F27: 富瀚转债 | G27: =VLOOKUP($F27,全部可转债!$A:$S,7,0) -> 115 | H27: =G27/D27-1 -> -0.086866762 | I27: =VLOOKUP($F27,全部可转债!$A:$S,19,0) -> -2.08 | J27: =VLOOKUP($F27,全部可转债!$A:$S,17,0) -> -0.73 | K27: =VLOOKUP($F27,全部可转债!$A:$S,5,0) -> 91.5 | L27: =VLOOKUP($F27,全部可转债!$A:$S,6,0) -> 118.95 | M27: =VLOOKUP($F27,全部可转债!$A:$S,18,0) -> 80.8 | N27: =VLOOKUP($F27,全部可转债!$A:$S,8,0) -> 77.775 | O27: =VLOOKUP($F27,全部可转债!$A:$S,15,0) -> 20270806 | P27: =VLOOKUP($F27,全部可转债!$A:$S,14,0) -> 5.801 | Q27: 1119 | R27: =VLOOKUP($F27,全部可转债!$A:$S,11,0) -> 未满足
A28: =VLOOKUP($F28,全部可转债!$A:$S,9,0) -> #N/A | B28: =L28*100/M28-100 -> #N/A | C28: 0 | D28: =VLOOKUP(F28,全部可转债!$A:$S,16,0) -> #N/A | E28: =VLOOKUP($F28,全部可转债!$A:$S,2,0) -> #N/A | F28: 宝莱转债 | G28: =VLOOKUP($F28,全部可转债!$A:$S,7,0) -> #N/A | H28: =G28/D28-1 -> #N/A | I28: =VLOOKUP($F28,全部可转债!$A:$S,19,0) -> #N/A | J28: =VLOOKUP($F28,全部可转债!$A:$S,17,0) -> #N/A | K28: =VLOOKUP($F28,全部可转债!$A:$S,5,0) -> #N/A | L28: =VLOOKUP($F28,全部可转债!$A:$S,6,0) -> #N/A | M28: =VLOOKUP($F28,全部可转债!$A:$S,18,0) -> #N/A | N28: =VLOOKUP($F28,全部可转债!$A:$S,8,0) -> #N/A | O28: =VLOOKUP($F28,全部可转债!$A:$S,15,0) -> #N/A | P28: =VLOOKUP($F28,全部可转债!$A:$S,14,0) -> #N/A | Q28: 3 | R28: =VLOOKUP($F28,全部可转债!$A:$S,11,0) -> #N/A
A29: =VLOOKUP($F29,全部可转债!$A:$S,9,0) -> #N/A | B29: =L29*100/M29-100 -> #N/A | C29: 0 | D29: =VLOOKUP(F29,全部可转债!$A:$S,16,0) -> #N/A | E29: =VLOOKUP($F29,全部可转债!$A:$S,2,0) -> #N/A | F29: 正川转债 | G29: =VLOOKUP($F29,全部可转债!$A:$S,7,0) -> #N/A | H29: =G29/D29-1 -> #N/A | I29: =VLOOKUP($F29,全部可转债!$A:$S,19,0) -> #N/A | J29: =VLOOKUP($F29,全部可转债!$A:$S,17,0) -> #N/A | K29: =VLOOKUP($F29,全部可转债!$A:$S,5,0) -> #N/A | L29: =VLOOKUP($F29,全部可转债!$A:$S,6,0) -> #N/A | M29: =VLOOKUP($F29,全部可转债!$A:$S,18,0) -> #N/A | N29: =VLOOKUP($F29,全部可转债!$A:$S,8,0) -> #N/A | O29: =VLOOKUP($F29,全部可转债!$A:$S,15,0) -> #N/A | P29: =VLOOKUP($F29,全部可转债!$A:$S,14,0) -> #N/A | R29: =VLOOKUP($F29,全部可转债!$A:$S,11,0) -> #N/A
A30: =VLOOKUP($F30,全部可转债!$A:$S,9,0) -> 70.52 | B30: =L30*100/M30-100 -> 77.908903 | C30: 0 | D30: =VLOOKUP(F30,全部可转债!$A:$S,16,0) -> 124.6 | E30: =VLOOKUP($F30,全部可转债!$A:$S,2,0) -> 123216 | F30: 科顺转债 | G30: =VLOOKUP($F30,全部可转债!$A:$S,7,0) -> 115 | H30: =G30/D30-1 -> -0.077046549 | I30: =VLOOKUP($F30,全部可转债!$A:$S,19,0) -> 4.77 | J30: =VLOOKUP($F30,全部可转债!$A:$S,17,0) -> 1.99 | K30: =VLOOKUP($F30,全部可转债!$A:$S,5,0) -> 6.61 | L30: =VLOOKUP($F30,全部可转债!$A:$S,6,0) -> 8.593 | M30: =VLOOKUP($F30,全部可转债!$A:$S,18,0) -> 4.83 | N30: =VLOOKUP($F30,全部可转债!$A:$S,8,0) -> 5.619 | O30: =VLOOKUP($F30,全部可转债!$A:$S,15,0) -> 20290804 | P30: =VLOOKUP($F30,全部可转债!$A:$S,14,0) -> 21.959 | R30: =VLOOKUP($F30,全部可转债!$A:$S,11,0) -> 未满足
A31: =VLOOKUP($F31,全部可转债!$A:$S,9,0) -> 29.31 | B31: =L31*100/M31-100 -> 19.473423 | C31: 0 | D31: =VLOOKUP(F31,全部可转债!$A:$S,16,0) -> 140.71 | E31: =VLOOKUP($F31,全部可转债!$A:$S,2,0) -> 118036 | F31: 力合转债 | G31: =VLOOKUP($F31,全部可转债!$A:$S,7,0) -> 115 | H31: =G31/D31-1 -> -0.18271622 | I31: =VLOOKUP($F31,全部可转债!$A:$S,19,0) -> -2.38 | J31: =VLOOKUP($F31,全部可转债!$A:$S,17,0) -> -0.77 | K31: =VLOOKUP($F31,全部可转债!$A:$S,5,0) -> 18.5 | L31: =VLOOKUP($F31,全部可转债!$A:$S,6,0) -> 24.05 | M31: =VLOOKUP($F31,全部可转债!$A:$S,18,0) -> 20.13 | N31: =VLOOKUP($F31,全部可转债!$A:$S,8,0) -> 15.725 | O31: =VLOOKUP($F31,全部可转债!$A:$S,15,0) -> 20290628 | P31: =VLOOKUP($F31,全部可转债!$A:$S,14,0) -> 3.8 | R31: =VLOOKUP($F31,全部可转债!$A:$S,11,0) -> 未满足 | S31: 0
A32: =VLOOKUP($F32,全部可转债!$A:$S,9,0) -> 55.05 | B32: =L32*100/M32-100 -> 59.974662 | C32: 0 | D32: =VLOOKUP(F32,全部可转债!$A:$S,16,0) -> 126 | E32: =VLOOKUP($F32,全部可转债!$A:$S,2,0) -> 127069 | F32: 小熊转债 | G32: =VLOOKUP($F32,全部可转债!$A:$S,7,0) -> 115 | H32: =G32/D32-1 -> -0.087301587 | I32: =VLOOKUP($F32,全部可转债!$A:$S,19,0) -> -0.08 | J32: =VLOOKUP($F32,全部可转债!$A:$S,17,0) -> 0.36 | K32: =VLOOKUP($F32,全部可转债!$A:$S,5,0) -> 43.71 | L32: =VLOOKUP($F32,全部可转债!$A:$S,6,0) -> 56.823 | M32: =VLOOKUP($F32,全部可转债!$A:$S,18,0) -> 35.52 | N32: =VLOOKUP($F32,全部可转债!$A:$S,8,0) -> 37.154 | O32: =VLOOKUP($F32,全部可转债!$A:$S,15,0) -> 20280812 | P32: =VLOOKUP($F32,全部可转债!$A:$S,14,0) -> 5.041 | R32: =VLOOKUP($F32,全部可转债!$A:$S,11,0) -> 未满足
A33: =VLOOKUP($F33,全部可转债!$A:$S,9,0) -> 50.79 | B33: =L33*100/M33-100 -> 71.661721 | C33: 0 | D33: =VLOOKUP(F33,全部可转债!$A:$S,16,0) -> 114.19 | E33: =VLOOKUP($F33,全部可转债!$A:$S,2,0) -> 127089 | F33: 晶澳转债 | G33: =VLOOKUP($F33,全部可转债!$A:$S,7,0) -> 108 | H33: =G33/D33-1 -> -0.054207899 | I33: =VLOOKUP($F33,全部可转债!$A:$S,19,0) -> 2.12 | J33: =VLOOKUP($F33,全部可转债!$A:$S,17,0) -> 0.5 | K33: =VLOOKUP($F33,全部可转债!$A:$S,5,0) -> 8.9 | L33: =VLOOKUP($F33,全部可转债!$A:$S,6,0) -> 11.57 | M33: =VLOOKUP($F33,全部可转债!$A:$S,18,0) -> 6.74 | N33: =VLOOKUP($F33,全部可转债!$A:$S,8,0) -> 7.565 | O33: =VLOOKUP($F33,全部可转债!$A:$S,15,0) -> 20290718 | P33: =VLOOKUP($F33,全部可转债!$A:$S,14,0) -> 89.588 | R33: =VLOOKUP($F33,全部可转债!$A:$S,11,0) -> 未满足
A34: =VLOOKUP($F34,全部可转债!$A:$S,9,0) -> 35.68 | B34: =L34*100/M34-100 -> 36.847042 | C34: 3 | D34: =VLOOKUP(F34,全部可转债!$A:$S,16,0) -> 128.89 | E34: =VLOOKUP($F34,全部可转债!$A:$S,2,0) -> 113661 | F34: 福22转债 | G34: =VLOOKUP($F34,全部可转债!$A:$S,7,0) -> 110 | H34: =G34/D34-1 -> -0.14655908 | I34: =VLOOKUP($F34,全部可转债!$A:$S,19,0) -> 0.73 | J34: =VLOOKUP($F34,全部可转债!$A:$S,17,0) -> 0.57 | K34: =VLOOKUP($F34,全部可转债!$A:$S,5,0) -> 14.59 | L34: =VLOOKUP($F34,全部可转债!$A:$S,6,0) -> 18.967 | M34: =VLOOKUP($F34,全部可转债!$A:$S,18,0) -> 13.86 | N34: =VLOOKUP($F34,全部可转债!$A:$S,8,0) -> 12.402 | O34: =VLOOKUP($F34,全部可转债!$A:$S,15,0) -> 20281122 | P34: =VLOOKUP($F34,全部可转债!$A:$S,14,0) -> 30.297 | R34: =VLOOKUP($F34,全部可转债!$A:$S,11,0) -> 未满足
A35: =VLOOKUP($F35,全部可转债!$A:$S,9,0) -> 24.15 | B35: =L35*100/M35-100 -> 24.94012 | C35: 8 | D35: =VLOOKUP(F35,全部可转债!$A:$S,16,0) -> 129.18 | E35: =VLOOKUP($F35,全部可转债!$A:$S,2,0) -> 110084 | F35: 贵燃转债 | G35: =VLOOKUP($F35,全部可转债!$A:$S,7,0) -> 110 | H35: =G35/D35-1 -> -0.148475 | I35: =VLOOKUP($F35,全部可转债!$A:$S,19,0) -> 2.61 | J35: =VLOOKUP($F35,全部可转债!$A:$S,17,0) -> 0.8 | K35: =VLOOKUP($F35,全部可转债!$A:$S,5,0) -> 6.42 | L35: =VLOOKUP($F35,全部可转债!$A:$S,6,0) -> 8.346 | M35: =VLOOKUP($F35,全部可转债!$A:$S,18,0) -> 6.68 | N35: =VLOOKUP($F35,全部可转债!$A:$S,8,0) -> 5.457 | O35: =VLOOKUP($F35,全部可转债!$A:$S,15,0) -> 20271227 | P35: =VLOOKUP($F35,全部可转债!$A:$S,14,0) -> 8.157 | R35: =VLOOKUP($F35,全部可转债!$A:$S,11,0) -> 未满足
A36: =VLOOKUP($F36,全部可转债!$A:$S,9,0) -> #N/A | B36: =L36*100/M36-100 -> #N/A | C36: -1 | D36: =VLOOKUP(F36,全部可转债!$A:$S,16,0) -> #N/A | E36: =VLOOKUP($F36,全部可转债!$A:$S,2,0) -> #N/A | F36: 艾迪转债 | G36: =VLOOKUP($F36,全部可转债!$A:$S,7,0) -> #N/A | H36: =G36/D36-1 -> #N/A | I36: =VLOOKUP($F36,全部可转债!$A:$S,19,0) -> #N/A | J36: =VLOOKUP($F36,全部可转债!$A:$S,17,0) -> #N/A | K36: =VLOOKUP($F36,全部可转债!$A:$S,5,0) -> #N/A | L36: =VLOOKUP($F36,全部可转债!$A:$S,6,0) -> #N/A | M36: =VLOOKUP($F36,全部可转债!$A:$S,18,0) -> #N/A | N36: =VLOOKUP($F36,全部可转债!$A:$S,8,0) -> #N/A | O36: =VLOOKUP($F36,全部可转债!$A:$S,15,0) -> #N/A | P36: =VLOOKUP($F36,全部可转债!$A:$S,14,0) -> #N/A | R36: =VLOOKUP($F36,全部可转债!$A:$S,11,0) -> #N/A
A37: =VLOOKUP($F37,全部可转债!$A:$S,9,0) -> 32.32 | B37: =L37*100/M37-100 -> 30.613208 | C37: 0 | D37: =VLOOKUP(F37,全部可转债!$A:$S,16,0) -> 131.7 | E37: =VLOOKUP($F37,全部可转债!$A:$S,2,0) -> 123172 | F37: 漱玉转债 | G37: =VLOOKUP($F37,全部可转债!$A:$S,7,0) -> 113 | H37: =G37/D37-1 -> -0.14198937 | I37: =VLOOKUP($F37,全部可转债!$A:$S,19,0) -> 5.7 | J37: =VLOOKUP($F37,全部可转债!$A:$S,17,0) -> 2.39 | K37: =VLOOKUP($F37,全部可转债!$A:$S,5,0) -> 14.91 | L37: =VLOOKUP($F37,全部可转债!$A:$S,6,0) -> 19.383 | M37: =VLOOKUP($F37,全部可转债!$A:$S,18,0) -> 14.84 | N37: =VLOOKUP($F37,全部可转债!$A:$S,8,0) -> 12.673 | O37: =VLOOKUP($F37,全部可转债!$A:$S,15,0) -> 20281215 | P37: =VLOOKUP($F37,全部可转债!$A:$S,14,0) -> 7.96 | R37: =VLOOKUP($F37,全部可转债!$A:$S,11,0) -> 未满足
A38: =VLOOKUP($F38,全部可转债!$A:$S,9,0) -> 53.04 | B38: =L38*100/M38-100 -> 47.782274 | C38: 0 | D38: =VLOOKUP(F38,全部可转债!$A:$S,16,0) -> 134.62 | E38: =VLOOKUP($F38,全部可转债!$A:$S,2,0) -> 123224 | F38: 宇邦转债 | G38: =VLOOKUP($F38,全部可转债!$A:$S,7,0) -> 115 | H38: =G38/D38-1 -> -0.14574357 | I38: =VLOOKUP($F38,全部可转债!$A:$S,19,0) -> -0.2 | J38: =VLOOKUP($F38,全部可转债!$A:$S,17,0) -> 0 | K38: =VLOOKUP($F38,全部可转债!$A:$S,5,0) -> 28.09 | L38: =VLOOKUP($F38,全部可转债!$A:$S,6,0) -> 36.517 | M38: =VLOOKUP($F38,全部可转债!$A:$S,18,0) -> 24.71 | N38: =VLOOKUP($F38,全部可转债!$A:$S,8,0) -> 23.877 | O38: =VLOOKUP($F38,全部可转债!$A:$S,15,0) -> 20290919 | P38: =VLOOKUP($F38,全部可转债!$A:$S,14,0) -> 2.848 | R38: =VLOOKUP($F38,全部可转债!$A:$S,11,0) -> 未满足
A39: =VLOOKUP($F39,全部可转债!$A:$S,9,0) -> 37.31 | B39: =L39*100/M39-100 -> 48.599496 | C39: 0 | D39: =VLOOKUP(F39,全部可转债!$A:$S,16,0) -> 120.12 | E39: =VLOOKUP($F39,全部可转债!$A:$S,2,0) -> 123114 | F39: 三角转债 | G39: =VLOOKUP($F39,全部可转债!$A:$S,7,0) -> 115 | H39: =G39/D39-1 -> -0.042624043 | I39: =VLOOKUP($F39,全部可转债!$A:$S,19,0) -> -0.65 | J39: =VLOOKUP($F39,全部可转债!$A:$S,17,0) -> 0.19 | K39: =VLOOKUP($F39,全部可转债!$A:$S,5,0) -> 22.69 | L39: =VLOOKUP($F39,全部可转债!$A:$S,6,0) -> 29.497 | M39: =VLOOKUP($F39,全部可转债!$A:$S,18,0) -> 19.85 | N39: =VLOOKUP($F39,全部可转债!$A:$S,8,0) -> 19.287 | O39: =VLOOKUP($F39,全部可转债!$A:$S,15,0) -> 20270525 | P39: =VLOOKUP($F39,全部可转债!$A:$S,14,0) -> 8.999 | R39: =VLOOKUP($F39,全部可转债!$A:$S,11,0) -> 未满足
A40: =VLOOKUP($F40,全部可转债!$A:$S,9,0) -> 27.65 | B40: =L40*100/M40-100 -> 35.602873 | C40: 0 | D40: =VLOOKUP(F40,全部可转债!$A:$S,16,0) -> 122.37 | E40: =VLOOKUP($F40,全部可转债!$A:$S,2,0) -> 127046 | F40: 百润转债 | G40: =VLOOKUP($F40,全部可转债!$A:$S,7,0) -> 110 | H40: =G40/D40-1 -> -0.10108687 | I40: =VLOOKUP($F40,全部可转债!$A:$S,19,0) -> 3.07 | J40: =VLOOKUP($F40,全部可转债!$A:$S,17,0) -> -0.13 | K40: =VLOOKUP($F40,全部可转债!$A:$S,5,0) -> 20.33 | L40: =VLOOKUP($F40,全部可转债!$A:$S,6,0) -> 26.429 | M40: =VLOOKUP($F40,全部可转债!$A:$S,18,0) -> 19.49 | N40: =VLOOKUP($F40,全部可转债!$A:$S,8,0) -> 17.28 | O40: =VLOOKUP($F40,全部可转债!$A:$S,15,0) -> 20270929 | P40: =VLOOKUP($F40,全部可转债!$A:$S,14,0) -> 11.274 | R40: =VLOOKUP($F40,全部可转债!$A:$S,11,0) -> 未满足
A41: =VLOOKUP($F41,全部可转债!$A:$S,9,0) -> 49.74 | B41: =L41*100/M41-100 -> 66.730159 | C41: 0 | D41: =VLOOKUP(F41,全部可转债!$A:$S,16,0) -> 116.75 | E41: =VLOOKUP($F41,全部可转债!$A:$S,2,0) -> 110093 | F41: 神马转债 | G41: =VLOOKUP($F41,全部可转债!$A:$S,7,0) -> 107 | H41: =G41/D41-1 -> -0.083511777 | I41: =VLOOKUP($F41,全部可转债!$A:$S,19,0) -> 1.29 | J41: =VLOOKUP($F41,全部可转债!$A:$S,17,0) -> 0.57 | K41: =VLOOKUP($F41,全部可转债!$A:$S,5,0) -> 8.08 | L41: =VLOOKUP($F41,全部可转债!$A:$S,6,0) -> 10.504 | M41: =VLOOKUP($F41,全部可转债!$A:$S,18,0) -> 6.3 | N41: =VLOOKUP($F41,全部可转债!$A:$S,8,0) -> 6.464 | O41: =VLOOKUP($F41,全部可转债!$A:$S,15,0) -> 20290316 | P41: =VLOOKUP($F41,全部可转债!$A:$S,14,0) -> 22.197 | R41: =VLOOKUP($F41,全部可转债!$A:$S,11,0) -> 未满足
A42: =VLOOKUP($F42,全部可转债!$A:$S,9,0) -> 72.61 | B42: =L42*100/M42-100 -> 99.354839 | C42: 0 | D42: =VLOOKUP(F42,全部可转债!$A:$S,16,0) -> 112.56 | E42: =VLOOKUP($F42,全部可转债!$A:$S,2,0) -> 110095 | F42: 双良转债 | G42: =VLOOKUP($F42,全部可转债!$A:$S,7,0) -> 110 | H42: =G42/D42-1 -> -0.022743426 | I42: =VLOOKUP($F42,全部可转债!$A:$S,19,0) -> 3.07 | J42: =VLOOKUP($F42,全部可转债!$A:$S,17,0) -> 0.97 | K42: =VLOOKUP($F42,全部可转债!$A:$S,5,0) -> 6.18 | L42: =VLOOKUP($F42,全部可转债!$A:$S,6,0) -> 8.034 | M42: =VLOOKUP($F42,全部可转债!$A:$S,18,0) -> 4.03 | N42: =VLOOKUP($F42,全部可转债!$A:$S,8,0) -> 5.253 | O42: =VLOOKUP($F42,全部可转债!$A:$S,15,0) -> 20290808 | P42: =VLOOKUP($F42,全部可转债!$A:$S,14,0) -> 14.006 | R42: =VLOOKUP($F42,全部可转债!$A:$S,11,0) -> 未满足
A43: =VLOOKUP($F43,全部可转债!$A:$S,9,0) -> 56.16 | B43: =L43*100/M43-100 -> 57.619048 | C43: 0 | D43: =VLOOKUP(F43,全部可转债!$A:$S,16,0) -> 128.8 | E43: =VLOOKUP($F43,全部可转债!$A:$S,2,0) -> 123214 | F43: 东宝转债 | G43: =VLOOKUP($F43,全部可转债!$A:$S,7,0) -> 113 | H43: =G43/D43-1 -> -0.12267081 | I43: =VLOOKUP($F43,全部可转债!$A:$S,19,0) -> 0.74 | J43: =VLOOKUP($F43,全部可转债!$A:$S,17,0) -> 0.95 | K43: =VLOOKUP($F43,全部可转债!$A:$S,5,0) -> 6.62 | L43: =VLOOKUP($F43,全部可转债!$A:$S,6,0) -> 8.606 | M43: =VLOOKUP($F43,全部可转债!$A:$S,18,0) -> 5.46 | N43: =VLOOKUP($F43,全部可转债!$A:$S,8,0) -> 5.958 | O43: =VLOOKUP($F43,全部可转债!$A:$S,15,0) -> 20290731 | P43: =VLOOKUP($F43,全部可转债!$A:$S,14,0) -> 4.549 | Q43: 1111 | R43: =VLOOKUP($F43,全部可转债!$A:$S,11,0) -> 未满足
A44: =VLOOKUP($F44,全部可转债!$A:$S,9,0) -> 32.24 | B44: =L44*100/M44-100 -> 25.494548 | C44: 0 | D44: =VLOOKUP(F44,全部可转债!$A:$S,16,0) -> 136.99 | E44: =VLOOKUP($F44,全部可转债!$A:$S,2,0) -> 123194 | F44: 百洋转债 | G44: =VLOOKUP($F44,全部可转债!$A:$S,7,0) -> 113 | H44: =G44/D44-1 -> -0.17512227 | I44: =VLOOKUP($F44,全部可转债!$A:$S,19,0) -> 2.56 | J44: =VLOOKUP($F44,全部可转债!$A:$S,17,0) -> 1.48 | K44: =VLOOKUP($F44,全部可转债!$A:$S,5,0) -> 24.79 | L44: =VLOOKUP($F44,全部可转债!$A:$S,6,0) -> 32.227 | M44: =VLOOKUP($F44,全部可转债!$A:$S,18,0) -> 25.68 | N44: =VLOOKUP($F44,全部可转债!$A:$S,8,0) -> 21.072 | O44: =VLOOKUP($F44,全部可转债!$A:$S,15,0) -> 20290414 | P44: =VLOOKUP($F44,全部可转债!$A:$S,14,0) -> 8.459 | R44: =VLOOKUP($F44,全部可转债!$A:$S,11,0) -> 未满足
A45: =VLOOKUP($F45,全部可转债!$A:$S,9,0) -> #N/A | B45: =L45*100/M45-100 -> #N/A | C45: -1 | D45: =VLOOKUP(F45,全部可转债!$A:$S,16,0) -> #N/A | E45: =VLOOKUP($F45,全部可转债!$A:$S,2,0) -> #N/A | F45: 立昂转债 | G45: =VLOOKUP($F45,全部可转债!$A:$S,7,0) -> #N/A | H45: =G45/D45-1 -> #N/A | I45: =VLOOKUP($F45,全部可转债!$A:$S,19,0) -> #N/A | J45: =VLOOKUP($F45,全部可转债!$A:$S,17,0) -> #N/A | K45: =VLOOKUP($F45,全部可转债!$A:$S,5,0) -> #N/A | L45: =VLOOKUP($F45,全部可转债!$A:$S,6,0) -> #N/A | M45: =VLOOKUP($F45,全部可转债!$A:$S,18,0) -> #N/A | N45: =VLOOKUP($F45,全部可转债!$A:$S,8,0) -> #N/A | O45: =VLOOKUP($F45,全部可转债!$A:$S,15,0) -> #N/A | P45: =VLOOKUP($F45,全部可转债!$A:$S,14,0) -> #N/A | R45: =VLOOKUP($F45,全部可转债!$A:$S,11,0) -> #N/A
A46: =VLOOKUP($F46,全部可转债!$A:$S,9,0) -> #N/A | B46: =L46*100/M46-100 -> #N/A | C46: -1 | D46: =VLOOKUP(F46,全部可转债!$A:$S,16,0) -> #N/A | E46: =VLOOKUP($F46,全部可转债!$A:$S,2,0) -> #N/A | F46: 瑞科转债 | G46: =VLOOKUP($F46,全部可转债!$A:$S,7,0) -> #N/A | H46: =G46/D46-1 -> #N/A | I46: =VLOOKUP($F46,全部可转债!$A:$S,19,0) -> #N/A | J46: =VLOOKUP($F46,全部可转债!$A:$S,17,0) -> #N/A | K46: =VLOOKUP($F46,全部可转债!$A:$S,5,0) -> #N/A | L46: =VLOOKUP($F46,全部可转债!$A:$S,6,0) -> #N/A | M46: =VLOOKUP($F46,全部可转债!$A:$S,18,0) -> #N/A | N46: =VLOOKUP($F46,全部可转债!$A:$S,8,0) -> #N/A | O46: =VLOOKUP($F46,全部可转债!$A:$S,15,0) -> #N/A | P46: =VLOOKUP($F46,全部可转债!$A:$S,14,0) -> #N/A | R46: =VLOOKUP($F46,全部可转债!$A:$S,11,0) -> #N/A
A47: =VLOOKUP($F47,全部可转债!$A:$S,9,0) -> 40.66 | B47: =L47*100/M47-100 -> 34.911576 | C47: 6 | D47: =VLOOKUP(F47,全部可转债!$A:$S,16,0) -> 135.54 | E47: =VLOOKUP($F47,全部可转债!$A:$S,2,0) -> 113680 | F47: 丽岛转债 | G47: =VLOOKUP($F47,全部可转债!$A:$S,7,0) -> 115 | H47: =G47/D47-1 -> -0.15154198 | I47: =VLOOKUP($F47,全部可转债!$A:$S,19,0) -> -3.34 | J47: =VLOOKUP($F47,全部可转债!$A:$S,17,0) -> -1.32 | K47: =VLOOKUP($F47,全部可转债!$A:$S,5,0) -> 12.91 | L47: =VLOOKUP($F47,全部可转债!$A:$S,6,0) -> 16.783 | M47: =VLOOKUP($F47,全部可转债!$A:$S,18,0) -> 12.44 | N47: =VLOOKUP($F47,全部可转债!$A:$S,8,0) -> 10.973 | O47: =VLOOKUP($F47,全部可转债!$A:$S,15,0) -> 20291115 | P47: =VLOOKUP($F47,全部可转债!$A:$S,14,0) -> 2.998 | R47: =VLOOKUP($F47,全部可转债!$A:$S,11,0) -> 未满足
A48: =VLOOKUP($F48,全部可转债!$A:$S,9,0) -> 72.95 | B48: =L48*100/M48-100 -> 76.338553 | C48: 11 | D48: =VLOOKUP(F48,全部可转债!$A:$S,16,0) -> 127.5 | E48: =VLOOKUP($F48,全部可转债!$A:$S,2,0) -> 123253 | F48: 永贵转债 | G48: =VLOOKUP($F48,全部可转债!$A:$S,7,0) -> 113 | H48: =G48/D48-1 -> -0.11372549 | I48: =VLOOKUP($F48,全部可转债!$A:$S,19,0) -> -1.18 | J48: =VLOOKUP($F48,全部可转债!$A:$S,17,0) -> -0.31 | K48: =VLOOKUP($F48,全部可转债!$A:$S,5,0) -> 18.19 | L48: =VLOOKUP($F48,全部可转债!$A:$S,6,0) -> 23.647 | M48: =VLOOKUP($F48,全部可转债!$A:$S,18,0) -> 13.41 | N48: =VLOOKUP($F48,全部可转债!$A:$S,8,0) -> 15.462 | O48: =VLOOKUP($F48,全部可转债!$A:$S,15,0) -> 20310313 | P48: =VLOOKUP($F48,全部可转债!$A:$S,14,0) -> 9.797 | R48: =VLOOKUP($F48,全部可转债!$A:$S,11,0) -> 未满足
A49: =VLOOKUP($F49,全部可转债!$A:$S,9,0) -> 70.57 | B49: =L49*100/M49-100 -> 84.247392 | C49: 0 | D49: =VLOOKUP(F49,全部可转债!$A:$S,16,0) -> 120.35 | E49: =VLOOKUP($F49,全部可转债!$A:$S,2,0) -> 113652 | F49: 伟22转债 | G49: =VLOOKUP($F49,全部可转债!$A:$S,7,0) -> 110 | H49: =G49/D49-1 -> -0.085999169 | I49: =VLOOKUP($F49,全部可转债!$A:$S,19,0) -> 1.51 | J49: =VLOOKUP($F49,全部可转债!$A:$S,17,0) -> 0.94 | K49: =VLOOKUP($F49,全部可转债!$A:$S,5,0) -> 19.02 | L49: =VLOOKUP($F49,全部可转债!$A:$S,6,0) -> 24.726 | M49: =VLOOKUP($F49,全部可转债!$A:$S,18,0) -> 13.42 | N49: =VLOOKUP($F49,全部可转债!$A:$S,8,0) -> 17.118 | O49: =VLOOKUP($F49,全部可转债!$A:$S,15,0) -> 20280722 | P49: =VLOOKUP($F49,全部可转债!$A:$S,14,0) -> 14.766 | Q49: -1 | R49: =VLOOKUP($F49,全部可转债!$A:$S,11,0) -> 未满足
A50: =VLOOKUP($F50,全部可转债!$A:$S,9,0) -> 173.49 | B50: =L50*100/M50-100 -> 224.78716 | C50: 0 | D50: =VLOOKUP(F50,全部可转债!$A:$S,16,0) -> 109.47 | E50: =VLOOKUP($F50,全部可转债!$A:$S,2,0) -> 123117 | F50: 健帆转债 | G50: =VLOOKUP($F50,全部可转债!$A:$S,7,0) -> 110 | H50: =G50/D50-1 -> 0.0048415091 | I50: =VLOOKUP($F50,全部可转债!$A:$S,19,0) -> 2.28 | J50: =VLOOKUP($F50,全部可转债!$A:$S,17,0) -> 0.02 | K50: =VLOOKUP($F50,全部可转债!$A:$S,5,0) -> 38.15 | L50: =VLOOKUP($F50,全部可转债!$A:$S,6,0) -> 49.595 | M50: =VLOOKUP($F50,全部可转债!$A:$S,18,0) -> 15.27 | N50: =VLOOKUP($F50,全部可转债!$A:$S,8,0) -> 32.428 | O50: =VLOOKUP($F50,全部可转债!$A:$S,15,0) -> 20270623 | P50: =VLOOKUP($F50,全部可转债!$A:$S,14,0) -> 9.998 | Q50: 817 | R50: =VLOOKUP($F50,全部可转债!$A:$S,11,0) -> 未满足
A51: =VLOOKUP($F51,全部可转债!$A:$S,9,0) -> 12.35 | B51: =L51*100/M51-100 -> 26.221929 | C51: 0 | D51: =VLOOKUP(F51,全部可转债!$A:$S,16,0) -> 115.71 | E51: =VLOOKUP($F51,全部可转债!$A:$S,2,0) -> 127040 | F51: 国泰转债 | G51: =VLOOKUP($F51,全部可转债!$A:$S,7,0) -> 108 | H51: =G51/D51-1 -> -0.066632097 | I51: =VLOOKUP($F51,全部可转债!$A:$S,19,0) -> 1.47 | J51: =VLOOKUP($F51,全部可转债!$A:$S,17,0) -> 1.63 | K51: =VLOOKUP($F51,全部可转债!$A:$S,5,0) -> 7.35 | L51: =VLOOKUP($F51,全部可转债!$A:$S,6,0) -> 9.555 | M51: =VLOOKUP($F51,全部可转债!$A:$S,18,0) -> 7.57 | N51: =VLOOKUP($F51,全部可转债!$A:$S,8,0) -> 6.247 | O51: =VLOOKUP($F51,全部可转债!$A:$S,15,0) -> 20270707 | P51: =VLOOKUP($F51,全部可转债!$A:$S,14,0) -> 39.862 | R51: =VLOOKUP($F51,全部可转债!$A:$S,11,0) -> 未满足
A52: =VLOOKUP($F52,全部可转债!$A:$S,9,0) -> 18.65 | B52: =L52*100/M52-100 -> 38.339947 | C52: 0 | D52: =VLOOKUP(F52,全部可转债!$A:$S,16,0) -> 111.5 | E52: =VLOOKUP($F52,全部可转债!$A:$S,2,0) -> 123107 | F52: 温氏转债 | G52: =VLOOKUP($F52,全部可转债!$A:$S,7,0) -> 108 | H52: =G52/D52-1 -> -0.031390135 | I52: =VLOOKUP($F52,全部可转债!$A:$S,19,0) -> 0.27 | J52: =VLOOKUP($F52,全部可转债!$A:$S,17,0) -> 0.4 | K52: =VLOOKUP($F52,全部可转债!$A:$S,5,0) -> 16.09 | L52: =VLOOKUP($F52,全部可转债!$A:$S,6,0) -> 20.917 | M52: =VLOOKUP($F52,全部可转债!$A:$S,18,0) -> 15.12 | N52: =VLOOKUP($F52,全部可转债!$A:$S,8,0) -> 14.481 | O52: =VLOOKUP($F52,全部可转债!$A:$S,15,0) -> 20270329 | P52: =VLOOKUP($F52,全部可转债!$A:$S,14,0) -> 77.063 | R52: =VLOOKUP($F52,全部可转债!$A:$S,11,0) -> 未满足
A53: =VLOOKUP($F53,全部可转债!$A:$S,9,0) -> -0.34 | B53: =L53*100/M53-100 -> 12.918089 | C53: 4 | D53: =VLOOKUP(F53,全部可转债!$A:$S,16,0) -> 114.73 | E53: =VLOOKUP($F53,全部可转债!$A:$S,2,0) -> 113046 | F53: 金田转债 | G53: =VLOOKUP($F53,全部可转债!$A:$S,7,0) -> 110 | H53: =G53/D53-1 -> -0.041227229 | I53: =VLOOKUP($F53,全部可转债!$A:$S,19,0) -> 3.53 | J53: =VLOOKUP($F53,全部可转债!$A:$S,17,0) -> 3.19 | K53: =VLOOKUP($F53,全部可转债!$A:$S,5,0) -> 10.18 | L53: =VLOOKUP($F53,全部可转债!$A:$S,6,0) -> 13.234 | M53: =VLOOKUP($F53,全部可转债!$A:$S,18,0) -> 11.72 | N53: =VLOOKUP($F53,全部可转债!$A:$S,8,0) -> 8.144 | O53: =VLOOKUP($F53,全部可转债!$A:$S,15,0) -> 20270322 | P53: =VLOOKUP($F53,全部可转债!$A:$S,14,0) -> 12.518 | R53: =VLOOKUP($F53,全部可转债!$A:$S,11,0) -> 公告强赎
A54: =VLOOKUP($F54,全部可转债!$A:$S,9,0) -> 343.3 | B54: =L54*100/M54-100 -> 376.86822 | C54: 0 | D54: =VLOOKUP(F54,全部可转债!$A:$S,16,0) -> 120.85 | E54: =VLOOKUP($F54,全部可转债!$A:$S,2,0) -> 123179 | F54: 立高转债 | G54: =VLOOKUP($F54,全部可转债!$A:$S,7,0) -> 115 | H54: =G54/D54-1 -> -0.048407116 | I54: =VLOOKUP($F54,全部可转债!$A:$S,19,0) -> 1.42 | J54: =VLOOKUP($F54,全部可转债!$A:$S,17,0) -> 0.11 | K54: =VLOOKUP($F54,全部可转债!$A:$S,5,0) -> 94.64 | L54: =VLOOKUP($F54,全部可转债!$A:$S,6,0) -> 123.032 | M54: =VLOOKUP($F54,全部可转债!$A:$S,18,0) -> 25.8 | N54: =VLOOKUP($F54,全部可转债!$A:$S,8,0) -> 80.444 | O54: =VLOOKUP($F54,全部可转债!$A:$S,15,0) -> 20290307 | P54: =VLOOKUP($F54,全部可转债!$A:$S,14,0) -> 9.499 | Q54: 1107 | R54: =VLOOKUP($F54,全部可转债!$A:$S,11,0) -> 未满足
A55: =VLOOKUP($F55,全部可转债!$A:$S,9,0) -> 186.83 | B55: =L55*100/M55-100 -> 215.55066 | C55: 0 | D55: =VLOOKUP(F55,全部可转债!$A:$S,16,0) -> 118.17 | E55: =VLOOKUP($F55,全部可转债!$A:$S,2,0) -> 123151 | F55: 康医转债 | G55: =VLOOKUP($F55,全部可转债!$A:$S,7,0) -> 115 | H55: =G55/D55-1 -> -0.026825759 | I55: =VLOOKUP($F55,全部可转债!$A:$S,19,0) -> 0.09 | J55: =VLOOKUP($F55,全部可转债!$A:$S,17,0) -> 0.04 | K55: =VLOOKUP($F55,全部可转债!$A:$S,5,0) -> 27.55 | L55: =VLOOKUP($F55,全部可转债!$A:$S,6,0) -> 35.815 | M55: =VLOOKUP($F55,全部可转债!$A:$S,18,0) -> 11.35 | N55: =VLOOKUP($F55,全部可转债!$A:$S,8,0) -> 23.418 | O55: =VLOOKUP($F55,全部可转债!$A:$S,15,0) -> 20280701 | P55: =VLOOKUP($F55,全部可转债!$A:$S,14,0) -> 6.998 | Q55: 1019 | R55: =VLOOKUP($F55,全部可转债!$A:$S,11,0) -> 未满足
A56: =VLOOKUP($F56,全部可转债!$A:$S,9,0) -> 39.32 | B56: =L56*100/M56-100 -> 43.987342 | C56: 0 | D56: =VLOOKUP(F56,全部可转债!$A:$S,16,0) -> 125.79 | E56: =VLOOKUP($F56,全部可转债!$A:$S,2,0) -> 123144 | F56: 裕兴转债 | G56: =VLOOKUP($F56,全部可转债!$A:$S,7,0) -> 115 | H56: =G56/D56-1 -> -0.085777884 | I56: =VLOOKUP($F56,全部可转债!$A:$S,19,0) -> -3.07 | J56: =VLOOKUP($F56,全部可转债!$A:$S,17,0) -> -0.55 | K56: =VLOOKUP($F56,全部可转债!$A:$S,5,0) -> 7 | L56: =VLOOKUP($F56,全部可转债!$A:$S,6,0) -> 9.1 | M56: =VLOOKUP($F56,全部可转债!$A:$S,18,0) -> 6.32 | N56: =VLOOKUP($F56,全部可转债!$A:$S,8,0) -> 5.95 | O56: =VLOOKUP($F56,全部可转债!$A:$S,15,0) -> 20280411 | P56: =VLOOKUP($F56,全部可转债!$A:$S,14,0) -> 5.997 | Q56: 707 | R56: =VLOOKUP($F56,全部可转债!$A:$S,11,0) -> 未满足
A57: =VLOOKUP($F57,全部可转债!$A:$S,9,0) -> 41.4 | B57: =L57*100/M57-100 -> 62.6564 | C57: 0 | D57: =VLOOKUP(F57,全部可转债!$A:$S,16,0) -> 113.02 | E57: =VLOOKUP($F57,全部可转债!$A:$S,2,0) -> 123175 | F57: 百畅转债 | G57: =VLOOKUP($F57,全部可转债!$A:$S,7,0) -> 112 | H57: =G57/D57-1 -> -0.0090249513 | I57: =VLOOKUP($F57,全部可转债!$A:$S,19,0) -> -1.33 | J57: =VLOOKUP($F57,全部可转债!$A:$S,17,0) -> -0.71 | K57: =VLOOKUP($F57,全部可转债!$A:$S,5,0) -> 13 | L57: =VLOOKUP($F57,全部可转债!$A:$S,6,0) -> 16.9 | M57: =VLOOKUP($F57,全部可转债!$A:$S,18,0) -> 10.39 | N57: =VLOOKUP($F57,全部可转债!$A:$S,8,0) -> 11.05 | O57: =VLOOKUP($F57,全部可转债!$A:$S,15,0) -> 20290222 | P57: =VLOOKUP($F57,全部可转债!$A:$S,14,0) -> 4.199 | Q57: 714 | R57: =VLOOKUP($F57,全部可转债!$A:$S,11,0) -> 未满足
A58: =VLOOKUP($F58,全部可转债!$A:$S,9,0) -> #N/A | B58: =L58*100/M58-100 -> #N/A | C58: 11 | D58: =VLOOKUP(F58,全部可转债!$A:$S,16,0) -> #N/A | E58: =VLOOKUP($F58,全部可转债!$A:$S,2,0) -> #N/A | F58: 兴瑞转债 | G58: =VLOOKUP($F58,全部可转债!$A:$S,7,0) -> #N/A | H58: =G58/D58-1 -> #N/A | I58: =VLOOKUP($F58,全部可转债!$A:$S,19,0) -> #N/A | J58: =VLOOKUP($F58,全部可转债!$A:$S,17,0) -> #N/A | K58: =VLOOKUP($F58,全部可转债!$A:$S,5,0) -> #N/A | L58: =VLOOKUP($F58,全部可转债!$A:$S,6,0) -> #N/A | M58: =VLOOKUP($F58,全部可转债!$A:$S,18,0) -> #N/A | N58: =VLOOKUP($F58,全部可转债!$A:$S,8,0) -> #N/A | O58: =VLOOKUP($F58,全部可转债!$A:$S,15,0) -> #N/A | P58: =VLOOKUP($F58,全部可转债!$A:$S,14,0) -> #N/A | R58: =VLOOKUP($F58,全部可转债!$A:$S,11,0) -> #N/A
A59: =VLOOKUP($F59,全部可转债!$A:$S,9,0) -> 18.08 | B59: =L59*100/M59-100 -> -4.6537602 | C59: 15 | D59: =VLOOKUP(F59,全部可转债!$A:$S,16,0) -> 161 | E59: =VLOOKUP($F59,全部可转债!$A:$S,2,0) -> 123160 | F59: 泰福转债 | G59: =VLOOKUP($F59,全部可转债!$A:$S,7,0) -> 115 | H59: =G59/D59-1 -> -0.28571429 | I59: =VLOOKUP($F59,全部可转债!$A:$S,19,0) -> -3 | J59: =VLOOKUP($F59,全部可转债!$A:$S,17,0) -> -0.87 | K59: =VLOOKUP($F59,全部可转债!$A:$S,5,0) -> 19.7 | L59: =VLOOKUP($F59,全部可转债!$A:$S,6,0) -> 25.61 | M59: =VLOOKUP($F59,全部可转债!$A:$S,18,0) -> 26.86 | N59: =VLOOKUP($F59,全部可转债!$A:$S,8,0) -> 16.745 | O59: =VLOOKUP($F59,全部可转债!$A:$S,15,0) -> 20280928 | P59: =VLOOKUP($F59,全部可转债!$A:$S,14,0) -> 2.314 | R59: =VLOOKUP($F59,全部可转债!$A:$S,11,0) -> 暂不强赎
A60: =VLOOKUP($F60,全部可转债!$A:$S,9,0) -> 97.93 | B60: =L60*100/M60-100 -> 104.91367 | C60: 0 | D60: =VLOOKUP(F60,全部可转债!$A:$S,16,0) -> 125.57 | E60: =VLOOKUP($F60,全部可转债!$A:$S,2,0) -> 123196 | F60: 正元转02 | G60: =VLOOKUP($F60,全部可转债!$A:$S,7,0) -> 115 | H60: =G60/D60-1 -> -0.084176157 | I60: =VLOOKUP($F60,全部可转债!$A:$S,19,0) -> -1.35 | J60: =VLOOKUP($F60,全部可转债!$A:$S,17,0) -> 0.45 | K60: =VLOOKUP($F60,全部可转债!$A:$S,5,0) -> 21.91 | L60: =VLOOKUP($F60,全部可转债!$A:$S,6,0) -> 28.483 | M60: =VLOOKUP($F60,全部可转债!$A:$S,18,0) -> 13.9 | N60: =VLOOKUP($F60,全部可转债!$A:$S,8,0) -> 18.623 | O60: =VLOOKUP($F60,全部可转债!$A:$S,15,0) -> 20290418 | P60: =VLOOKUP($F60,全部可转债!$A:$S,14,0) -> 3.501 | Q60: 811 | R60: =VLOOKUP($F60,全部可转债!$A:$S,11,0) -> 未满足
A61: =VLOOKUP($F61,全部可转债!$A:$S,9,0) -> 167.08 | B61: =L61*100/M61-100 -> 185.41558 | C61: 0 | D61: =VLOOKUP(F61,全部可转债!$A:$S,16,0) -> 121.65 | E61: =VLOOKUP($F61,全部可转债!$A:$S,2,0) -> 127098 | F61: 欧晶转债 | G61: =VLOOKUP($F61,全部可转债!$A:$S,7,0) -> 112 | H61: =G61/D61-1 -> -0.079325935 | I61: =VLOOKUP($F61,全部可转债!$A:$S,19,0) -> 0.53 | J61: =VLOOKUP($F61,全部可转债!$A:$S,17,0) -> 0.83 | K61: =VLOOKUP($F61,全部可转债!$A:$S,5,0) -> 42 | L61: =VLOOKUP($F61,全部可转债!$A:$S,6,0) -> 54.6 | M61: =VLOOKUP($F61,全部可转债!$A:$S,18,0) -> 19.13 | N61: =VLOOKUP($F61,全部可转债!$A:$S,8,0) -> 35.7 | O61: =VLOOKUP($F61,全部可转债!$A:$S,15,0) -> 20291124 | P61: =VLOOKUP($F61,全部可转债!$A:$S,14,0) -> 4.693 | Q61: 601 | R61: =VLOOKUP($F61,全部可转债!$A:$S,11,0) -> 未满足
A62: =VLOOKUP($F62,全部可转债!$A:$S,9,0) -> 39.64 | B62: =L62*100/M62-100 -> 30.555217 | C62: 0 | D62: =VLOOKUP(F62,全部可转债!$A:$S,16,0) -> 139.05 | E62: =VLOOKUP($F62,全部可转债!$A:$S,2,0) -> 123222 | F62: 博俊转债 | G62: =VLOOKUP($F62,全部可转债!$A:$S,7,0) -> 115 | H62: =G62/D62-1 -> -0.17295937 | I62: =VLOOKUP($F62,全部可转债!$A:$S,19,0) -> 3.6 | J62: =VLOOKUP($F62,全部可转债!$A:$S,17,0) -> 1.24 | K62: =VLOOKUP($F62,全部可转债!$A:$S,5,0) -> 16.46 | L62: =VLOOKUP($F62,全部可转债!$A:$S,6,0) -> 21.398 | M62: =VLOOKUP($F62,全部可转债!$A:$S,18,0) -> 16.39 | N62: =VLOOKUP($F62,全部可转债!$A:$S,8,0) -> 13.991 | O62: =VLOOKUP($F62,全部可转债!$A:$S,15,0) -> 20290908 | P62: =VLOOKUP($F62,全部可转债!$A:$S,14,0) -> 2.438 | R62: =VLOOKUP($F62,全部可转债!$A:$S,11,0) -> 未满足
A63: =VLOOKUP($F63,全部可转债!$A:$S,9,0) -> 35.15 | B63: =L63*100/M63-100 -> 35.991984 | C63: 0 | D63: =VLOOKUP(F63,全部可转债!$A:$S,16,0) -> 129.19 | E63: =VLOOKUP($F63,全部可转债!$A:$S,2,0) -> 127082 | F63: 亚科转债 | G63: =VLOOKUP($F63,全部可转债!$A:$S,7,0) -> 112 | H63: =G63/D63-1 -> -0.13305983 | I63: =VLOOKUP($F63,全部可转债!$A:$S,19,0) -> 0.4 | J63: =VLOOKUP($F63,全部可转债!$A:$S,17,0) -> 0.27 | K63: =VLOOKUP($F63,全部可转债!$A:$S,5,0) -> 5.22 | L63: =VLOOKUP($F63,全部可转债!$A:$S,6,0) -> 6.786 | M63: =VLOOKUP($F63,全部可转债!$A:$S,18,0) -> 4.99 | N63: =VLOOKUP($F63,全部可转债!$A:$S,8,0) -> 4.698 | O63: =VLOOKUP($F63,全部可转债!$A:$S,15,0) -> 20290309 | P63: =VLOOKUP($F63,全部可转债!$A:$S,14,0) -> 11.585 | R63: =VLOOKUP($F63,全部可转债!$A:$S,11,0) -> 未满足
A64: =VLOOKUP($F64,全部可转债!$A:$S,9,0) -> 73.14 | B64: =L64*100/M64-100 -> 73.007519 | C64: 0 | D64: =VLOOKUP(F64,全部可转债!$A:$S,16,0) -> 130.1 | E64: =VLOOKUP($F64,全部可转债!$A:$S,2,0) -> 123220 | F64: 易瑞转债 | G64: =VLOOKUP($F64,全部可转债!$A:$S,7,0) -> 115 | H64: =G64/D64-1 -> -0.11606457 | I64: =VLOOKUP($F64,全部可转债!$A:$S,19,0) -> 1.06 | J64: =VLOOKUP($F64,全部可转债!$A:$S,17,0) -> 0.47 | K64: =VLOOKUP($F64,全部可转债!$A:$S,5,0) -> 8.85 | L64: =VLOOKUP($F64,全部可转债!$A:$S,6,0) -> 11.505 | M64: =VLOOKUP($F64,全部可转债!$A:$S,18,0) -> 6.65 | N64: =VLOOKUP($F64,全部可转债!$A:$S,8,0) -> 7.522 | O64: =VLOOKUP($F64,全部可转债!$A:$S,15,0) -> 20290818 | P64: =VLOOKUP($F64,全部可转债!$A:$S,14,0) -> 2.905 | Q64: 904 | R64: =VLOOKUP($F64,全部可转债!$A:$S,11,0) -> 未满足
A65: =VLOOKUP($F65,全部可转债!$A:$S,9,0) -> 41.91 | B65: =L65*100/M65-100 -> 25.762355 | C65: 0 | D65: =VLOOKUP(F65,全部可转债!$A:$S,16,0) -> 146.69 | E65: =VLOOKUP($F65,全部可转债!$A:$S,2,0) -> 123211 | F65: 阳谷转债 | G65: =VLOOKUP($F65,全部可转债!$A:$S,7,0) -> 115 | H65: =G65/D65-1 -> -0.21603381 | I65: =VLOOKUP($F65,全部可转债!$A:$S,19,0) -> 1.17 | J65: =VLOOKUP($F65,全部可转债!$A:$S,17,0) -> 0.07 | K65: =VLOOKUP($F65,全部可转债!$A:$S,5,0) -> 9.2 | L65: =VLOOKUP($F65,全部可转债!$A:$S,6,0) -> 11.96 | M65: =VLOOKUP($F65,全部可转债!$A:$S,18,0) -> 9.51 | N65: =VLOOKUP($F65,全部可转债!$A:$S,8,0) -> 7.82 | O65: =VLOOKUP($F65,全部可转债!$A:$S,15,0) -> 20290727 | P65: =VLOOKUP($F65,全部可转债!$A:$S,14,0) -> 3.07 | R65: =VLOOKUP($F65,全部可转债!$A:$S,11,0) -> 未满足
A66: =VLOOKUP($F66,全部可转债!$A:$S,9,0) -> 33.48 | B66: =L66*100/M66-100 -> 10.285853 | C66: 0 | D66: =VLOOKUP(F66,全部可转债!$A:$S,16,0) -> 157.34 | E66: =VLOOKUP($F66,全部可转债!$A:$S,2,0) -> 123209 | F66: 聚隆转债 | G66: =VLOOKUP($F66,全部可转债!$A:$S,7,0) -> 113 | H66: =G66/D66-1 -> -0.28181009 | I66: =VLOOKUP($F66,全部可转债!$A:$S,19,0) -> -1.39 | J66: =VLOOKUP($F66,全部可转债!$A:$S,17,0) -> -0.52 | K66: =VLOOKUP($F66,全部可转债!$A:$S,5,0) -> 17.51 | L66: =VLOOKUP($F66,全部可转债!$A:$S,6,0) -> 22.763 | M66: =VLOOKUP($F66,全部可转债!$A:$S,18,0) -> 20.64 | N66: =VLOOKUP($F66,全部可转债!$A:$S,8,0) -> 14.884 | O66: =VLOOKUP($F66,全部可转债!$A:$S,15,0) -> 20290726 | P66: =VLOOKUP($F66,全部可转债!$A:$S,14,0) -> 1.672 | R66: =VLOOKUP($F66,全部可转债!$A:$S,11,0) -> 未满足
A67: =VLOOKUP($F67,全部可转债!$A:$S,9,0) -> #N/A | B67: =L67*100/M67-100 -> #N/A | C67: -1 | D67: =VLOOKUP(F67,全部可转债!$A:$S,16,0) -> #N/A | E67: =VLOOKUP($F67,全部可转债!$A:$S,2,0) -> #N/A | F67: 星球转债 | G67: =VLOOKUP($F67,全部可转债!$A:$S,7,0) -> #N/A | H67: =G67/D67-1 -> #N/A | I67: =VLOOKUP($F67,全部可转债!$A:$S,19,0) -> #N/A | J67: =VLOOKUP($F67,全部可转债!$A:$S,17,0) -> #N/A | K67: =VLOOKUP($F67,全部可转债!$A:$S,5,0) -> #N/A | L67: =VLOOKUP($F67,全部可转债!$A:$S,6,0) -> #N/A | M67: =VLOOKUP($F67,全部可转债!$A:$S,18,0) -> #N/A | N67: =VLOOKUP($F67,全部可转债!$A:$S,8,0) -> #N/A | O67: =VLOOKUP($F67,全部可转债!$A:$S,15,0) -> #N/A | P67: =VLOOKUP($F67,全部可转债!$A:$S,14,0) -> #N/A | R67: =VLOOKUP($F67,全部可转债!$A:$S,11,0) -> #N/A
A68: =VLOOKUP($F68,全部可转债!$A:$S,9,0) -> 10.55 | B68: =L68*100/M68-100 -> 9.6243523 | C68: 0 | D68: =VLOOKUP(F68,全部可转债!$A:$S,16,0) -> 131.1 | E68: =VLOOKUP($F68,全部可转债!$A:$S,2,0) -> 113631 | F68: 皖天转债 | G68: =VLOOKUP($F68,全部可转债!$A:$S,7,0) -> 110 | H68: =G68/D68-1 -> -0.16094584 | I68: =VLOOKUP($F68,全部可转债!$A:$S,19,0) -> 0.65 | J68: =VLOOKUP($F68,全部可转债!$A:$S,17,0) -> 0.86 | K68: =VLOOKUP($F68,全部可转债!$A:$S,5,0) -> 6.51 | L68: =VLOOKUP($F68,全部可转债!$A:$S,6,0) -> 8.463 | M68: =VLOOKUP($F68,全部可转债!$A:$S,18,0) -> 7.72 | N68: =VLOOKUP($F68,全部可转债!$A:$S,8,0) -> 5.208 | O68: =VLOOKUP($F68,全部可转债!$A:$S,15,0) -> 20271108 | P68: =VLOOKUP($F68,全部可转债!$A:$S,14,0) -> 5.958 | R68: =VLOOKUP($F68,全部可转债!$A:$S,11,0) -> 未满足
A69: =VLOOKUP($F69,全部可转债!$A:$S,9,0) -> 15.55 | B69: =L69*100/M69-100 -> 10.023641 | C69: 4 | D69: =VLOOKUP(F69,全部可转债!$A:$S,16,0) -> 136.53 | E69: =VLOOKUP($F69,全部可转债!$A:$S,2,0) -> 127110 | F69: 广核转债 | G69: =VLOOKUP($F69,全部可转债!$A:$S,7,0) -> 106 | H69: =G69/D69-1 -> -0.22361386 | I69: =VLOOKUP($F69,全部可转债!$A:$S,19,0) -> 0.48 | J69: =VLOOKUP($F69,全部可转债!$A:$S,17,0) -> 0.59 | K69: =VLOOKUP($F69,全部可转债!$A:$S,5,0) -> 3.58 | L69: =VLOOKUP($F69,全部可转债!$A:$S,6,0) -> 4.654 | M69: =VLOOKUP($F69,全部可转债!$A:$S,18,0) -> 4.23 | N69: =VLOOKUP($F69,全部可转债!$A:$S,8,0) -> 3.043 | O69: =VLOOKUP($F69,全部可转债!$A:$S,15,0) -> 20310709 | P69: =VLOOKUP($F69,全部可转债!$A:$S,14,0) -> 48.992 | R69: =VLOOKUP($F69,全部可转债!$A:$S,11,0) -> 未满足
A70: =VLOOKUP($F70,全部可转债!$A:$S,9,0) -> 6.61 | B70: =L70*100/M70-100 -> -5.7971014 | C70: 15 | D70: =VLOOKUP(F70,全部可转债!$A:$S,16,0) -> 147.12 | E70: =VLOOKUP($F70,全部可转债!$A:$S,2,0) -> 113686 | F70: 泰瑞转债 | G70: =VLOOKUP($F70,全部可转债!$A:$S,7,0) -> 115 | H70: =G70/D70-1 -> -0.21832518 | I70: =VLOOKUP($F70,全部可转债!$A:$S,19,0) -> -2.82 | J70: =VLOOKUP($F70,全部可转债!$A:$S,17,0) -> -4.13 | K70: =VLOOKUP($F70,全部可转债!$A:$S,5,0) -> 8 | L70: =VLOOKUP($F70,全部可转债!$A:$S,6,0) -> 10.4 | M70: =VLOOKUP($F70,全部可转债!$A:$S,18,0) -> 11.04 | N70: =VLOOKUP($F70,全部可转债!$A:$S,8,0) -> 6.8 | O70: =VLOOKUP($F70,全部可转债!$A:$S,15,0) -> 20300702 | P70: =VLOOKUP($F70,全部可转债!$A:$S,14,0) -> 3.363 | R70: =VLOOKUP($F70,全部可转债!$A:$S,11,0) -> 计数中
A71: =VLOOKUP($F71,全部可转债!$A:$S,9,0) -> 32.54 | B71: =L71*100/M71-100 -> 42.657503 | C71: 3 | D71: =VLOOKUP(F71,全部可转债!$A:$S,16,0) -> 120.78 | E71: =VLOOKUP($F71,全部可转债!$A:$S,2,0) -> 127034 | F71: 绿茵转债 | G71: =VLOOKUP($F71,全部可转债!$A:$S,7,0) -> 113 | H71: =G71/D71-1 -> -0.064414638 | I71: =VLOOKUP($F71,全部可转债!$A:$S,19,0) -> -1.24 | J71: =VLOOKUP($F71,全部可转债!$A:$S,17,0) -> 0.23 | K71: =VLOOKUP($F71,全部可转债!$A:$S,5,0) -> 9.58 | L71: =VLOOKUP($F71,全部可转债!$A:$S,6,0) -> 12.454 | M71: =VLOOKUP($F71,全部可转债!$A:$S,18,0) -> 8.73 | N71: =VLOOKUP($F71,全部可转债!$A:$S,8,0) -> 8.143 | O71: =VLOOKUP($F71,全部可转债!$A:$S,15,0) -> 20270430 | P71: =VLOOKUP($F71,全部可转债!$A:$S,14,0) -> 4.279 | R71: =VLOOKUP($F71,全部可转债!$A:$S,11,0) -> 未满足
A72: =VLOOKUP($F72,全部可转债!$A:$S,9,0) -> 35.82 | B72: =L72*100/M72-100 -> 36.823529 | C72: 1 | D72: =VLOOKUP(F72,全部可转债!$A:$S,16,0) -> 129.05 | E72: =VLOOKUP($F72,全部可转债!$A:$S,2,0) -> 123183 | F72: 海顺转债 | G72: =VLOOKUP($F72,全部可转债!$A:$S,7,0) -> 115 | H72: =G72/D72-1 -> -0.10887253 | I72: =VLOOKUP($F72,全部可转债!$A:$S,19,0) -> 1.38 | J72: =VLOOKUP($F72,全部可转债!$A:$S,17,0) -> -0.65 | K72: =VLOOKUP($F72,全部可转债!$A:$S,5,0) -> 11.63 | L72: =VLOOKUP($F72,全部可转债!$A:$S,6,0) -> 15.119 | M72: =VLOOKUP($F72,全部可转债!$A:$S,18,0) -> 11.05 | N72: =VLOOKUP($F72,全部可转债!$A:$S,8,0) -> 9.886 | O72: =VLOOKUP($F72,全部可转债!$A:$S,15,0) -> 20290323 | P72: =VLOOKUP($F72,全部可转债!$A:$S,14,0) -> 6.329 | R72: =VLOOKUP($F72,全部可转债!$A:$S,11,0) -> 未满足
A73: =VLOOKUP($F73,全部可转债!$A:$S,9,0) -> 44.43 | B73: =L73*100/M73-100 -> 22.972973 | C73: 12 | D73: =VLOOKUP(F73,全部可转债!$A:$S,16,0) -> 152.68 | E73: =VLOOKUP($F73,全部可转债!$A:$S,2,0) -> 113646 | F73: 永吉转债 | G73: =VLOOKUP($F73,全部可转债!$A:$S,7,0) -> 108.3 | H73: =G73/D73-1 -> -0.2906733 | I73: =VLOOKUP($F73,全部可转债!$A:$S,19,0) -> -1.85 | J73: =VLOOKUP($F73,全部可转债!$A:$S,17,0) -> -1.19 | K73: =VLOOKUP($F73,全部可转债!$A:$S,5,0) -> 8.05 | L73: =VLOOKUP($F73,全部可转债!$A:$S,6,0) -> 10.465 | M73: =VLOOKUP($F73,全部可转债!$A:$S,18,0) -> 8.51 | N73: =VLOOKUP($F73,全部可转债!$A:$S,8,0) -> 6.843 | O73: =VLOOKUP($F73,全部可转债!$A:$S,15,0) -> 20280414 | P73: =VLOOKUP($F73,全部可转债!$A:$S,14,0) -> 1.372 | R73: =VLOOKUP($F73,全部可转债!$A:$S,11,0) -> 未满足
A74: =VLOOKUP($F74,全部可转债!$A:$S,9,0) -> 7.75 | B74: =L74*100/M74-100 -> 2.6315789 | C74: 4 | D74: =VLOOKUP(F74,全部可转债!$A:$S,16,0) -> 136.48 | E74: =VLOOKUP($F74,全部可转债!$A:$S,2,0) -> 113681 | F74: 镇洋转债 | G74: =VLOOKUP($F74,全部可转债!$A:$S,7,0) -> 115 | H74: =G74/D74-1 -> -0.1573857 | I74: =VLOOKUP($F74,全部可转债!$A:$S,19,0) -> 0.87 | J74: =VLOOKUP($F74,全部可转债!$A:$S,17,0) -> 0.39 | K74: =VLOOKUP($F74,全部可转债!$A:$S,5,0) -> 10.95 | L74: =VLOOKUP($F74,全部可转债!$A:$S,6,0) -> 14.235 | M74: =VLOOKUP($F74,全部可转债!$A:$S,18,0) -> 13.87 | N74: =VLOOKUP($F74,全部可转债!$A:$S,8,0) -> 9.307 | O74: =VLOOKUP($F74,全部可转债!$A:$S,15,0) -> 20291229 | P74: =VLOOKUP($F74,全部可转债!$A:$S,14,0) -> 5.476 | R74: =VLOOKUP($F74,全部可转债!$A:$S,11,0) -> 未满足
A75: =VLOOKUP($F75,全部可转债!$A:$S,9,0) -> 13.62 | B75: =L75*100/M75-100 -> 16.48 | C75: 0 | D75: =VLOOKUP(F75,全部可转债!$A:$S,16,0) -> 126.81 | E75: =VLOOKUP($F75,全部可转债!$A:$S,2,0) -> 113058 | F75: 友发转债 | G75: =VLOOKUP($F75,全部可转债!$A:$S,7,0) -> 112 | H75: =G75/D75-1 -> -0.1167889 | I75: =VLOOKUP($F75,全部可转债!$A:$S,19,0) -> 0.6 | J75: =VLOOKUP($F75,全部可转债!$A:$S,17,0) -> 0.72 | K75: =VLOOKUP($F75,全部可转债!$A:$S,5,0) -> 4.48 | L75: =VLOOKUP($F75,全部可转债!$A:$S,6,0) -> 5.824 | M75: =VLOOKUP($F75,全部可转债!$A:$S,18,0) -> 5 | N75: =VLOOKUP($F75,全部可转债!$A:$S,8,0) -> 3.808 | O75: =VLOOKUP($F75,全部可转债!$A:$S,15,0) -> 20280330 | P75: =VLOOKUP($F75,全部可转债!$A:$S,14,0) -> 18.638 | R75: =VLOOKUP($F75,全部可转债!$A:$S,11,0) -> 未满足
A76: =VLOOKUP($F76,全部可转债!$A:$S,9,0) -> #N/A | B76: =L76*100/M76-100 -> #N/A | C76: -1 | D76: =VLOOKUP(F76,全部可转债!$A:$S,16,0) -> #N/A | E76: =VLOOKUP($F76,全部可转债!$A:$S,2,0) -> #N/A | F76: 科利转债 | G76: =VLOOKUP($F76,全部可转债!$A:$S,7,0) -> #N/A | H76: =G76/D76-1 -> #N/A | I76: =VLOOKUP($F76,全部可转债!$A:$S,19,0) -> #N/A | J76: =VLOOKUP($F76,全部可转债!$A:$S,17,0) -> #N/A | K76: =VLOOKUP($F76,全部可转债!$A:$S,5,0) -> #N/A | L76: =VLOOKUP($F76,全部可转债!$A:$S,6,0) -> #N/A | M76: =VLOOKUP($F76,全部可转债!$A:$S,18,0) -> #N/A | N76: =VLOOKUP($F76,全部可转债!$A:$S,8,0) -> #N/A | O76: =VLOOKUP($F76,全部可转债!$A:$S,15,0) -> #N/A | P76: =VLOOKUP($F76,全部可转债!$A:$S,14,0) -> #N/A | R76: =VLOOKUP($F76,全部可转债!$A:$S,11,0) -> #N/A
A77: =VLOOKUP($F77,全部可转债!$A:$S,9,0) -> 109.3 | B77: =L77*100/M77-100 -> 126.96838 | C77: 0 | D77: =VLOOKUP(F77,全部可转债!$A:$S,16,0) -> 119.88 | E77: =VLOOKUP($F77,全部可转债!$A:$S,2,0) -> 113638 | F77: 台21转债 | G77: =VLOOKUP($F77,全部可转债!$A:$S,7,0) -> 112 | H77: =G77/D77-1 -> -0.065732399 | I77: =VLOOKUP($F77,全部可转债!$A:$S,19,0) -> 1.44 | J77: =VLOOKUP($F77,全部可转债!$A:$S,17,0) -> 0.52 | K77: =VLOOKUP($F77,全部可转债!$A:$S,5,0) -> 16.01 | L77: =VLOOKUP($F77,全部可转债!$A:$S,6,0) -> 20.813 | M77: =VLOOKUP($F77,全部可转债!$A:$S,18,0) -> 9.17 | N77: =VLOOKUP($F77,全部可转债!$A:$S,8,0) -> 13.609 | O77: =VLOOKUP($F77,全部可转债!$A:$S,15,0) -> 20271229 | P77: =VLOOKUP($F77,全部可转债!$A:$S,14,0) -> 5.997 | Q77: 820 | R77: =VLOOKUP($F77,全部可转债!$A:$S,11,0) -> 未满足
A78: =VLOOKUP($F78,全部可转债!$A:$S,9,0) -> 30.75 | B78: =L78*100/M78-100 -> 53.508772 | C78: 0 | D78: =VLOOKUP(F78,全部可转债!$A:$S,16,0) -> 110.73 | E78: =VLOOKUP($F78,全部可转债!$A:$S,2,0) -> 128142 | F78: 新乳转债 | G78: =VLOOKUP($F78,全部可转债!$A:$S,7,0) -> 110 | H78: =G78/D78-1 -> -0.0065926127 | I78: =VLOOKUP($F78,全部可转债!$A:$S,19,0) -> 4 | J78: =VLOOKUP($F78,全部可转债!$A:$S,17,0) -> 0.7 | K78: =VLOOKUP($F78,全部可转债!$A:$S,5,0) -> 17.5 | L78: =VLOOKUP($F78,全部可转债!$A:$S,6,0) -> 22.75 | M78: =VLOOKUP($F78,全部可转债!$A:$S,18,0) -> 14.82 | N78: =VLOOKUP($F78,全部可转债!$A:$S,8,0) -> 14 | O78: =VLOOKUP($F78,全部可转债!$A:$S,15,0) -> 20261218 | P78: =VLOOKUP($F78,全部可转债!$A:$S,14,0) -> 7.178 | R78: =VLOOKUP($F78,全部可转债!$A:$S,11,0) -> 未满足
A79: =VLOOKUP($F79,全部可转债!$A:$S,9,0) -> 23.68 | B79: =L79*100/M79-100 -> 30.744986 | C79: 1 | D79: =VLOOKUP(F79,全部可转债!$A:$S,16,0) -> 122.98 | E79: =VLOOKUP($F79,全部可转债!$A:$S,2,0) -> 123104 | F79: 卫宁转债 | G79: =VLOOKUP($F79,全部可转债!$A:$S,7,0) -> 120 | H79: =G79/D79-1 -> -0.024231582 | I79: =VLOOKUP($F79,全部可转债!$A:$S,19,0) -> 0.29 | J79: =VLOOKUP($F79,全部可转债!$A:$S,17,0) -> 0.4 | K79: =VLOOKUP($F79,全部可转债!$A:$S,5,0) -> 7.02 | L79: =VLOOKUP($F79,全部可转债!$A:$S,6,0) -> 9.126 | M79: =VLOOKUP($F79,全部可转债!$A:$S,18,0) -> 6.98 | N79: =VLOOKUP($F79,全部可转债!$A:$S,8,0) -> 5.967 | O79: =VLOOKUP($F79,全部可转债!$A:$S,15,0) -> 20270316 | P79: =VLOOKUP($F79,全部可转债!$A:$S,14,0) -> 9.699 | Q79: 14 | R79: =VLOOKUP($F79,全部可转债!$A:$S,11,0) -> 未满足

Sheet 转债测算公式
D3: 转股零股模拟
D4: 成本 | E4: 数量 | F4: 转债价格 | G4: 转股价 | H4: 余额 | J4: 现金退 | L4: 股数 | M4: 股价 | P4: 可得 | Q4: 利润 | R4: 溢价率 | S4: 收益率
D5: =E5*F5 -> 8400 | E5: 80 | F5: 105 | G5: 90 | H5: =MOD(100*E5,G5) -> 80 | I5: =H5*0.02 -> 1.6 | J5: =H5+I5 -> 81.6 | L5: =INT(100*E5/G5) -> 88 | M5: 95 | P5: =M5*L5+J5 -> 8441.6 | Q5: =P5-F5*E5 -> 41.6 | R5: =F5/(100/G5*M5)-1 -> -0.0052631579 | S5: =P5/D5-1 -> 0.004952381
D7: 溢价率变化模拟
D8: 转债价格 | E8: 转股价 | F8: 股价 | G8: 分红 | H8: 原溢价率 | I8: 新溢价率
C9: 南京银行 | D9: 137.111 | E9: 8.22 | F9: 11.29 | G9: 0.21176 | H9: =D9/(100/E9*F9)-1 -> -0.0017250487 | I9: =D9/(100/(E9-G9)*(F9-G9))-1 -> -0.0088517719 | L9: 转股价<股价时，分红后，转股价值提升，溢价率降低
C10: 齐鲁转债 | D10: 129.914 | E10: 5.14 | F10: 6.65 | G10: 0.139 | H10: =D10/(100/E10*F10)-1 -> 0.0041473083 | I10: =D10/(100/(E10-G10)*(F10-G10))-1 -> -0.0021503394
D12: 增发股票后转股价调整公式，增发股票越多，增发价越低，转股价值提升幅度越大
D13: 调整前转股价 | E13: 增发新股价 | F13: 原股本 | G13: 增发数量 | H13: 增发率 | I13: 新转股价 | J13: 新强赎价 | L13: 转股价变化率 | M13: 股价 | P13: 转债价格 | Q13: 新溢价率
C14: 晨丰转债 | D14: 12.77 | E14: =8.69-0.008 -> 8.682 | F14: 169005534 | G14: 49484821 | H14: =G14/F14 -> 0.2928 | I14: =(D14+E14*H14)/(1+H14) -> 11.844129 | J14: =I14*1.3 -> 15.397367 | L14: =I14/D14 -> 0.92749637 | M14: 13.51 | P14: 126 | Q14: =P14/(100/I14*M14)-1 -> 0.10463377 | S14: 跟中辰的基本面差不多
C15: 永东转2 | D15: 8.49 | M15: 6.81
C16: 浦发转债 | D16: 12.92 | I16: =D16-0.41 -> 12.51 | L16: =I16/D16 -> 0.96826625 | M16: =14.58-0.41 -> 14.17 | P16: 114.5 | Q16: =P16/(100/I16*M16)-1 -> 0.010864502

Sheet 收益日记
A1: 0.6 | B1: 日期 | C1: 可转债超额 | D1: 可转债等权指数 | E1: 可转债轮动组合 | F1: 可转债实盘 | G1: 对应正股涨幅 | H1: 转债正股比值 | I1: 模拟正股delta40 | J1: ST实盘 | K1: ST板块 | L1: ST超额 | M1: ST等权 | N1: ST星等权 | O1: ST重整 | P1: 盈亏 | Q1: 累计盈亏 | R1: 封基收益 | S1: 涨超6数量 | T1: 小狮子实盘 | U1: 微盘股 | V1: 微盘股轮出 | W1: 微盘股轮入 | X1: ST涨 超5% | Y1: ST跌 超5% | Z1: 波动率 | AA1: 创新低 | AB1: 上涨板块
B2: 202508汇总 | C2: =SUM(C3:C23) -> -0.052 | D2: =SUM(D3:D23) -> 0.052 | F2: =SUM(F3:F23) -> 0 | J2: =SUM(J3:J24) -> 0.0843 | K2: =SUM(K3:K24) -> 0.0033 | L2: =SUM(L3:L24) -> 0.081
B3: 45870 | C3: =F3-D3 -> -0.0037 | D3: 0.0037 | F3: 0
B4: 45873 | C4: =F4-D4 -> -0.0114 | D4: 0.0114 | F4: 0
B5: 45874 | C5: =F5-D5 -> -0.0082 | D5: 0.0082
B6: 45875 | C6: =F6-D6 -> -0.0076 | D6: 0.0076
B7: 45876 | C7: =F7-D7 -> 0.0014 | D7: -0.0014
B8: 45877 | C8: =F8-D8 -> -0.0014 | D8: 0.0014
B9: 45880 | C9: =F9-D9 -> -0.0109 | D9: 0.0109
B10: 45881 | C10: =F10-D10 -> 0.0035 | D10: -0.0035
B11: 45882 | C11: =F11-D11 -> -0.0097 | D11: 0.0097
B12: 45883 | C12: =F12-D12 -> 0.0067 | D12: -0.0067
B13: 45884 | C13: =F13-D13 -> -0.0131 | D13: 0.0131
B14: 45887 | C14: =F14-D14 -> -0.0119 | D14: 0.0119
B15: 45888 | C15: =F15-D15 -> -0.0037 | D15: 0.0037
B16: 45889 | C16: =F16-D16 -> -0.0034 | D16: 0.0034
... B23: 45898 | C23: =F23-D23 -> 0.0069 | D23: -0.0069
B24: 202509汇总 | C24: =SUM(C25:C46) -> 0.00657 | D24: =SUM(D25:D46) -> 0.0247 | E24: =SUM(E25:E46) -> 0.03127 | F24: =SUM(F25:F46) -> 0.03127 | G24: =SUM(G25:G46) -> 0.00727 | H24: =F24/G24 -> 4.301238 | I24: =SUM(I25:I46) -> 0.004362 | J24: =SUM(J25:J46) -> 0.0843 | K24: =SUM(K25:K46) -> 0.0033 | L24: =SUM(L25:L46) -> 0.081
B25: 20250901 | C25: =F25-D25 -> -0.0008 | D25: -0.0035 | E25: =F25 -> -0.0043 | F25: -0.0043 | G25: 0.0055 | H25: =F25/G25 -> -0.78181818 | I25: =G25*$A$1 -> 0.0033 | J25: 0.014 | K25: 0.0084 | L25: =J25-K25 -> 0.0056
B26: 20250902 | C26: =F26-D26 -> 0.0024 | D26: -0.0127 | E26: =F26 -> -0.0103 | F26: -0.0103 | G26: -0.0154 | H26: =F26/G26 -> 0.66883117 | I26: =G26*$A$1 -> -0.00924 | J26: -0.0015 | K26: -0.0072 | L26: =J26-K26 -> 0.0057
B27: 20250903 | C27: =F27-D27 -> -0.0021 | D27: 0.0011 | E27: =F27 -> -0.001 | F27: -0.001 | G27: -0.0269 | H27: =F27/G27 -> 0.037174721 | I27: =G27*$A$1 -> -0.01614 | J27: 0.0057 | K27: -0.0069 | L27: =J27-K27 -> 0.0126
B28: 20250904 | C28: =F28-D28 -> 0.0024 | D28: -0.0057 | E28: =F28 -> -0.0033 | F28: -0.0033 | G28: -0.0113 | H28: =F28/G28 -> 0.2920354 | I28: =G28*$A$1 -> -0.00678 | J28: -0.0031 | K28: -0.0099 | L28: =J28-K28 -> 0.0068
B29: 20250905 | C29: =F29-D29 -> 0.0039 | D29: 0.0264 | E29: =F29 -> 0.0303 | F29: 0.0303 | G29: 0.0346 | H29: =F29/G29 -> 0.87572254 | I29: =G29*$A$1 -> 0.02076 | J29: 0.0108 | K29: 0.0135 | L29: =J29-K29 -> -0.0027
B30: 20250908 | C30: =F30-D30 -> 0.0026 | D30: 0.009 | E30: =F30 -> 0.0116 | F30: 0.0116 | G30: 0.022 | H30: =F30/G30 -> 0.52727273 | I30: =G30*$A$1 -> 0.0132 | J30: 0.0297 | K30: 0.015 | L30: =J30-K30 -> 0.0147
B31: 20250909 | C31: =F31-D31 -> 0.0041 | D31: -0.0124 | E31: =F31 -> -0.0083 | F31: -0.0083 | G31: -0.0047 | H31: =F31/G31 -> 1.7659574 | I31: =G31*$A$1 -> -0.00282 | J31: 0.0184 | K31: 0.0048 | L31: =J31-K31 -> 0.0136
B32: 20250910 | C32: =F32-D32 -> -0.0008 | D32: -0.0077 | E32: =F32 -> -0.0085 | F32: -0.0085 | G32: 0.0037 | H32: =F32/G32 -> -2.2972973 | I32: =G32*$A$1 -> 0.00222 | J32: 0.011 | K32: 0.0111 | L32: =J32-K32 -> -0.0001
B33: 20250911 | C33: =F33-D33 -> -0.0029 | D33: 0.0156 | E33: =F33 -> 0.0127 | F33: 0.0127 | G33: 0.0132 | H33: =F33/G33 -> 0.96212121 | I33: =G33*$A$1 -> 0.00792 | J33: -0.0028 | K33: 0 | L33: =J33-K33 -> -0.0028
B34: 20250912 | C34: =F34-D34 -> -0.0007 | D34: 0.0032 | E34: =F34 -> 0.0025 | F34: 0.0025 | G34: 0.0029 | H34: =F34/G34 -> 0.86206897 | I34: =G34*$A$1 -> 0.00174 | J34: 0.0038 | K34: 0.0021 | L34: =J34-K34 -> 0.0017
B35: 20250915 | C35: =F35-D35 -> -0.0009 | D35: -0.0082 | E35: =F35 -> -0.0091 | F35: -0.0091 | G35: -0.0115 | H35: =F35/G35 -> 0.79130435 | I35: =G35*$A$1 -> -0.0069 | J35: -0.0009 | K35: -0.0059 | L35: =J35-K35 -> 0.005
B36: 20250916 | C36: =F36-D36 -> -0.003 | D36: 0.0018 | E36: =F36 -> -0.0012 | F36: -0.0012 | G36: 0.0078 | H36: =F36/G36 -> -0.15384615 | I36: =G36*$A$1 -> 0.00468 | J36: 0.0146 | K36: 0.0033 | L36: =J36-K36 -> 0.0113
... B46: 20250930 | C46: =F46-D46 -> -0.0005 | D46: 0.0065 | E46: =F46 -> 0.006 | F46: 0.006 | G46: 0.005 | H46: =F46/G46 -> 1.2 | I46: =G46*$A$1 -> 0.003 | J46: 0.0045 | K46: 0.0046 | L46: =J46-K46 -> -0.0001
B47: 202510汇总 | C47: =SUM(C48:C64) -> -0.01085 | D47: =SUM(D48:D64) -> -0.0033 | E47: =SUM(E48:E64) -> -0.00572 | F47: =SUM(F48:F64) -> -0.01415 | G47: =SUM(G48:G64) -> -0.00209 | H47: =F47/G47 -> 6.7703349 | I47: =SUM(I48:I64) -> -0.001254 | J47: =SUM(J48:J64) -> 0.0405 | K47: =SUM(K48:K64) -> 0.0551 | L47: =SUM(L48:L64) -> -0.0146 | R47: 0.014
B48: 20251009 | C48: =F48-D48 -> -0.0056 | D48: 0.0053 | E48: =F48 -> -0.0003 | F48: -0.0003 | G48: 0.0009 | H48: =E48/G48 -> -0.33333333 | I48: =G48*$A$1 -> 0.00054 | J48: -0.0097 | K48: -0.0096 | L48: =J48-K48 -> -0.0001
B49: 20251010 | C49: =F49-D49 -> 0.005 | D49: -0.005 | E49: =F49 -> 0 | F49: 0 | G49: -0.00153 | H49: =E49/G49 -> 0 | I49: =G49*$A$1 -> -0.000918 | J49: 0.0055 | K49: 0.0022 | L49: =J49-K49 -> 0.0033
B50: 20251013 | C50: =F50-D50 -> 0.0032 | D50: -0.0039 | E50: =F50 -> -0.0007 | F50: -0.0007 | G50: -0.00154 | H50: =E50/G50 -> 0.45454545 | I50: =G50*$A$1 -> -0.000924 | J50: -0.0086 | K50: -0.0022 | L50: =J50-K50 -> -0.0064
B51: 20251014 | C51: =F51-D51 -> 0.0052 | D51: -0.0127 | E51: =F51 -> -0.0075 | F51: -0.0075 | G51: -0.01345 | H51: =E51/G51 -> 0.55762082 | I51: =G51*$A$1 -> -0.00807 | J51: 0.0008 | K51: -0.0041 | L51: =J51-K51 -> 0.0049
B52: 20251015 | C52: =F52-D52 -> -0.0039 | D52: 0.0064 | E52: =F52 -> 0.0025 | F52: 0.0025 | G52: 0.00714 | H52: =E52/G52 -> 0.35014006 | I52: =G52*$A$1 -> 0.004284 | J52: 0.0079 | K52: 0.0122 | L52: =J52-K52 -> -0.0043
B53: 20251016 | C53: =F53-D53 -> 0.0016 | D53: -0.0119 | E53: =F53 -> -0.0103 | F53: -0.0103 | G53: -0.01326 | H53: =E53/G53 -> 0.77677225 | I53: =G53*$A$1 -> -0.007956 | J53: 0.004 | K53: 0.0064 | L53: =J53-K53 -> -0.0024
B54: 20251017 | C54: =F54-D54 -> 0.0011 | D54: -0.0103 | E54: =F54 -> -0.0092 | F54: -0.0092 | G54: -0.0244 | H54: =E54/G54 -> 0.37704918 | I54: =G54*$A$1 -> -0.01464 | J54: -0.0062 | K54: -0.0111 | L54: =J54-K54 -> 0.0049
B55: 20251020 | C55: =F55-D55 -> 0.0015 | D55: 0.0038 | E55: =F55 -> 0.0053 | F55: 0.0053 | G55: 0.014 | H55: =E55/G55 -> 0.37857143 | I55: =G55*$A$1 -> 0.0084 | J55: 0.01 | K55: 0.0155 | L55: =J55-K55 -> -0.0055
B56: 20251021 | C56: =F56-D56 -> -0.0022 | D56: 0.013 | E56: =F56 -> 0.0108 | F56: 0.0108 | G56: 0.0165 | H56: =E56/G56 -> 0.65454545 | I56: =G56*$A$1 -> 0.0099 | J56: 0.0158 | K56: 0.0115 | L56: =J56-K56 -> 0.0043
B57: 20251022 | C57: =F57-D57 -> 0.0027 | D57: -0.0044 | E57: =F57 -> -0.0017 | F57: -0.0017 | G57: 0.0018 | H57: =E57/G57 -> -0.94444444 | I57: =G57*$A$1 -> 0.00108 | J57: 0 | K57: 0.0105 | L57: =J57-K57 -> -0.0105
A58: 切正股 | B58: 20251023 | C58: =F58-D58 -> 0.0032 | D58: 0.0001 | E58: 0.0023 | F58: 0.0033 | G58: 0.0045 | H58: =E58/G58 -> 0.51111111 | I58: =G58*$A$1 -> 0.0027 | J58: 0.0071 | K58: 0.0071 | L58: =J58-K58 -> 0
B59: 20251024 | C59: =F59-D59 -> -0.01 | D59: 0.0102 | E59: 0.0049 | F59: 0.0002 | G59: 0.0002 | H59: =E59/G59 -> 24.5 | I59: =G59*$A$1 -> 0.00012 | J59: 0.0152 | K59: 0.0062 | L59: =J59-K59 -> 0.009
B60: 20251027 | C60: =F60-D60 -> -0.0036 | D60: 0.0067 | E60: 0.00558 | F60: 0.0031 | G60: 0.0062 | H60: =E60/G60 -> 0.9 | I60: =G60*$A$1 -> 0.00372 | J60: 0.0056 | K60: 0.0009 | L60: =J60-K60 -> 0.0047
B61: 20251028 | C61: =F61-D61 -> 0.00315 | D61: -0.003 | E61: -0.0019 | F61: 0.00015 | G61: 0.0003 | H61: =E61/G61 -> -6.3333333 | I61: =G61*$A$1 -> 0.00018 | J61: -0.0115 | K61: 0.0001 | L61: =J61-K61 -> -0.0116
A62: 切转债 | B62: 20251029 | C62: =F62-D62 -> -0.0066 | D62: 0.0066 | E62: 0.0043 | F62: 0 | G62: 0.0064 | H62: =E62/G62 -> 0.671875 | I62: =G62*$A$1 -> 0.00384 | J62: -0.0063 | K62: -0.0062 | L62: =J62-K62 -> -0.0001
B63: 20251030 | C63: =F63-D63 -> -0.0047 | D63: -0.0091 | E63: -0.0138 | F63: -0.0138 | G63: -0.0153 | H63: =E63/G63 -> 0.90196078 | I63: =G63*$A$1 -> -0.00918 | J63: -0.0034 | K63: 0.0014 | L63: =J63-K63 -> -0.0048
B64: 20251031 | C64: =F64-D64 -> -0.0009 | D64: 0.0049 | E64: 0.004 | F64: 0.004 | G64: 0.00945 | H64: =E64/G64 -> 0.42328042 | I64: =G64*$A$1 -> 0.00567 | J64: 0.0143 | K64: 0.0143 | L64: =J64-K64 -> 0 | P64: =8696 -> 8696
B65: 202511汇总 | C65: =SUM(C66:C85) -> 0.00825 | D65: =SUM(D66:D85) -> -0.006 | E65: =SUM(E66:E85) -> -0.00305 | F65: =SUM(F66:F85) -> 0.00225 | G65: =SUM(G66:G85) -> -0.05282 | H65: =F65/G65 -> -0.042597501 | I65: =SUM(I66:I85) -> -0.031692 | J65: =SUM(J66:J85) -> 0.03525 | K65: =SUM(K66:K85) -> 0.0336 | L65: =SUM(L66:L85) -> 0.00165 | M65: =SUM(M66:M85) -> 0.02858 | N65: =SUM(N66:N85) -> 0.032079 | O65: =SUM(O66:O85) -> -0.0839 | P65: =SUM(P66:P85) -> 46884 | R65: =SUM(R66:R85) -> 0.0036 | U65: =SUM(U66:U85) -> 0.0456
B66: 20251103 | C66: =F66-D66 -> 0.0028 | D66: 0.0008 | E66: 0.0036 | F66: 0.0036 | G66: 0.0044 | H66: =E66/G66 -> 0.81818182 | I66: =G66*$A$1 -> 0.00264 | J66: 0.014 | K66: 0.0188 | L66: =J66-K66 -> -0.0048 | M66: 0.0184 | N66: 0.0178 | P66: 13093 | R66: 0.0017 | U66: 0.014 | X66: 31
B67: 20251104 | C67: =F67-D67 -> 0.0025 | D67: -0.009 | E67: -0.0065 | F67: -0.0065 | G67: -0.0105 | H67: =E67/G67 -> 0.61904762 | I67: =G67*$A$1 -> -0.0063 | J67: 0.0026 | K67: 0.0021 | L67: =J67-K67 -> 0.0005 | M67: 0.0017 | N67: 0.002379 | P67: -1175 | R67: -0.0066 | U67: 0.0029 | X67: 18
B68: 20251105 | C68: =F68-D68 -> -0.0006 | D68: 0.007 | E68: 0.0064 | F68: 0.0064 | G68: 0.0058 | H68: =E68/G68 -> 1.1034483 | I68: =G68*$A$1 -> 0.00348 | J68: 0.0031 | K68: 0.0041 | L68: =J68-K68 -> -0.001 | M68: 0.0005 | N68: 0.0075 | P68: 6620 | R68: 0.0055 | U68: 0.0114 | X68: 17
B69: 20251106 | C69: =F69-D69 -> -0.0035 | D69: 0.0065 | E69: 0.003 | F69: 0.003 | G69: 0.003 | H69: =E69/G69 -> 1 | I69: =G69*$A$1 -> 0.0018 | J69: -0.0046 | K69: -0.0039 | L69: =J69-K69 -> -0.0007 | M69: -0.0048 | N69: -0.0026 | P69: -2020 | R69: 0.0033 | U69: 0.0015 | X69: 11
B70: 20251107 | C70: =F70-D70 -> 0.0012 | D70: -0.0012 | E70: 0 | F70: 0 | G70: 0.00154 | H70: =E70/G70 -> 0 | I70: =G70*$A$1 -> 0.000924 | J70: -0.00185 | K70: -0.0003 | L70: =J70-K70 -> -0.00155 | M70: 0.00122 | N70: -0.002 | P70: -2330 | R70: -0.0002 | U70: 0.0013 | X70: 13
B71: 20251110 | C71: =F71-D71 -> 0.0029 | D71: 0.0052 | E71: 0.0081 | F71: 0.0081 | G71: 0.0105 | H71: =E71/G71 -> 0.77142857 | I71: =G71*$A$1 -> 0.0063 | J71: 0.0056 | K71: 0.0065 | L71: =J71-K71 -> -0.0009 | M71: 0.0091 | N71: 0.003 | P71: 9500 | R71: 0.0115 | U71: 0.0073 | X71: 25
B72: 20251111 | C72: =F72-D72 -> 0.00125 | D72: -0.0006 | E72: 0.00065 | F72: 0.00065 | G72: 4e-05 | H72: =E72/G72 -> 16.25 | I72: =G72*$A$1 -> 2.4e-05 | J72: 0.0133 | K72: 0.0075 | L72: =J72-K72 -> 0.0058 | M72: 0.00916 | N72: 0.0057 | P72: 10600 | R72: 0.0001 | U72: 0.0077 | X72: 19
B73: 20251112 | C73: =F73-D73 -> 0.0016 | D73: -0.0031 | E73: -0.0015 | F73: -0.0015 | G73: -0.0092 | H73: =E73/G73 -> 0.16304348 | I73: =G73*$A$1 -> -0.00552 | J73: 0.0198 | K73: 0.0074 | L73: =J73-K73 -> 0.0124 | M73: 0.0064 | N73: 0.0071 | P73: 17700 | R73: -0.0035 | U73: -0.0027 | X73: 24
B74: 20251113 | C74: =F74-D74 -> -0.0036 | D74: 0.0114 | E74: 0.0078 | F74: 0.0078 | G74: 0.0088 | H74: =E74/G74 -> 0.88636364 | I74: =G74*$A$1 -> 0.00528 | J74: 0.0142 | K74: 0.0102 | L74: =J74-K74 -> 0.004 | M74: 0.0172 | N74: 0.0052 | P74: 17200 | R74: 0.0081 | U74: 0.0089 | X74: 23
B75: 20251114 | C75: =F75-D75 -> 0.0005 | D75: -0.0068 | E75: -0.0063 | F75: -0.0063 | G75: -0.0076 | H75: =E75/G75 -> 0.82894737 | I75: =G75*$A$1 -> -0.00456 | J75: 0.0154 | K75: 0.0063 | L75: =J75-K75 -> 0.0091 | M75: 0.0051 | N75: 0.0068 | P75: 12500 | R75: -0.0059 | U75: 0.0094 | X75: 25
B76: 20251117 | C76: =F76-D76 -> -0.0027 | D76: -0.0016 | E76: -0.0043 | F76: -0.0043 | G76: -0.009 | H76: =E76/G76 -> 0.47777778 | I76: =G76*$A$1 -> -0.0054 | J76: 0.0048 | K76: 0.0034 | L76: =J76-K76 -> 0.0014 | M76: 0.0062 | N76: 0.0004 | O76: -0.012 | P76: 3400 | R76: -0.0027 | U76: 0.0081 | X76: 22
B77: 20251118 | C77: =F77-D77 -> 0.0007 | D77: -0.0053 | E77: -0.0046 | F77: -0.0046 | G77: -0.0158 | H77: =E77/G77 -> 0.29113924 | I77: =G77*$A$1 -> -0.00948 | J77: 0.0077 | K77: -0.0022 | L77: =J77-K77 -> 0.0099 | M77: -0.006 | N77: 0.0008 | O77: -0.006 | P77: 5900 | R77: -0.0062 | U77: -0.007 | X77: 21
B78: 20251119 | C78: =F78-D78 -> 0.0014 | D78: 0.001 | E78: 0.0024 | F78: 0.0024 | G78: -0.0088 | H78: =E78/G78 -> -0.27272727 | I78: =G78*$A$1 -> -0.00528 | J78: -0.0082 | K78: -0.0128 | L78: =J78-K78 -> 0.0046 | M78: -0.0205 | N78: -0.008 | O78: -0.03 | P78: -6767 | R78: 0.0023 | U78: -0.0217 | X78: 13
B79: 20251120 | C79: =F79-D79 -> -0.0019 | D79: -0.0019 | E79: -0.0038 | F79: -0.0038 | G79: -0.0153 | H79: =E79/G79 -> 0.24836601 | I79: =G79*$A$1 -> -0.00918 | J79: -0.025 | K79: -0.0101 | L79: =J79-K79 -> -0.0149 | M79: -0.0095 | N79: -0.011 | O79: -0.018 | P79: -24500 | R79: -0.0038 | U79: -0.0065 | X79: 12
B80: 20251121 | C80: =F80-D80 -> 0.0053 | D80: -0.0118 | E80: -0.0095 | F80: -0.0065 | G80: -0.038 | H80: =E80/G80 -> 0.25 | I80: =G80*$A$1 -> -0.0228 | J80: -0.03 | K80: -0.0337 | L80: =J80-K80 -> 0.0037 | M80: -0.0363 | N80: -0.0316 | O80: -0.0415 | P80: -20000 | R80: -0.0073 | U80: -0.049 | X80: 5
B81: 20251124 | C81: =F81-D81 -> -0.0013 | D81: 0.0061 | E81: 0.0048 | F81: 0.0048 | G81: 0.0082 | H81: =E81/G81 -> 0.58536585 | I81: =G81*$A$1 -> 0.00492 | J81: 0.003 | K81: 0.0063 | L81: =J81-K81 -> -0.0033 | M81: 0.0068 | N81: 0.0043 | O81: 0.0167 | P81: 2600 | R81: 0.0061 | U81: 0.0225 | X81: 15
B82: 20251125 | C82: =F82-D82 -> -0.0012 | D82: 0.0031 | E82: 0.0019 | F82: 0.0019 | G82: 0.0101 | H82: =E82/G82 -> 0.18811881 | I82: =G82*$A$1 -> 0.00606 | J82: 0 | K82: 0.0171 | L82: =J82-K82 -> -0.0171 | M82: 0.0176 | N82: 0.0183 | O82: 0.0112 | P82: 1386 | R82: 0.0038 | U82: 0.0176 | X82: 22
B83: 20251126 | C83: =F83-D83 -> 0.0027 | D83: -0.0089 | E83: -0.008 | F83: -0.0062 | G83: -0.0055 | H83: =E83/G83 -> 1.4545455 | I83: =G83*$A$1 -> -0.0033 | J83: -0.0015 | K83: 0.0015 | L83: =J83-K83 -> -0.003 | M83: 0.0064 | N83: -0.0014 | O83: 0.0001 | P83: -2000 | R83: -0.0065 | U83: -0.0102 | X83: 12
B84: 20251127 | C84: =F84-D84 -> 0 | D84: -0.005 | E84: -0.0055 | F84: -0.005 | G84: 0.0073 | H84: =E84/G84 -> -0.75342466 | I84: =G84*$A$1 -> 0.00438 | J84: -0.0008 | K84: -0.0035 | L84: =J84-K84 -> 0.0027 | M84: -0.0063 | N84: -0.0011 | O84: -0.0114 | P84: -923 | R84: -0.0052 | U84: 0.0126 | X84: 10
B85: 20251128 | C85: =F85-D85 -> 0.0002 | D85: 0.0081 | E85: 0.0083 | F85: 0.0083 | G85: 0.0072 | H85: =E85/G85 -> 1.1527778 | I85: =G85*$A$1 -> 0.00432 | J85: 0.0037 | K85: 0.0089 | L85: =J85-K85 -> -0.0052 | M85: 0.0062 | N85: 0.0105 | O85: 0.007 | P85: 6100 | R85: 0.0091 | U85: 0.0175
B86: 202512汇总 | C86: =SUM(C87:C109) -> -0.0054435897 | D86: =SUM(D87:D109) -> 0.0309 | E86: =SUM(E87:E109) -> 0.01725 | F86: =SUM(F87:F109) -> 0.02545641 | G86: =SUM(G87:G109) -> 0.00464 | H86: =F86/G86 -> 5.4862953 | I86: =SUM(I87:I109) -> 0.002784 | J86: =SUM(J87:J109) -> -0.03918 | K86: =SUM(K87:K109) -> -0.0478 | L86: =SUM(L87:L109) -> 0.00862 | M86: =SUM(M87:M109) -> -0.0578 | N86: =SUM(N87:N109) -> -0.039716 | O86: =SUM(O87:O109) -> -0.0042 | P86: =SUM(P87:P109) -> -7926 | R86: =SUM(R87:R109) -> 0.0194 | T86: =SUM(T87:T109) -> 0.0156 | U86: =SUM(U87:U109) -> -0.0195
B87: 20251201 | C87: =F87-D87 -> 0.001 | D87: 0.0007 | E87: 0.0013 | F87: 0.0017 | G87: 0.0075 | H87: =E87/G87 -> 0.17333333 | I87: =G87*$A$1 -> 0.0045 | J87: 0.0031 | K87: -0.0003 | L87: =J87-K87 -> 0.0034 | M87: 0.0015 | N87: -0.0011 | O87: -0.0027 | P87: 50 | R87: 0.0029 | U87: 0 | X87: 13
B88: 20251202 | C88: =F88-D88 -> 0.0007 | D88: -0.0058 | E88: -0.0061 | F88: -0.0051 | G88: -0.0107 | H88: =E88/G88 -> 0.57009346 | I88: =G88*$A$1 -> -0.00642 | J88: 0.01 | K88: -0.0062 | L88: =J88-K88 -> 0.0162 | M88: -0.0056 | N88: -0.0041 | O88: -0.0002 | P88: 3000 | R88: -0.0061 | U88: -0.0033 | X88: 9
B89: 20251203 | C89: =F89-D89 -> -0.0006 | D89: -0.0024 | E89: -0.003 | F89: -0.003 | G89: -0.0089 | H89: =E89/G89 -> 0.33707865 | I89: =G89*$A$1 -> -0.00534 | J89: -0.0132 | K89: -0.0112 | L89: =J89-K89 -> -0.002 | M89: -0.0174 | N89: -0.0063 | O89: 0.0021 | P89: -5800 | R89: -0.0026 | U89: -0.0089 | X89: 8
B90: 20251204 | C90: =F90-D90 -> -0.0007 | D90: -0.0017 | E90: -0.003 | F90: -0.0024 | G90: -0.0109 | H90: =E90/G90 -> 0.27522936 | I90: =G90*$A$1 -> -0.00654 | J90: -0.0291 | K90: -0.0191 | L90: =J90-K90 -> -0.01 | M90: -0.0134 | N90: -0.0232 | O90: -0.03 | P90: -12300 | R90: -0.0021 | U90: -0.0172 | X90: 2
B91: 20251205 | C91: =F91-D91 -> 0.0006 | D91: 0.0114 | E91: 0.0119 | F91: 0.012 | G91: 0.0122 | H91: =E91/G91 -> 0.97540984 | I91: =G91*$A$1 -> 0.00732 | J91: 0.008 | K91: 0.0053 | L91: =J91-K91 -> 0.0027 | M91: 0.0062 | N91: 0.0059 | O91: -0.0085 | P91: 4300 | R91: 0.013 | U91: 0.0177 | X91: 10
B92: 20251208 | C92: =F92-D92 -> -0.0019 | D92: 0.0061 | E92: 0.0038 | F92: 0.0042 | G92: 0.0063 | H92: =E92/G92 -> 0.6031746 | I92: =G92*$A$1 -> 0.00378 | J92: 0.0036 | K92: 0.0009 | L92: =J92-K92 -> 0.0027 | M92: 0.0023 | N92: -0.001 | O92: 0.0128 | P92: 2400 | R92: 0.0021 | U92: 0.0112 | X92: 7
B93: 20251209 | C93: =F93-D93 -> 0.0007 | D93: -0.007 | E93: -0.0065 | F93: -0.0063 | G93: -0.0071 | H93: =E93/G93 -> 0.91549296 | I93: =G93*$A$1 -> -0.00426 | J93: -0.0001 | K93: -0.0039 | L93: =J93-K93 -> 0.0038 | M93: -0.0001 | N93: -0.0042 | O93: -0.0073 | P93: -1700 | R93: -0.0071 | U93: -0.0088 | X93: 3 | Y93: 6
B94: 20251210 | C94: =F94-D94 -> 0.0023 | D94: 0.0039 | E94: 0.006 | F94: 0.0062 | G94: 0.0067 | H94: =E94/G94 -> 0.89552239 | I94: =G94*$A$1 -> 0.00402 | J94: -0.0183 | K94: -0.0048 | L94: =J94-K94 -> -0.0135 | M94: -0.0045 | N94: -0.0036 | O94: -0.0101 | P94: -6200 | R94: 0.0062 | U94: -0.0103 | X94: 4 | Y94: 9
B95: 20251211 | C95: =F95-D95 -> -0.0036435897 | D95: -0.0056 | E95: -0.0091 | F95: =-721/78000 -> -0.0092435897 | G95: -0.0242 | H95: =E95/G95 -> 0.37603306 | I95: =G95*$A$1 -> -0.01452 | J95: -0.02 | K95: -0.0154 | L95: =J95-K95 -> -0.0046 | M95: -0.016 | N95: -0.0132 | O95: -0.0004 | P95: -8872 | R95: -0.0077 | U95: -0.0264 | X95: 3 | Y95: 9
B96: 20251212 | C96: =F96-D96 -> -0.0003 | D96: 0.0037 | E96: 0.003 | F96: 0.0034 | G96: 0.0113 | H96: =E96/G96 -> 0.26548673 | I96: =G96*$A$1 -> 0.00678 | J96: -0.01 | K96: -0.0081 | L96: =J96-K96 -> -0.0019 | M96: -0.0082 | N96: -0.0105 | O96: 0.0001 | P96: -3934 | R96: 0.0025 | U96: -0.013 | X96: 4 | Y96: 15
B97: 20251215 | C97: =F97-D97 -> 0.0021 | D97: -0.0021 | E97: 0.0004 | F97: 0 | G97: 0.0052 | H97: =E97/G97 -> 0.076923077 | I97: =G97*$A$1 -> 0.00312 | J97: 0 | K97: -0.0069 | L97: =J97-K97 -> 0.0069 | M97: -0.0051 | N97: -0.012 | O97: 0.0047 | P97: -120 | R97: 0.0012 | U97: 0.0063 | X97: 5 | Y97: 21
B98: 20251216 | C98: =F98-D98 -> 0.0012 | D98: -0.0088 | E98: -0.008 | F98: -0.0076 | G98: -0.0186 | H98: =E98/G98 -> 0.43010753 | I98: =G98*$A$1 -> -0.01116 | J98: -0.0194 | K98: -0.0217 | L98: =J98-K98 -> 0.0023 | M98: -0.0199 | N98: -0.0237 | O98: -0.0118 | P98: -7719 | R98: -0.008 | U98: -0.0188 | X98: 4 | Y98: 31
B99: 20251217 | C99: =F99-D99 -> -0.0013 | D99: 0.0094 | E99: 0.0081 | F99: 0.0081 | G99: 0.00926 | H99: =E99/G99 -> 0.87473002 | I99: =G99*$A$1 -> 0.005556 | J99: 0.00086 | K99: 0.003 | L99: =J99-K99 -> -0.00214 | M99: 0.0075 | N99: 0.00075 | O99: 0.0021 | P99: 1169 | R99: 0.0084 | U99: 0.001 | X99: 8 | Y99: 7
B100: 20251218 | C100: =F100-D100 -> 0.0003 | D100: 0.0036 | E100: 0.0039 | F100: 0.0039 | G100: 0.0105 | H100: =E100/G100 -> 0.37142857 | I100: =G100*$A$1 -> 0.0063 | J100: 0.0108 | K100: 0.0035 | L100: =J100-K100 -> 0.0073 | M100: 0.0057 | N100: 0.0022 | O100: 0.0041 | P100: 7700 | R100: 0.0063 | U100: 0.0184 | X100: 13 | Y100: 7
B101: 20251219 | C101: =F101-D101 -> -0.0012 | D101: 0.005 | E101: 0.0041 | F101: 0.0038 | G101: 0.0134 | H101: =E101/G101 -> 0.30597015 | I101: =G101*$A$1 -> 0.00804 | J101: 0.0146 | K101: 0.0139 | L101: =J101-K101 -> 0.0007 | M101: 0.0146 | N101: 0.0135 | O101: 0.0187 | P101: 7300 | R101: 0.0037 | U101: 0.025 | X101: 15 | Y101: 7
B102: 20251222 | C102: =F102-D102 -> 0.0047 | D102: 0.0062 | E102: 0.0096 | F102: 0.0109 | G102: 0.0149 | H102: =E102/G102 -> 0.6442953 | I102: =G102*$A$1 -> 0.00894 | J102: 0.01166 | K102: 0.016 | L102: =J102-K102 -> -0.00434 | M102: 0.0099 | N102: 0.0183 | O102: 0.0157 | P102: 6200 | R102: 0.0028 | U102: -0.0014 | X102: 26 | Y102: 2
B103: 20251223 | C103: =F103-D103 -> 0.003 | D103: -0.004 | E103: -0.00486 | F103: -0.001 | G103: -0.00567 | H103: =E103/G103 -> 0.85714286 | I103: =G103*$A$1 -> -0.003402 | J103: -0.0111 | K103: -0.0073 | L103: =J103-K103 -> -0.0038 | M103: -0.0127 | N103: -0.0024 | O103: 0.003 | P103: -4900 | R103: -0.0019 | U103: -0.006 | X103: 15 | Y103: 13
A104: ST清仓 | B104: 20251224 | C104: =F104-D104 -> -0.0034 | D104: 0.0102 | E104: 0.00547 | F104: 0.0068 | G104: 0.00738 | H104: =E104/G104 -> 0.74119241 | I104: =G104*$A$1 -> 0.004428 | J104: 0 | K104: 0.0102 | L104: =J104-K104 -> -0.0102 | M104: 0.0054 | N104: 0.014 | O104: 0.007 | P104: 3300 | R104: 0.006 | T104: 0.0122 | U104: 0.0101 | X104: 16 | Y104: 3
B105: 20251225 | C105: =F105-D105 -> -0.0019 | D105: 0.01 | E105: 0.0087 | F105: 0.0081 | G105: 0.0126 | H105: =E105/G105 -> 0.69047619 | I105: =G105*$A$1 -> 0.00756 | J105: 0 | K105: 0.0103 | L105: =J105-K105 -> -0.0103 | M105: 0.0095 | N105: 0.0125 | O105: 0.0048 | P105: 3000 | R105: 0.0058 | T105: 0.0139 | U105: 0.0113 | X105: 21 | Y105: 3
B106: 20251226 | C106: =F106-D106 -> -0.0022 | D106: -0.0023 | E106: -0.0042 | F106: -0.0045 | G106: -0.004 | H106: =E106/G106 -> 1.05 | I106: =G106*$A$1 -> -0.0024 | J106: 0 | K106: 0.0015 | L106: =J106-K106 -> -0.0015 | M106: -0.0048 | N106: 0.007 | O106: 0.0055 | P106: 400 | R106: -0.0038 | T106: -0.0073 | U106: -0.007 | X106: 11 | Y106: 2
B107: 20251229 | C107: =F107-D107 -> -0.0023 | D107: -0.0035 | E107: -0.00556 | F107: -0.0058 | G107: -0.0048 | H107: =E107/G107 -> 1.1583333 | I107: =G107*$A$1 -> -0.00288 | J107: 0 | K107: -0.0035 | L107: =J107-K107 -> 0.0035 | M107: -0.0077 | N107: -0.0037 | O107: -0.0093 | P107: 200 | R107: -0.0057 | T107: -0.0005 | U107: 0.004 | X107: 19 | Y107: 12
B108: 20251230 | C108: =F108-D108 -> -0.0015 | D108: 0.0018 | E108: 0.0003 | F108: 0.0003 | G108: -0.008 | H108: =E108/G108 -> -0.0375 | I108: =G108*$A$1 -> -0.0048 | J108: -0.0006 | K108: -0.0043 | L108: =J108-K108 -> 0.0037 | M108: -0.0035 | N108: -0.005766 | O108: -0.008 | P108: -600 | R108: 0.001 | T108: -0.0065 | U108: -0.0087 | X108: 16 | Y108: 11
B109: 20251231 | C109: =F109-D109 -> -0.0011 | D109: 0.0021 | E109: 0.001 | F109: 0.001 | G109: -0.00973 | H109: =E109/G109 -> -0.10277492 | I109: =G109*$A$1 -> -0.005838 | J109: 0.02 | K109: 0.0003 | L109: =J109-K109 -> 0.0197 | M109: -0.0015 | N109: 0.0009 | O109: 0.0035 | P109: 5200 | R109: 0.0025 | T109: 0.0038 | U109: 0.0053 | X109: 7 | Y109: 9
B110: 202601汇总 | C110: =SUM(C111:C130) -> 0.01085 | D110: =SUM(D111:D130) -> 0.0725 | E110: =SUM(E111:E130) -> 0.0752 | F110: =SUM(F111:F130) -> 0.08335 | G110: =SUM(G111:G130) -> 0.13345 | H110: =F110/G110 -> 0.62457849 | I110: =SUM(I111:I130) -> 0.08007 | J110: =SUM(J111:J130) -> -0.0219 | K110: =SUM(K111:K130) -> 0.0436 | L110: =SUM(L111:L130) -> -0.0655 | M110: =SUM(M111:M130) -> 0.04513 | N110: =SUM(N111:N130) -> 0.0277 | O110: =SUM(O111:O130) -> -0.01485 | P110: =SUM(P111:P130) -> 85220 | Q110: 0 | R110: =SUM(R111:R130) -> 0.0687 | S110: =SUM(S111:S130) -> 0 | T110: =SUM(T111:T130) -> 0.0653 | U110: =SUM(U111:U130) -> 0.1042
B111: 20260105 | C111: =F111-D111 -> -0.0033 | D111: 0.0163 | E111: 0.014 | F111: 0.013 | G111: 0.0231 | H111: =E111/G111 -> 0.60606061 | I111: =G111*$A$1 -> 0.01386 | J111: 0 | K111: 0.012 | L111: =J111-K111 -> -0.012 | M111: 0.01 | N111: 0.0148 | O111: -0.0026 | P111: 9100 | Q111: =Q110+P111 -> 9100 | R111: 0.0097 | T111: 0.0027 | U111: 0.0141 | X111: 23 | Y111: 6 | AA111: 0 | AB111: 半导体、医药
B112: 20260106 | C112: =F112-D112 -> -0.0002 | D112: 0.0137 | E112: 0.0135 | F112: 0.0135 | G112: 0.0187 | H112: =E112/G112 -> 0.72192513 | I112: =G112*$A$1 -> 0.01122 | J112: 0 | K112: 0.0121 | L112: =J112-K112 -> -0.0121 | M112: 0.0126 | N112: 0.0152 | O112: 0.0008 | P112: 25000 | Q112: =Q111+P112 -> 34100 | R112: 0.0114 | T112: -0.0031 | U112: 0.0025 | X112: 29 | Y112: 1 | AA112: 0 | AB112: 军工券商有色化工
B113: 20260107 | C113: =F113-D113 -> -0.0053 | D113: 0.0051 | E113: -0.0002 | F113: -0.0002 | G113: -0.00455 | H113: =E113/G113 -> 0.043956044 | I113: =G113*$A$1 -> -0.00273 | J113: -0.0182 | K113: 0.0015 | L113: =J113-K113 -> -0.0197 | M113: 0.0005 | N113: 0.004 | O113: 0.0066 | P113: -7550 | Q113: =Q112+P113 -> 26550 | R113: 0.0034 | T113: -0.008 | U113: -0.0046 | X113: 21 | Y113: 6 | AA113: 0 | AB113: 半导体煤炭
B114: 20260108 | C114: =F114-D114 -> -0.002 | D114: 0.007 | E114: 0.005 | F114: 0.005 | G114: 0.0089 | H114: =E114/G114 -> 0.56179775 | I114: =G114*$A$1 -> 0.00534 | J114: 0 | K114: 0.01 | L114: =J114-K114 -> -0.01 | M114: 0.009 | N114: 0.0122 | O114: 0.0128 | P114: 2800 | Q114: =Q113+P114 -> 29350 | R114: 0.0023 | T114: 0.0217 | U114: 0.0201 | X114: 24 | Y114: 3 | AA114: 0 | AB114: 军工地产
B115: 20260109 | C115: =F115-D115 -> -0.0035 | D115: 0.0113 | E115: 0.0078 | F115: 0.0078 | G115: 0.0073 | H115: =E115/G115 -> 1.0684932 | I115: =G115*$A$1 -> 0.00438 | J115: -0.0037 | K115: 0.0063 | L115: =J115-K115 -> -0.01 | M115: 0.0082 | N115: 0.0055 | O115: 0.0149 | P115: 8000 | Q115: =Q114+P115 -> 37350 | R115: 0.0066 | T115: 0.0123 | U115: 0.0121 | X115: 21 | Y115: 3 | AA115: 0 | AB115: 军工汽车零部件游戏医疗有色
...

Sheet etf
A1: 日期 | B1: 豆粕 | C1: 汽零 | D1: 机器人 | E1: 化工 | F1: 工程机械 | G1: 酒 | H1: 粮食 | I1: 消费 | J1: 旅游 | K1: 钢铁 | L1: 有色 | M1: 红利 | N1: 基建 | O1: 证券 | P1: 家电 | Q1: 煤炭 | R1: 银行 | S1: 房地产 | T1: 畜牧 | U1: 电网设备 | V1: 储能电池 | W1: 绿电 | X1: 医疗 | Y1: 中药 | Z1: 医药 | AA1: 生物医药 | AB1: 创新药 | AC1: 电力 | AD1: 汽车 | AE1: 光伏 | AF1: 软件 | AG1: 游戏 | AH1: 传媒 | AI1: 军工 | AJ1: 半导体 | AK1: 通信 | AL1: 上证 | AM1: 深圳 | AN1: 创业板 | AO1: 北交所 | AP1: 上证50 | AQ1: 沪深300 | AR1: 中证500 | AS1: 中证1000 | AT1: 微盘股 | AU1: 可转债等权 | AV1: ST | AW1: 融资板块 | AX1: 176 | AY1: 铁哥 | AZ1: 羊哥 | BA1: 雪哥 | BB1: 光头哥 | BD1: 中证1000超额
A2: 202512汇总 | B2: -0.0371 | C2: 0.12 | D2: 0.0722 | E2: 0.1031 | F2: 0.058 | G2: -0.0806 | H2: 0.0216 | I2: -0.0434 | J2: 0.0787 | K2: 0.0291 | L2: 0.1309 | M2: -0.0152 | N2: 0.0215 | O2: 0.0263 | P2: 0.0413 | Q2: -0.0551 | R2: -0.0156 | S2: -0.0285 | T2: -0.0199 | U2: 0.0601 | V2: 0.019 | W2: -0.0258 | X2: -0.0173 | Y2: -0.0306 | Z2: -0.0382 | AA2: -0.0352 | AB2: -0.0525 | AC2: -0.0263 | AD2: 0.0445 | AE2: 0.0042 | AF2: 0 | AG2: 0.0227 | AH2: 0.0071 | AI2: 0.1715 | AJ2: 0.0525 | AK2: 0.1217 | AL2: 0.0206 | AM2: 0.0417 | AN2: 0.0493 | AO2: 0.038 | AP2: 0.0207 | AQ2: 0.0228 | AR2: 0.0617 | AS2: 0.0356 | AT2: -0.0214
A3: 2025年汇总 | B3: 0.0668 | C3: 0.4362 | D3: 0.3089 | E3: 0.4256 | F3: 0.3567 | G3: -0.13 | H3: 0.1736 | I3: -0.0294 | J3: 0.1475 | K3: 0.2349 | L3: 0.9805 | M3: -0.0501 | N3: 0.0627 | O3: 0.035 | P3: 0.1749 | Q3: -0.0927 | R3: 0.1084 | S3: 0.0268 | T3: 0.1073 | U3: 0.3256 | V3: 0.5796 | W3: 0.0148 | X3: -0.0398 | Y3: -0.0412 | Z3: 0.0471 | AA3: 0.0637 | AB3: 0.1923 | AC3: 0.0101 | AD3: 0.1223 | AE3: 0.2708 | AF3: 0.1206 | AG3: 0.4386 | AH3: 0.2894 | AI3: 0.3177 | AJ3: 0.4509 | AK3: 0.9947 | AL3: 0.1841 | AM3: 0.2987 | AN3: 0.4957 | AO3: 0.388 | AP3: 0.129 | AQ3: 0.1766 | AR3: 0.3039 | AS3: 0.2749 | AT3: 0.8102
A4: 2026年汇总 | B4: =B5+B6+B21+B44+B66+B85+B107+B131+B153+B175 -> 0.17022915 | C4: =C5+C6+C21+C44+C66+C85+C107+C131+C153+C175 -> -0.25838592 | D4: =D5+D6+D21+D44+D66+D85+D107+D131+D153+D175 -> -0.084106511 | E4: =E5+E6+E21+E44+E66+E85+E107+E131+E153+E175 -> -0.069170959 | F4: =F5+F6+F21+F44+F66+F85+F107+F131+F153+F175 -> -0.096685762 | G4: =G5+G6+G21+G44+G66+G85+G107+G131+G153+G175 -> -0.23390865 | H4: =H5+H6+H21+H44+H66+H85+H107+H131+H153+H175 -> -0.098053073 | I4: =I5+I6+I21+I44+I66+I85+I107+I131+I153+I175 -> -0.17414608 | ... BD4: =BD5+BD6+BD21+BD44+BD66+BD85+BD107+BD131+BD153+BD175 -> 0.0061922045
A5: 202601汇总 | B5: 0.0169 | C5: -0.0118 | D5: 0.0436 | E5: 0.1141 | F5: 0.0623 | G5: 0.0093 | H5: 0.121 | I5: -0.0189 | J5: -0.0136 | K5: 0.0669 | L5: 0.2138 | M5: 0.0342 | N5: 0.0565 | O5: -0.014 | P5: 0.0064 | Q5: 0.0992 | R5: -0.0583 | S5: 0.0314 | T5: 0.0172 | U5: 0.164 | V5: 0.0143 | W5: 0.0325 | X5: 0.0471 | Y5: 0.0038 | Z5: 0.0053 | AA5: 0.0286 | AB5: 0.0084 | AC5: 0.027 | AD5: -0.0517 | AE5: 0.1102 | AF5: 0.0949 | AG5: 0.1042 | AH5: 0.2214 | AI5: 0.0532 | AJ5: 0.1687 | AK5: 0.0479 | AL5: 0.038 | AM5: 0.0513 | AN5: 0.0442 | AO5: 0.0635 | AP5: 0.0115 | AQ5: 0.0165 | AR5: 0.1212 | AS5: 0.0868 | AT5: 0.1074 | AU5: 0.0725 | AV5: 0.0436 | AW5: 0.0827 | AX5: 0.0615
A6: 202602汇总 | B6: =SUM(B7:B20) -> 0.0176 | C6: =SUM(C7:C20) -> 0.0207 | D6: =SUM(D7:D20) -> 0.0209 | E6: =SUM(E7:E20) -> 0.0521 | F6: =SUM(F7:F20) -> 0.0952 | G6: =SUM(G7:G20) -> -0.0271 | H6: =SUM(H7:H20) -> -0.0177 | I6: =SUM(I7:I20) -> -0.0032 | ... AJ6: =SUM(AJ7:AJ20) -> -0.0126 | AK6: 0.0164 | AL6: 0.0109 | AM6: 0.0204 | AN6: -0.0108 | AO6: 0.0036 | AP6: -0.0088 | AQ6: 0.0009 | AR6: 0.0344 | AS6: 0.0371 | AT6: 0.065 | AU6: 0.0133 | AV6: 0.0544 | AW6: 0.0373 | AX6: =SUM(AX7:AX20) -> 0.031 | AY6: =SUM(AY7:AY20) -> 0.0202 | AZ6: =SUM(AZ7:AZ20) -> 0 | BA6: =SUM(BA7:BA20) -> 0.0392
A7: 20260202 | B7: -0.004 | C7: -0.0218 | D7: -0.02 | E7: -0.0697 | F7: -0.0311 | G7: 0.0148 | H7: -0.0703 | I7: -0.0013 | J7: -0.0125 | K7: -0.062 | L7: -0.1 | M7: -0.0312 | N7: -0.0375 | O7: -0.0134 | P7: -0.0121 | Q7: -0.0593 | R7: 0.0013 | S7: -0.0336 | T7: -0.0369 | U7: 0.0133 | V7: -0.0155 | W7: -0.0075 | X7: -0.0225 | Y7: -0.0124 | Z7: -0.0211 | AA7: -0.0253 | AB7: -0.0298 | AC7: -0.0146 | AD7: -0.0228 | AE7: -0.0094 | AF7: -0.0251 | AG7: -0.0352 | AH7: -0.0287 | AI7: -0.018 | AJ7: -0.0544 | AX7: -0.023 | AY7: -0.0193 | BA7: -0.0135
A8: 20260203 | B8: -0.0015 | C8: 0.0311 | D8: 0.0259 | E8: 0.041 | F8: 0.066 | G8: 0.0036 | H8: 0.0138 | I8: 0.0077 | J8: 0.014 | K8: 0.0344 | L8: 0.0684 | M8: 0.0016 | N8: 0.0207 | O8: 0.0034 | P8: 0.0103 | Q8: 0.0056 | R8: -0.0103 | S8: 0.0228 | T8: 0.008 | U8: 0.0366 | V8: 0.0234 | W8: 0.005 | X8: 0.0172 | Y8: 0.0048 | Z8: 0.0134 | AA8: 0.0156 | AB8: 0.0123 | AC8: 0.0079 | AD8: 0.0196 | AE8: 0.0605 | AF8: 0.0307 | AG8: 0.028 | AH8: 0.0346 | AI8: 0.0444 | AJ8: 0.0148 | AX8: 0.0192 | AY8: 0.0161 | BA8: 0.0224
A9: 20260204 | B9: 0.002 | C9: 0.0079 | D9: -0.0054 | E9: 0.0011 | F9: 0.0216 | G9: 0.02 | H9: 0.0027 | I9: 0.0217 | J9: 0.0313 | K9: 0.0233 | L9: 0.0018 | M9: 0.0324 | N9: 0.0138 | O9: 0.0145 | P9: 0.0095 | Q9: 0.0907 | R9: 0.0143 | S9: 0.0275 | T9: 0.0095 | U9: 0.0033 | V9: 0.0122 | W9: 0.0174 | X9: 0.0169 | Y9: 0.0144 | Z9: 0.008 | AA9: 0.0102 | AB9: 0.0109 | AC9: 0.0137 | AD9: 0.02 | AE9: 0.0312 | AF9: -0.0191 | AG9: -0.0311 | AH9: -0.0327 | AI9: 0.0013 | AJ9: -0.0207 | AX9: 0.0133 | AY9: 0.003 | BA9: 0.0039
A10: 20260205 | B10: 0.0025 | C10: -0.0163 | D10: -0.0173 | E10: -0.0213 | F10: -0.0111 | G10: 0.0053 | H10: -0.0227 | I10: 0.01 | J10: 0.0158 | K10: -0.0208 | L10: -0.0484 | M10: -0.0044 | N10: -0.0176 | O10: 0.0017 | P10: -0.0038 | Q10: -0.0283 | R10: 0.0167 | S10: -0.0013 | T10: -0.0016 | U10: -0.0479 | V10: -0.0356 | W10: -0.0122 | X10: 0 | Y10: 0.0095 | Z10: 0.0105 | AA10: 0 | AB10: 0.0024 | AC10: -0.0087 | AD10: -0.0043 | AE10: -0.0545 | AF10: -0.0141 | AG10: 0.002 | AH10: -0.0076 | AI10: -0.0128 | AJ10: -0.0106 | AX10: -0.0062 | AY10: -0.0008 | BA10: -0.0034
A11: 20260206 | B11: 0.001 | C11: 0.0046 | D11: 0.0065 | E11: 0.0264 | F11: -0.0118 | G11: -0.0195 | H11: 0.0056 | I11: -0.0124 | J11: -0.0167 | K11: -0.004 | L11: 0.0042 | M11: -0.0032 | N11: -0.0098 | O11: -0.0059 | P11: -0.0044 | Q11: -0.0044 | R11: -0.0025 | S11: -0.0134 | T11: 0 | U11: 0.0052 | V11: 0.0062 | W11: 0.0017 | X11: -0.0056 | Y11: 0.0066 | Z11: -0.0026 | AA11: -0.0025 | AB11: -0.0012 | AC11: 0.0029 | AD11: -0.0022 | AE11: 0.0073 | AF11: -0.0165 | AG11: 0.0052 | AH11: -0.0145 | AI11: -0.0177 | AJ11: -0.0088 | AX11: 0.0057 | AY11: -0.0008 | BA11: 0.0075
A12: 20260209 | B12: 0.0015 | C12: 0.0105 | D12: 0.0165 | E12: 0.0134 | F12: 0.0364 | G12: 0 | H12: 0.0055 | I12: 0.0013 | J12: 0.017 | K12: 0.018 | L12: 0.0214 | M12: 0.0058 | N12: 0.014 | O12: 0.0093 | P12: 0.0095 | Q12: 0.0053 | R12: 0.0025 | S12: 0.022 | T12: 0.0031 | U12: 0.0299 | V12: 0.0276 | W12: 0.0058 | X12: 0.0028 | Y12: 0.0019 | Z12: 0 | AA12: 0.0051 | AB12: 0.0036 | AC12: 0.0049 | AD12: 0.0058 | AE12: 0.0381 | AF12: 0.0347 | AG12: 0.0286 | AH12: 0.0431 | AI12: 0.0181 | AJ12: 0.0323 | AX12: 0.0112 | AY12: 0.0092 | BA12: 0.015
A13: 20260210 | B13: -0.005 | C13: 0.0072 | D13: 0.0099 | E13: -0.0011 | F13: 0.0049 | G13: -0.0162 | H13: -0.0073 | I13: -0.0125 | J13: -0.006 | K13: -0.0013 | L13: -0.0018 | M13: 0.0038 | N13: -0.0065 | O13: -0.0008 | P13: 0.0101 | Q13: 0.0088 | R13: 0.0025 | S13: -0.0164 | T13: -0.0031 | U13: 0.0095 | V13: -0.0051 | W13: -0.0057 | X13: 0.0084 | Y13: -0.0056 | Z13: 0.0131 | AA13: 0.0076 | AB13: 0.0144 | AC13: -0.0058 | AD13: 0.0029 | AE13: -0.0166 | AF13: 0.0086 | AG13: 0.0556 | AH13: 0.0455 | AI13: 0.002 | AJ13: 0.0049 | AX13: 0.0012 | AY13: -0.0009 | BA13: -0.0001
A14: 20260211 | B14: 0.0061 | C14: -0.0103 | D14: -0.0116 | E14: 0.021 | F14: 0.0044 | G14: 0 | H14: 0.0074 | I14: 0 | J14: -0.012 | K14: 0.0177 | L14: 0.0278 | M14: 0.0086 | N14: 0.0025 | O14: -0.0017 | P14: -0.0106 | Q14: 0.014 | R14: 0.0025 | S14: -0.0026 | T14: 0.0031 | U14: 0.0006 | V14: -0.0047 | W14: -0.0017 | X14: -0.0055 | Y14: -0.0028 | Z14: 0 | AA14: -0.0025 | AB14: -0.0024 | AC14: 0.001 | AD14: 0.0007 | AE14: -0.0098 | AF14: -0.0096 | AG14: 0 | AH14: -0.0285 | AI14: -0.0075 | AJ14: -0.0116 | AX14: 0.0038 | AY14: 0.0035 | BA14: 0.0006
A15: 20260212 | B15: 0.001 | C15: 0.0039 | D15: 0.0136 | E15: 0.0011 | F15: 0.0212 | G15: -0.0183 | H15: -0.011 | I15: -0.0114 | J15: -0.0207 | K15: 0.0006 | L15: 0.0066 | M15: -0.0009 | N15: 0.0033 | O15: -0.0075 | P15: 0 | Q15: 0.0034 | R15: -0.0151 | S15: -0.0052 | T15: -0.011 | U15: 0.0326 | V15: 0.0313 | W15: 0.0074 | X15: -0.0056 | Y15: -0.0103 | Z15: -0.0026 | AA15: -0.005 | AB15: -0.0035 | AC15: 0.0078 | AD15: -0.0014 | AE15: 0.0126 | AF15: 0.0152 | AG15: -0.0215 | AH15: 0.0057 | AI15: 0.0137 | AJ15: 0.0216 | AX15: -0.0001 | AY15: -0.0001 | BA15: -0.0042
A16: 20260213 | B16: 0.0055 | C16: -0.0013 | D16: 0.0009 | E16: -0.0195 | F16: -0.0256 | G16: 0 | H16: -0.0083 | I16: -0.0038 | J16: -0.0062 | K16: -0.0251 | L16: -0.0343 | M16: -0.0135 | N16: -0.0098 | O16: -0.0093 | P16: -0.0044 | Q16: -0.0172 | R16: -0.0064 | S16: -0.0045 | T16: -0.0095 | U16: -0.0209 | V16: -0.0181 | W16: -0.0131 | X16: -0.014 | Y16: -0.0038 | Z16: -0.0129 | AA16: -0.0177 | AB16: -0.013 | AC16: -0.0125 | AD16: -0.0051 | AE16: -0.0301 | AF16: -0.0128 | AG16: -0.0073 | AH16: -0.0194 | AI16: 0.0034 | AJ16: 0.0018 | AX16: -0.0086 | AY16: -0.005 | BA16: -0.0024
A17: 20260224 | B17: 0.0005 | C17: 0.0026 | D17: -0.0071 | E17: 0.0353 | F17: 0.0361 | G17: -0.0112 | H17: 0.0318 | I17: -0.0077 | J17: -0.0338 | K17: 0.0205 | L17: 0.0306 | M17: 0.0169 | N17: 0.0246 | O17: -0.0017 | P17: 0.0044 | Q17: 0.0315 | R17: -0.0026 | S17: 0 | T17: 0.0048 | U17: 0.0437 | V17: 0.0051 | W17: 0.02 | X17: 0 | Y17: 0.0057 | Z17: -0.0026 | AA17: 0 | AB17: -0.0048 | AC17: 0.0195 | AD17: 0.0087 | AE17: 0.0146 | AF17: -0.0292 | AG17: -0.0474 | AH17: -0.0306 | AI17: 0.0121 | AJ17: 0.0036 | AX17: 0.0122 | AY17: 0.0042 | BA17: 0.0117
A18: 20260225 | B18: 0.0095 | C18: 0.0013 | D18: 0.0009 | E18: 0.016 | F18: 0.0053 | G18: 0.0057 | H18: 0.0236 | I18: 0.0052 | J18: 0.0039 | K18: 0.0427 | L18: 0.0385 | M18: 0.0013 | N18: 0.008 | O18: 0.006 | P18: -0.0025 | Q18: -0.0025 | R18: -0.0039 | S18: 0.0273 | T18: 0.0127 | U18: 0.0063 | V18: 0.0156 | W18: 0.0033 | X18: 0.0085 | Y18: 0.0028 | Z18: 0.0026 | AA18: 0.0154 | AB18: 0.0072 | AC18: 0.0067 | AD18: 0.0007 | AE18: 0.0117 | AF18: 0.0033 | AG18: -0.0058 | AH18: -0.0043 | AI18: 0.0167 | AJ18: 0.0084 | AX18: 0.0045 | AY18: 0.0094 | BA18: 0.0046
... A20: 20260227 | B20: 0 | C20: -0.0019 | D20: 0.0018 | E20: 0.0063 | F20: -0.0132 | G20: 0.0019 | H20: 0.0124 | I20: 0.0052 | J20: 0.0065 | K20: 0.0245 | L20: 0.0348 | M20: 0.0116 | N20: 0.0103 | O20: 0.0026 | P20: -0.0013 | Q20: 0.0282 | R20: 0.0013 | S20: 0.0026 | T20: 0.0157 | U20: -0.0025 | V20: 0.0041 | W20: 0.0241 | X20: 0.0057 | Y20: 0 | Z20: -0.0026 | AA20: -0.0051 | AB20: 0.0012 | AC20: 0.0273 | AD20: 0.0029 | AE20: 0.0161 | AF20: 0.0244 | AG20: 0.0026 | AH20: 0.0095 | AI20: -0.0013 | AJ20: -0.0082 | AX20: 0.0028 | AY20: 0.0018 | BA20: 0.0023
A21: 202603汇总 | B21: =SUM(B22:B43) -> 0.0318 | C21: =SUM(C22:C43) -> -0.1472 | D21: =SUM(D22:D43) -> -0.1631 | E21: =SUM(E22:E43) -> -0.0992 | F21: =SUM(F22:F43) -> -0.1444 | G21: =SUM(G22:G43) -> -0.0628 | H21: =SUM(H22:H43) -> -0.0501 | I21: =SUM(I22:I43) -> -0.0416 | ... AV21: =SUM(AV22:AV43) -> -0.042 | AW21: -0.1026 | AX21: =SUM(AX22:AX43) -> -0.0696 | AY21: =SUM(AY22:AY43) -> -0.0916 | AZ21: =SUM(AZ22:AZ43) -> -0.0314 | BA21: =SUM(BA22:BA43) -> -0.0743 | BD21: =AX21-AS21 -> 0.0428
A22: 20260302 | B22: 0.0084 | C22: -0.0194 | D22: -0.0223 | E22: 0.0198 | F22: -0.0059 | G22: -0.019 | H22: 0.021 | I22: -0.009 | J22: -0.031 | K22: 0.0012 | L22: 0.0365 | M22: 0.022 | N22: -0.0008 | O22: -0.0128 | P22: -0.0177 | Q22: 0.0341 | R22: 0.0052 | S22: -0.0227 | T22: -0.0062 | U22: 0.0172 | V22: 0.0127 | W22: 0.0078 | X22: -0.0169 | Y22: -0.0104 | Z22: -0.0211 | AA22: -0.0257 | AB22: -0.0243 | AC22: 0.0147 | AD22: -0.0036 | AE22: 0 | AF22: -0.0292 | AG22: -0.0323 | AH22: -0.0369 | AI22: 0.0245 | AJ22: -0.0178 | AK22: 0.0083 | AL22: 0.0047 | AM22: -0.002 | AN22: -0.0049 | AO22: -0.0399 | AP22: 0.0023 | AQ22: 0.0038 | AR22: 0 | AS22: -0.0098 | AT22: -0.0321 | AU22: -0.004 | AV22: -0.0168 | AX22: -0.0036 | AY22: -0.0211 | BA22: -0.0194 | BD22: =AX22-AS22 -> 0.0062
A23: 20260303 | B23: 0.0084 | C23: -0.0423 | D23: -0.0492 | E23: -0.0326 | F23: -0.0361 | G23: -0.0019 | H23: -0.0017 | I23: -0.0039 | J23: -0.016 | K23: -0.0328 | L23: -0.0544 | M23: 0.0194 | N23: -0.029 | O23: -0.0087 | P23: -0.0277 | Q23: 0.0322 | R23: 0.009 | S23: -0.0292 | T23: -0.0078 | U23: -0.0419 | V23: -0.0183 | W23: -0.0062 | X23: -0.0259 | Y23: -0.0106 | Z23: -0.0135 | AA23: -0.029 | AB23: -0.0299 | AC23: -0.0099 | AD23: -0.0233 | AE23: -0.0229 | AF23: -0.0357 | AG23: -0.0463 | AH23: -0.0543 | AI23: -0.0686 | AJ23: -0.058 | AK23: -0.0319 | AL23: -0.0143 | AM23: -0.0307 | AN23: -0.0257 | AO23: -0.0411 | AP23: -0.0106 | AQ23: -0.0154 | AR23: -0.0435 | AS23: -0.0395 | AT23: -0.0266 | AU23: -0.0231 | AV23: -0.033 | AX23: -0.013 | AY23: -0.033 | BA23: -0.0186 | BD23: =AX23-AS23+BD22 -> 0.0327
A24: 20260304 | B24: 0.0249 | C24: -0.0083 | D24: -0.0067 | E24: -0.0179 | F24: -0.0095 | G24: -0.0252 | H24: 0.0309 | I24: -0.0078 | J24: -0.0095 | K24: -0.0093 | L24: -0.0072 | M24: -0.0187 | N24: -0.0065 | O24: -0.0253 | P24: -0.0053 | Q24: -0.0218 | R24: -0.0115 | S24: -0.0089 | T24: 0.0047 | U24: 0.0333 | V24: -0.0059 | W24: 0.0109 | X24: -0.0147 | Y24: -0.0116 | Z24: -0.0137 | AA24: -0.0109 | AB24: -0.009 | AC24: 0.0073 | AD24: -0.0082 | AE24: 0 | AF24: -0.0127 | AG24: -0.0086 | AH24: -0.0047 | AI24: 0.0122 | AJ24: 0 | AK24: -0.0076 | AL24: -0.0098 | AM24: -0.0075 | AN24: -0.0141 | AO24: -0.0026 | AP24: -0.0133 | AQ24: -0.0114 | AR24: -0.0039 | AS24: -0.0059 | AT24: -0.0065 | AU24: -0.0022 | AV24: -0.0018 | AX24: -0.0096 | AY24: -0.0141 | BA24: -0.0064 | BD24: =AX24-AS24+BD23 -> 0.029
A25: 20260305 | B25: -0.0195 | C25: 0.0139 | D25: 0.0174 | E25: 0.0118 | F25: 0.0232 | G25: 0.002 | H25: -0.0425 | I25: -0.004 | J25: -0.0068 | K25: 0.0012 | L25: -0.0081 | M25: -0.0039 | N25: 0.0171 | O25: 0.0018 | P25: 0.0113 | Q25: -0.0024 | R25: 0.0103 | S25: 0.0062 | T25: -0.0109 | U25: 0.0413 | V25: 0.0087 | W25: 0.0124 | X25: 0 | Y25: 0.002 | Z25: 0.0055 | AA25: 0.0055 | AB25: 0.0078 | AC25: 0.0163 | AD25: 0.006 | AE25: 0.0135 | AF25: 0.0047 | AG25: 0.0151 | AH25: 0.017 | AI25: 0.0073 | AJ25: 0.0173 | AK25: 0.0204 | AL25: 0.0064 | AM25: 0.0123 | AN25: 0.0166 | AO25: 0.0112 | AP25: 0.0048 | AQ25: 0.0098 | AR25: 0.0073 | AS25: 0.0095 | AT25: 0.0133 | AU25: 0.0002 | AV25: 0.0145 | AX25: 0.0032 | AY25: 0.0092 | BA25: 0.0076 | BD25: =AX25-AS25+BD24 -> 0.0227
A26: 20260306 | B26: 0.0315 | C26: 0.0089 | D26: 0.0057 | E26: 0.0191 | F26: 0.0116 | G26: 0.0139 | H26: 0.0313 | I26: 0.0225 | J26: 0.0151 | K26: 0.005 | L26: -0.0202 | M26: -0.0018 | N26: 0.0168 | O26: 0.0125 | P26: 0.0066 | Q26: -0.012 | R26: 0.0013 | S26: 0.0103 | T26: 0.0394 | U26: 0.0039 | V26: 0.0091 | W26: 0.0145 | X26: 0.024 | Y26: 0.0127 | Z26: 0.0248 | AA26: 0.0273 | AB26: 0.0309 | AC26: 0.0107 | AD26: 0.006 | AE26: 0.0018 | AF26: 0.0198 | AG26: 0.0014 | AH26: 0.0056 | AI26: 0.0099 | AJ26: 0 | AK26: -0.005 | AL26: 0.0038 | AM26: 0.0059 | AN26: 0.0038 | AO26: 0.0001 | AP26: 0.0014 | AQ26: 0.0027 | AR26: 0.0062 | AS26: 0.0095 | AT26: 0.0351 | AU26: 0.0039 | AV26: 0.0124 | AX26: 0.0143 | AY26: 0.0168 | BA26: 0.018 | BD26: =AX26-AS26+BD25 -> 0.0275
A27: 20260309 | B27: 0.0499 | C27: -0.019 | D27: -0.0085 | E27: -0.0156 | F27: -0.0311 | G27: -0.0098 | H27: -0.0042 | I27: -0.0026 | J27: -0.0244 | K27: -0.0068 | L27: -0.0097 | M27: 0.0073 | N27: -0.0102 | O27: -0.0168 | P27: -0.019 | Q27: 0.0315 | R27: -0.0077 | S27: -0.0169 | T27: -0.0015 | U27: 0.0111 | V27: 0.0068 | W27: 0.0136 | X27: -0.0146 | Y27: -0.0048 | Z27: -0.0134 | AA27: -0.008 | AB27: -0.0137 | AC27: 0.0132 | AD27: -0.0134 | AE27: 0.0195 | AF27: 0.0149 | AG27: -0.0007 | AH27: 0 | AI27: -0.0197 | AJ27: -0.0202 | AK27: -0.0231 | AL27: -0.0067 | AM27: -0.0074 | AN27: -0.0064 | AO27: -0.0232 | AP27: -0.0099 | AQ27: -0.0097 | AR27: -0.0097 | AS27: -0.0055 | AT27: -0.0087 | AU27: -0.0043 | AV27: -0.0062 | AX27: -0.0086 | AY27: -0.0102 | BA27: -0.0055 | BD27: =AX27-AS27+BD26 -> 0.0244
A28: 20260310 | B28: -0.0237 | C28: 0.0243 | D28: 0.0209 | E28: -0.0063 | F28: 0.0355 | G28: 0.0059 | H28: -0.0034 | I28: 0.0013 | J28: 0.0139 | K28: -0.0056 | L28: 0.0097 | M28: -0.0118 | N28: 0.019 | O28: 0.0072 | P28: 0.022 | Q28: -0.0329 | R28: 0.0013 | S28: 0.0103 | T28: -0.0015 | U28: 0.0071 | V28: 0.0192 | W28: 0.0015 | X28: 0.0148 | Y28: 0.0097 | Z28: 0.0191 | AA28: 0.0214 | AB28: 0.0291 | AC28: -0.0009 | AD28: 0.0143 | AE28: 0.0113 | AF28: 0.0079 | AG28: 0.0149 | AH28: 0.0074 | AI28: 0.0121 | AJ28: 0.0264 | AK28: 0.0481 | AL28: 0.0065 | AM28: 0.0204 | AN28: 0.0304 | AO28: 0.0194 | AP28: 0.0064 | AQ28: 0.0128 | AR28: 0.0158 | AS28: 0.0178 | AT28: 0.0264 | AU28: 0.0122 | AV28: 0.0163 | AX28: 0.0095 | AY28: 0.0187 | BA28: 0.0173 | BD28: =AX28-AS28+BD27 -> 0.0161
A29: 20260311 | B29: 0.0298 | C29: -0.0014 | D29: -0.0047 | E29: 0.0245 | F29: -0.0109 | G29: -0.0039 | H29: 0.0204 | I29: 0.0052 | J29: -0.0082 | K29: -0.005 | L29: -0.0035 | M29: 0.0131 | N29: 0.021 | O29: 0.0027 | P29: 0.002 | Q29: 0.0276 | R29: 0.009 | S29: 0.0041 | T29: 0.0152 | U29: -0.0043 | V29: 0.0408 | W29: 0.0245 | X29: 0.0029 | Y29: -0.001 | Z29: -0.0027 | AA29: -0.0052 | AB29: -0.0074 | AC29: 0.0252 | AD29: 0.0097 | AE29: 0.0155 | AF29: -0.0078 | AG29: -0.007 | AH29: -0.0073 | AI29: -0.0146 | AJ29: -0.0113 | AK29: 0.0041 | AL29: 0.0025 | AM29: 0.0078 | AN29: 0.0131 | AO29: 0.0041 | AP29: 0.0012 | AQ29: 0.0064 | AR29: -0.0008 | AS29: 0.0016 | AT29: -0.0081 | AU29: 0.0005 | AV29: 0.0078 | AX29: 0.0005 | AY29: -0.0023 | BA29: -0.0018 | BD29: =AX29-AS29+BD28 -> 0.015
A30: 20260312 | B30: -0.0053 | C30: -0.0102 | D30: -0.0112 | E30: -0.0021 | F30: -0.0335 | G30: 0 | H30: 0.0067 | I30: 0.0039 | J30: -0.0014 | K30: 0.0088 | L30: -0.0075 | M30: 0.0205 | N30: 0.0061 | O30: -0.0018 | P30: -0.0039 | Q30: 0.0528 | R30: 0.0089 | S30: -0.0027 | T30: 0.0135 | U30: -0.0138 | V30: -0.0021 | W30: 0.0224 | X30: -0.0087 | Y30: -0.0039 | Z30: -0.0054 | AA30: -0.0079 | AB30: -0.0087 | AC30: 0.0229 | AD30: -0.0074 | AE30: 0.0025 | AF30: -0.0079 | AG30: -0.0141 | AH30: -0.0176 | AI30: -0.0215 | AJ30: -0.014 | AK30: -0.011 | AL30: -0.001 | AM30: -0.0063 | AN30: -0.0096 | AO30: -0.0112 | AP30: -0.0046 | AQ30: -0.0036 | AR30: -0.0052 | AS30: -0.0033 | AT30: -0.0136 | AU30: -0.0145 | AV30: -0.0073 | AX30: -0.0005 | AY30: 0 | BA30: -0.0104 | BD30: =AX30-AS30+BD29 -> 0.0178
A31: 20260313 | B31: 0.0399 | C31: -0.0144 | D31: -0.0161 | E31: -0.0042 | F31: -0.0159 | G31: 0.0119 | H31: -0.0075 | I31: 0.0026 | J31: 0.0014 | K31: -0.0056 | L31: -0.0271 | M31: -0.005 | N31: 0.0114 | O31: -0.008 | P31: -0.0026 | Q31: -0.012 | R31: 0.0025 | S31: 0 | T31: -0.0059 | U31: -0.0279 | V31: -0.0123 | W31: -0.0205 | X31: -0.0059 | Y31: -0.0019 | Z31: -0.0081 | AA31: -0.0053 | AB31: -0.0075 | AC31: -0.0216 | AD31: -0.0067 | AE31: -0.0161 | AF31: -0.0261 | AG31: -0.0136 | AH31: -0.0169 | AI31: -0.0295 | AJ31: -0.0071 | AK31: -0.0087 | AL31: -0.0081 | AM31: -0.0065 | AN31: -0.0022 | AO31: -0.0103 | AP31: -0.005 | AQ31: -0.0039 | AR31: -0.0143 | AS31: -0.0146 | AT31: 0.0006 | AU31: -0.0126 | AV31: -0.0005 | AX31: -0.0046 | AY31: -0.0045 | BA31: -0.0044 | BD31: =AX31-AS31+BD30 -> 0.0278
A32: 20260316 | B32: -0.0254 | C32: -0.0049 | D32: -0.001 | E32: -0.0334 | F32: -0.0197 | G32: 0.0137 | H32: 0.0042 | I32: 0.0115 | J32: 0.0055 | K32: -0.032 | L32: -0.0306 | M32: -0.0086 | N32: -0.03 | O32: -0.0054 | P32: -0.0059 | Q32: -0.0235 | R32: 0.0025 | S32: 0.0061 | T32: 0.006 | U32: -0.0248 | V32: 0.0004 | W32: -0.0239 | X32: 0.003 | Y32: 0.0068 | Z32: 0.0027 | AA32: 0.0053 | AB32: 0.0113 | AC32: -0.0271 | AD32: 0.0104 | AE32: -0.0249 | AF32: -0.0023 | AG32: -0.0014 | AH32: 0.0077 | AI32: 0.0007 | AJ32: 0.0214 | AK32: 0.015 | AL32: -0.0026 | AM32: 0.0019 | AN32: 0.0141 | AO32: -0.0035 | AP32: -0.0009 | AQ32: 0.0005 | AR32: -0.0066 | AS32: -0.0004 | AT32: 0.0021 | AU32: -0.001 | AV32: 0.005 | AX32: 0.0003 | AY32: 0.0106 | BA32: 0.0066 | BD32: =AX32-AS32+BD31 -> 0.0285
A33: 20260317 | B33: -0.0053 | C33: -0.014 | D33: -0.0173 | E33: -0.027 | F33: -0.0047 | G33: -0.0019 | H33: -0.0341 | I33: -0.0025 | J33: -0.0014 | K33: -0.0032 | L33: -0.0165 | M33: -0.0078 | N33: -0.0147 | O33: 0.0108 | P33: -0.0112 | Q33: -0.0217 | R33: 0.0088 | S33: 0.0034 | T33: -0.0192 | U33: -0.031 | V33: -0.0351 | W33: -0.0074 | X33: 0 | Y33: 0.001 | Z33: 0.0054 | AA33: 0 | AB33: 0.0062 | AC33: -0.0061 | AD33: -0.0066 | AE33: -0.0176 | AF33: -0.0129 | AG33: -0.0058 | AH33: -0.0114 | AI33: -0.0276 | AJ33: -0.0273 | AK33: -0.041 | AL33: -0.0085 | AM33: -0.0187 | AN33: -0.0229 | AO33: -0.0185 | AP33: 0.0032 | AQ33: -0.0073 | AR33: -0.0207 | AS33: -0.0233 | AT33: -0.0228 | AU33: -0.0197 | AV33: -0.0075 | AX33: -0.0061 | AY33: -0.0084 | BA33: -0.0161 | BD33: =AX33-AS33+BD32 -> 0.0457
A34: 20260318 | B34: 0.0004 | C34: 0.0021 | D34: 0.0059 | E34: -0.0022 | F34: 0.0024 | G34: -0.0097 | H34: -0.0146 | I34: -0.0076 | J34: -0.0069 | K34: -0.0072 | L34: -0.0077 | M34: -0.0039 | N34: -0.0016 | O34: -0.0036 | P34: 0.0067 | Q34: -0.0071 | R34: -0.0025 | S34: -0.0108 | T34: 0 | U34: 0.0183 | V34: 0.0089 | W34: 0 | X34: -0.0029 | Y34: -0.0029 | Z34: -0.0027 | AA34: 0.0053 | AB34: 0.005 | AC34: 0.0026 | AD34: -0.0059 | AE34: 0.0045 | AF34: 0.0154 | AG34: 0.0087 | AH34: 0.0106 | AI34: 0.0174 | AJ34: 0.0222 | AK34: 0.041 | AL34: 0.0032 | AM34: 0.0105 | AN34: 0.0202 | AO34: 0.0069 | AP34: -0.0007 | AQ34: 0.0045 | AR34: 0.01 | AS34: 0.0096 | AT34: 0.0177 | AU34: 0.0142 | AV34: 0.0053 | AX34: 0.0001 | AY34: 0.0091 | BA34: 0.0151 | BD34: =AX34-AS34+BD33 -> 0.0362
... A36: 20260320 | B36: -0.0174 | C36: -0.0166 | D36: -0.02 | E36: -0.0105 | F36: -0.0129 | G36: -0.0079 | H36: -0.0162 | I36: -0.0078 | J36: -0.0071 | K36: -0.0211 | L36: -0.0139 | M36: -0.0027 | N36: -0.0144 | O36: -0.0163 | P36: -0.0129 | Q36: 0.0031 | R36: -0.0025 | S36: -0.0175 | T36: -0.0123 | U36: -0.0191 | V36: 0.0271 | W36: 0.0015 | X36: -0.0181 | Y36: 0.001 | Z36: -0.0082 | AA36: -0.0135 | AB36: -0.0125 | AC36: 0.0018 | AD36: -0.0076 | AE36: 0.0299 | AF36: -0.038 | AG36: -0.0298 | AH36: -0.03 | AI36: -0.0279 | AJ36: -0.017 | AK36: 0.0133 | AL36: -0.0124 | AM36: -0.0025 | AN36: 0.013 | AO36: -0.0101 | AP36: -0.0111 | AQ36: -0.0035 | AR36: -0.0149 | AS36: -0.0159 | AT36: -0.0373 | AU36: -0.01 | AV36: -0.0138 | AX36: -0.01 | AY36: -0.0207 | BA36: -0.0232 | BD36: =AX36-AS36+BD35 -> 0.0481
